Workbook

Sheet Summary M1 Digital
A1: BN - P&L | B1: Forecast | C1: Forecast | D1: Forecast | E1: Forecast | F1: Forecast | G1: Forecast | H1: Forecast | I1: Forecast | J1: Forecast | K1: Forecast
B2: 45992 | C2: 46023 | D2: 46054 | E2: 46082 | F2: 46113 | G2: 46143 | H2: 46174 | I2: 46204 | J2: 46235 | K2: 46266 | L2: FY26
A3: App
A4: Turnover
A5: CoS
A6: GP
A7: GP%
A9: Facebook
A10: Turnover | B10: ='Revenue - Digital'!D6 -> 6666.6667 | C10: ='Revenue - Digital'!E6 -> 8750 | D10: ='Revenue - Digital'!F6 -> 8750 | E10: ='Revenue - Digital'!G6 -> 8750 | F10: ='Revenue - Digital'!H6 -> 8750 | G10: ='Revenue - Digital'!I6 -> 8750 | H10: ='Revenue - Digital'!J6 -> 8750 | I10: ='Revenue - Digital'!K6 -> 8750 | ... K10: ='Revenue - Digital'!M6 -> 8750
A11: CoS - Staff costs | B11: =-SUMIF('M1 Staff costs'!$A:$A,'Summary M1 Digital'!$A$9,'M1 Staff costs'!I:I) -> -2831.4 | C11: =-SUMIF('M1 Staff costs'!$A:$A,'Summary M1 Digital'!$A$9,'M1 Staff costs'!J:J) -> -3425.4 | D11: =-SUMIF('M1 Staff costs'!$A:$A,'Summary M1 Digital'!$A$9,'M1 Staff costs'!K:K) -> -2831.4 | E11: =-SUMIF('M1 Staff costs'!$A:$A,'Summary M1 Digital'!$A$9,'M1 Staff costs'!L:L) -> -2587.9 | F11: =-SUMIF('M1 Staff costs'!$A:$A,'Summary M1 Digital'!$A$9,'M1 Staff costs'!M:M) -> -2439.4 | G11: =-SUMIF('M1 Staff costs'!$A:$A,'Summary M1 Digital'!$A$9,'M1 Staff costs'!N:N) -> -2439.4 | H11: =-SUMIF('M1 Staff costs'!$A:$A,'Summary M1 Digital'!$A$9,'M1 Staff costs'!O:O) -> -2439.4 | I11: =-SUMIF('M1 Staff costs'!$A:$A,'Summary M1 Digital'!$A$9,'M1 Staff costs'!P:P) -> -2439.4 | J11: =-SUMIF('M1 Staff costs'!$A:$A,'Summary M1 Digital'!$A$9,'M1 Staff costs'!Q:Q) -> -2439.4 | K11: =-SUMIF('M1 Staff costs'!$A:$A,'Summary M1 Digital'!$A$9,'M1 Staff costs'!R:R) -> -2439.4
A12: CoS - Freelancers | B12: =-SUMIF('M1 Freelancers'!$A:$A,'M1 Freelancers'!$A$5,'M1 Freelancers'!E:E) -> -300 | C12: =-SUMIF('M1 Freelancers'!$A:$A,'M1 Freelancers'!$A$5,'M1 Freelancers'!F:F) -> -300 | D12: =-SUMIF('M1 Freelancers'!$A:$A,'M1 Freelancers'!$A$5,'M1 Freelancers'!G:G) -> -300 | E12: =-SUMIF('M1 Freelancers'!$A:$A,'M1 Freelancers'!$A$5,'M1 Freelancers'!H:H) -> -300 | F12: =-SUMIF('M1 Freelancers'!$A:$A,'M1 Freelancers'!$A$5,'M1 Freelancers'!I:I) -> -300 | G12: =-SUMIF('M1 Freelancers'!$A:$A,'M1 Freelancers'!$A$5,'M1 Freelancers'!J:J) -> -300 | H12: =-SUMIF('M1 Freelancers'!$A:$A,'M1 Freelancers'!$A$5,'M1 Freelancers'!K:K) -> -300 | I12: =-SUMIF('M1 Freelancers'!$A:$A,'M1 Freelancers'!$A$5,'M1 Freelancers'!L:L) -> -300 | J12: =-SUMIF('M1 Freelancers'!$A:$A,'M1 Freelancers'!$A$5,'M1 Freelancers'!M:M) -> -300 | K12: =-SUMIF('M1 Freelancers'!$A:$A,'M1 Freelancers'!$A$5,'M1 Freelancers'!N:N) -> -300
A13: GP | B13: =SUM(B10:B12) -> 3535.2667 | C13: =SUM(C10:C12) -> 5024.6 | D13: =SUM(D10:D12) -> 5618.6 | E13: =SUM(E10:E12) -> 5862.1 | F13: =SUM(F10:F12) -> 6010.6 | G13: =SUM(G10:G12) -> 6010.6 | H13: =SUM(H10:H12) -> 6010.6 | I13: =SUM(I10:I12) -> 6010.6 | ... K13: =SUM(K10:K12) -> 6010.6
A14: Other Op costs | B14: =-SUMIF(OH!$A:$A,'Summary M1 Digital'!$A$9,OH!E:E) -> -1029.2 | C14: =-SUMIF(OH!$A:$A,'Summary M1 Digital'!$A$9,OH!F:F) -> -1029.2 | D14: =-SUMIF(OH!$A:$A,'Summary M1 Digital'!$A$9,OH!G:G) -> -862.53333 | E14: =-SUMIF(OH!$A:$A,'Summary M1 Digital'!$A$9,OH!H:H) -> -862.53333 | F14: =-SUMIF(OH!$A:$A,'Summary M1 Digital'!$A$9,OH!I:I) -> -862.53333 | G14: =-SUMIF(OH!$A:$A,'Summary M1 Digital'!$A$9,OH!J:J) -> -862.53333 | H14: =-SUMIF(OH!$A:$A,'Summary M1 Digital'!$A$9,OH!K:K) -> -862.53333 | I14: =-SUMIF(OH!$A:$A,'Summary M1 Digital'!$A$9,OH!L:L) -> -862.53333 | J14: =-SUMIF(OH!$A:$A,'Summary M1 Digital'!$A$9,OH!M:M) -> -862.53333 | K14: =-SUMIF(OH!$A:$A,'Summary M1 Digital'!$A$9,OH!N:N) -> -862.53333
A15: Contribution | B15: =SUM(B13:B14) -> 2506.0667 | C15: =SUM(C13:C14) -> 3995.4 | D15: =SUM(D13:D14) -> 4756.0667 | E15: =SUM(E13:E14) -> 4999.5667 | F15: =SUM(F13:F14) -> 5148.0667 | G15: =SUM(G13:G14) -> 5148.0667 | H15: =SUM(H13:H14) -> 5148.0667 | I15: =SUM(I13:I14) -> 5148.0667 | ... K15: =SUM(K13:K14) -> 5148.0667
A18: Magazine
A19: Turnover
A20: CoS - Staff costs
A21: CoS - Freelancers
A22: GP
A23: Other Op costs
A24: Contribution
A26: Website
A27: Turnover | B27: ='Revenue - Digital'!D10 -> 18900 | C27: ='Revenue - Digital'!E10 -> 3000 | D27: ='Revenue - Digital'!F10 -> 3000 | E27: ='Revenue - Digital'!G10 -> 3000 | F27: ='Revenue - Digital'!H10 -> 3000 | G27: ='Revenue - Digital'!I10 -> 3000 | H27: ='Revenue - Digital'!J10 -> 3000 | I27: ='Revenue - Digital'!K10 -> 3000 | ... K27: ='Revenue - Digital'!M10 -> 3000
A28: CoS - Staff costs | B28: =-SUMIF('M1 Staff costs'!$A:$A,$A$26,'M1 Staff costs'!I:I) -> -2481.831 | C28: =-SUMIF('M1 Staff costs'!$A:$A,$A$26,'M1 Staff costs'!J:J) -> -2481.831 | D28: =-SUMIF('M1 Staff costs'!$A:$A,$A$26,'M1 Staff costs'!K:K) -> -1763.1863 | E28: =-SUMIF('M1 Staff costs'!$A:$A,$A$26,'M1 Staff costs'!L:L) -> 0 | F28: =-SUMIF('M1 Staff costs'!$A:$A,$A$26,'M1 Staff costs'!M:M) -> 0 | G28: =-SUMIF('M1 Staff costs'!$A:$A,$A$26,'M1 Staff costs'!N:N) -> 0 | H28: =-SUMIF('M1 Staff costs'!$A:$A,$A$26,'M1 Staff costs'!O:O) -> 0 | I28: =-SUMIF('M1 Staff costs'!$A:$A,$A$26,'M1 Staff costs'!P:P) -> 0 | J28: =-SUMIF('M1 Staff costs'!$A:$A,$A$26,'M1 Staff costs'!Q:Q) -> 0 | K28: =-SUMIF('M1 Staff costs'!$A:$A,$A$26,'M1 Staff costs'!R:R) -> 0
A29: CoS - Freelancers
A30: GP | B30: =SUM(B27:B29) -> 16418.169 | C30: =SUM(C27:C29) -> 518.169 | D30: =SUM(D27:D29) -> 1236.8137 | E30: =SUM(E27:E29) -> 3000 | F30: =SUM(F27:F29) -> 3000 | G30: =SUM(G27:G29) -> 3000 | H30: =SUM(H27:H29) -> 3000 | I30: =SUM(I27:I29) -> 3000 | ... K30: =SUM(K27:K29) -> 3000
A31: Other Op costs | B31: =-SUMIF(OH!$A:$A,$A$26,OH!E:E) -> 0 | C31: =-SUMIF(OH!$A:$A,$A$26,OH!F:F) -> 0 | D31: =-SUMIF(OH!$A:$A,$A$26,OH!G:G) -> 0 | E31: =-SUMIF(OH!$A:$A,$A$26,OH!H:H) -> 0 | F31: =-SUMIF(OH!$A:$A,$A$26,OH!I:I) -> 0 | G31: =-SUMIF(OH!$A:$A,$A$26,OH!J:J) -> 0 | H31: =-SUMIF(OH!$A:$A,$A$26,OH!K:K) -> 0 | I31: =-SUMIF(OH!$A:$A,$A$26,OH!L:L) -> 0 | J31: =-SUMIF(OH!$A:$A,$A$26,OH!M:M) -> 0 | K31: =-SUMIF(OH!$A:$A,$A$26,OH!N:N) -> 0
A32: Contribution | B32: =SUM(B30:B31) -> 16418.169 | C32: =SUM(C30:C31) -> 518.169 | D32: =SUM(D30:D31) -> 1236.8137 | E32: =SUM(E30:E31) -> 3000 | F32: =SUM(F30:F31) -> 3000 | G32: =SUM(G30:G31) -> 3000 | H32: =SUM(H30:H31) -> 3000 | I32: =SUM(I30:I31) -> 3000 | ... K32: =SUM(K30:K31) -> 3000
A35: Youtube
A36: Turnover | B36: ='Revenue - Digital'!D18 -> 1000 | C36: ='Revenue - Digital'!E18 -> 1000 | D36: ='Revenue - Digital'!F18 -> 1000 | E36: ='Revenue - Digital'!G18 -> 1000 | F36: ='Revenue - Digital'!H18 -> 1000 | G36: ='Revenue - Digital'!I18 -> 1000 | H36: ='Revenue - Digital'!J18 -> 1000 | I36: ='Revenue - Digital'!K18 -> 1000 | ... K36: ='Revenue - Digital'!M18 -> 1000
A37: CoS - Staff costs | B37: =-SUMIF('M1 Staff costs'!$A:$A,$A$35,'M1 Staff costs'!I:I) -> -4118.4 | C37: =-SUMIF('M1 Staff costs'!$A:$A,$A$35,'M1 Staff costs'!J:J) -> -4712.4 | D37: =-SUMIF('M1 Staff costs'!$A:$A,$A$35,'M1 Staff costs'!K:K) -> -4118.4 | E37: =-SUMIF('M1 Staff costs'!$A:$A,$A$35,'M1 Staff costs'!L:L) -> -3969.9 | F37: =-SUMIF('M1 Staff costs'!$A:$A,$A$35,'M1 Staff costs'!M:M) -> -3821.4 | G37: =-SUMIF('M1 Staff costs'!$A:$A,$A$35,'M1 Staff costs'!N:N) -> -3821.4 | H37: =-SUMIF('M1 Staff costs'!$A:$A,$A$35,'M1 Staff costs'!O:O) -> -3821.4 | I37: =-SUMIF('M1 Staff costs'!$A:$A,$A$35,'M1 Staff costs'!P:P) -> -3821.4 | J37: =-SUMIF('M1 Staff costs'!$A:$A,$A$35,'M1 Staff costs'!Q:Q) -> -3821.4 | K37: =-SUMIF('M1 Staff costs'!$A:$A,$A$35,'M1 Staff costs'!R:R) -> -3821.4
A38: CoS - Freelancers | B38: =-SUMIF('M1 Freelancers'!$A:$A,'M1 Freelancers'!$A$8,'M1 Freelancers'!E:E) -> -133.33333 | C38: =-SUMIF('M1 Freelancers'!$A:$A,'M1 Freelancers'!$A$8,'M1 Freelancers'!F:F) -> -133.33333 | D38: =-SUMIF('M1 Freelancers'!$A:$A,'M1 Freelancers'!$A$8,'M1 Freelancers'!G:G) -> -133.33333 | E38: =-SUMIF('M1 Freelancers'!$A:$A,'M1 Freelancers'!$A$8,'M1 Freelancers'!H:H) -> -133.33333 | F38: =-SUMIF('M1 Freelancers'!$A:$A,'M1 Freelancers'!$A$8,'M1 Freelancers'!I:I) -> -133.33333 | G38: =-SUMIF('M1 Freelancers'!$A:$A,'M1 Freelancers'!$A$8,'M1 Freelancers'!J:J) -> -133.33333 | H38: =-SUMIF('M1 Freelancers'!$A:$A,'M1 Freelancers'!$A$8,'M1 Freelancers'!K:K) -> -133.33333 | I38: =-SUMIF('M1 Freelancers'!$A:$A,'M1 Freelancers'!$A$8,'M1 Freelancers'!L:L) -> -133.33333 | J38: =-SUMIF('M1 Freelancers'!$A:$A,'M1 Freelancers'!$A$8,'M1 Freelancers'!M:M) -> -133.33333 | K38: =-SUMIF('M1 Freelancers'!$A:$A,'M1 Freelancers'!$A$8,'M1 Freelancers'!N:N) -> -133.33333
A39: GP | B39: =SUM(B36:B38) -> -3251.7333 | C39: =SUM(C36:C38) -> -3845.7333 | D39: =SUM(D36:D38) -> -3251.7333 | E39: =SUM(E36:E38) -> -3103.2333 | F39: =SUM(F36:F38) -> -2954.7333 | G39: =SUM(G36:G38) -> -2954.7333 | H39: =SUM(H36:H38) -> -2954.7333 | I39: =SUM(I36:I38) -> -2954.7333 | ... K39: =SUM(K36:K38) -> -2954.7333
A40: Other Op costs | B40: =-SUMIF(OH!$A:$A,$A$35,OH!E:E) -> -1029.2 | C40: =-SUMIF(OH!$A:$A,$A$35,OH!F:F) -> -1029.2 | D40: =-SUMIF(OH!$A:$A,$A$35,OH!G:G) -> -862.53333 | E40: =-SUMIF(OH!$A:$A,$A$35,OH!H:H) -> -862.53333 | F40: =-SUMIF(OH!$A:$A,$A$35,OH!I:I) -> -862.53333 | G40: =-SUMIF(OH!$A:$A,$A$35,OH!J:J) -> -862.53333 | H40: =-SUMIF(OH!$A:$A,$A$35,OH!K:K) -> -862.53333 | I40: =-SUMIF(OH!$A:$A,$A$35,OH!L:L) -> -862.53333 | J40: =-SUMIF(OH!$A:$A,$A$35,OH!M:M) -> -862.53333 | K40: =-SUMIF(OH!$A:$A,$A$35,OH!N:N) -> -862.53333
A41: Contribution | B41: =SUM(B39:B40) -> -4280.9333 | C41: =SUM(C39:C40) -> -4874.9333 | D41: =SUM(D39:D40) -> -4114.2667 | E41: =SUM(E39:E40) -> -3965.7667 | F41: =SUM(F39:F40) -> -3817.2667 | G41: =SUM(G39:G40) -> -3817.2667 | H41: =SUM(H39:H40) -> -3817.2667 | I41: =SUM(I39:I40) -> -3817.2667 | ... K41: =SUM(K39:K40) -> -3817.2667
A44: Instagram
A45: Turnover | B45: ='Revenue - Digital'!D24 -> 0 | C45: ='Revenue - Digital'!E24 -> 2083.3333 | D45: ='Revenue - Digital'!F24 -> 2083.3333 | E45: ='Revenue - Digital'!G24 -> 2083.3333 | F45: ='Revenue - Digital'!H24 -> 2083.3333 | G45: ='Revenue - Digital'!I24 -> 2083.3333 | H45: ='Revenue - Digital'!J24 -> 2083.3333 | I45: ='Revenue - Digital'!K24 -> 2083.3333 | ... K45: ='Revenue - Digital'!M24 -> 2083.3333
A46: CoS - Staff costs | B46: =-SUMIF('M1 Staff costs'!$A:$A,$A$44,'M1 Staff costs'!I:I) -> -2343.825 | C46: =-SUMIF('M1 Staff costs'!$A:$A,$A$44,'M1 Staff costs'!J:J) -> -2937.825 | D46: =-SUMIF('M1 Staff costs'!$A:$A,$A$44,'M1 Staff costs'!K:K) -> -2343.825 | E46: =-SUMIF('M1 Staff costs'!$A:$A,$A$44,'M1 Staff costs'!L:L) -> -2100.325 | F46: =-SUMIF('M1 Staff costs'!$A:$A,$A$44,'M1 Staff costs'!M:M) -> -1951.825 | G46: =-SUMIF('M1 Staff costs'!$A:$A,$A$44,'M1 Staff costs'!N:N) -> -1951.825 | H46: =-SUMIF('M1 Staff costs'!$A:$A,$A$44,'M1 Staff costs'!O:O) -> -1951.825 | I46: =-SUMIF('M1 Staff costs'!$A:$A,$A$44,'M1 Staff costs'!P:P) -> -1951.825 | J46: =-SUMIF('M1 Staff costs'!$A:$A,$A$44,'M1 Staff costs'!Q:Q) -> -1951.825 | K46: =-SUMIF('M1 Staff costs'!$A:$A,$A$44,'M1 Staff costs'!R:R) -> -1951.825
A47: CoS - Freelancers | B47: =-SUMIF('M1 Freelancers'!$A:$A,'M1 Freelancers'!$A$6,'M1 Freelancers'!E:E) -> -300 | C47: =-SUMIF('M1 Freelancers'!$A:$A,'M1 Freelancers'!$A$6,'M1 Freelancers'!F:F) -> -300 | D47: =-SUMIF('M1 Freelancers'!$A:$A,'M1 Freelancers'!$A$6,'M1 Freelancers'!G:G) -> -300 | E47: =-SUMIF('M1 Freelancers'!$A:$A,'M1 Freelancers'!$A$6,'M1 Freelancers'!H:H) -> -300 | F47: =-SUMIF('M1 Freelancers'!$A:$A,'M1 Freelancers'!$A$6,'M1 Freelancers'!I:I) -> -300 | G47: =-SUMIF('M1 Freelancers'!$A:$A,'M1 Freelancers'!$A$6,'M1 Freelancers'!J:J) -> -300 | H47: =-SUMIF('M1 Freelancers'!$A:$A,'M1 Freelancers'!$A$6,'M1 Freelancers'!K:K) -> -300 | I47: =-SUMIF('M1 Freelancers'!$A:$A,'M1 Freelancers'!$A$6,'M1 Freelancers'!L:L) -> -300 | J47: =-SUMIF('M1 Freelancers'!$A:$A,'M1 Freelancers'!$A$6,'M1 Freelancers'!M:M) -> -300 | K47: =-SUMIF('M1 Freelancers'!$A:$A,'M1 Freelancers'!$A$6,'M1 Freelancers'!N:N) -> -300
A48: GP | B48: =SUM(B45:B47) -> -2643.825 | C48: =SUM(C45:C47) -> -1154.4917 | D48: =SUM(D45:D47) -> -560.49167 | E48: =SUM(E45:E47) -> -316.99167 | F48: =SUM(F45:F47) -> -168.49167 | G48: =SUM(G45:G47) -> -168.49167 | H48: =SUM(H45:H47) -> -168.49167 | I48: =SUM(I45:I47) -> -168.49167 | ... K48: =SUM(K45:K47) -> -168.49167
A49: Other Op costs | B49: =-SUMIF(OH!$A:$A,$A$44,OH!E:E) -> -1029.2 | C49: =-SUMIF(OH!$A:$A,$A$44,OH!F:F) -> -1029.2 | D49: =-SUMIF(OH!$A:$A,$A$44,OH!G:G) -> -862.53333 | E49: =-SUMIF(OH!$A:$A,$A$44,OH!H:H) -> -862.53333 | F49: =-SUMIF(OH!$A:$A,$A$44,OH!I:I) -> -862.53333 | G49: =-SUMIF(OH!$A:$A,$A$44,OH!J:J) -> -862.53333 | H49: =-SUMIF(OH!$A:$A,$A$44,OH!K:K) -> -862.53333 | I49: =-SUMIF(OH!$A:$A,$A$44,OH!L:L) -> -862.53333 | J49: =-SUMIF(OH!$A:$A,$A$44,OH!M:M) -> -862.53333 | K49: =-SUMIF(OH!$A:$A,$A$44,OH!N:N) -> -862.53333
A50: Contribution | B50: =SUM(B48:B49) -> -3673.025 | C50: =SUM(C48:C49) -> -2183.6917 | D50: =SUM(D48:D49) -> -1423.025 | E50: =SUM(E48:E49) -> -1179.525 | F50: =SUM(F48:F49) -> -1031.025 | G50: =SUM(G48:G49) -> -1031.025 | H50: =SUM(H48:H49) -> -1031.025 | I50: =SUM(I48:I49) -> -1031.025 | ... K50: =SUM(K48:K49) -> -1031.025
A53: TikTok
A54: Turnover | B54: 0 | C54: 0 | D54: 0 | E54: 0 | F54: 0 | G54: 0 | H54: 0 | I54: 0 | J54: 0 | K54: 0
A55: CoS - Staff costs | B55: =-SUMIF('M1 Staff costs'!$A:$A,$A$53,'M1 Staff costs'!I:I) -> -1591.425 | C55: =-SUMIF('M1 Staff costs'!$A:$A,$A$53,'M1 Staff costs'!J:J) -> -1710.225 | D55: =-SUMIF('M1 Staff costs'!$A:$A,$A$53,'M1 Staff costs'!K:K) -> -1591.425 | E55: =-SUMIF('M1 Staff costs'!$A:$A,$A$53,'M1 Staff costs'!L:L) -> -1347.925 | F55: =-SUMIF('M1 Staff costs'!$A:$A,$A$53,'M1 Staff costs'!M:M) -> -1199.425 | G55: =-SUMIF('M1 Staff costs'!$A:$A,$A$53,'M1 Staff costs'!N:N) -> -1199.425 | H55: =-SUMIF('M1 Staff costs'!$A:$A,$A$53,'M1 Staff costs'!O:O) -> -1199.425 | I55: =-SUMIF('M1 Staff costs'!$A:$A,$A$53,'M1 Staff costs'!P:P) -> -1199.425 | J55: =-SUMIF('M1 Staff costs'!$A:$A,$A$53,'M1 Staff costs'!Q:Q) -> -1199.425 | K55: =-SUMIF('M1 Staff costs'!$A:$A,$A$53,'M1 Staff costs'!R:R) -> -1199.425
A56: CoS - Freelancers | B56: =-SUMIF('M1 Freelancers'!$A:$A,'M1 Freelancers'!$A$7,'M1 Freelancers'!E:E) -> -133.33333 | C56: =-SUMIF('M1 Freelancers'!$A:$A,'M1 Freelancers'!$A$7,'M1 Freelancers'!F:F) -> -133.33333 | D56: =-SUMIF('M1 Freelancers'!$A:$A,'M1 Freelancers'!$A$7,'M1 Freelancers'!G:G) -> -133.33333 | E56: =-SUMIF('M1 Freelancers'!$A:$A,'M1 Freelancers'!$A$7,'M1 Freelancers'!H:H) -> -133.33333 | F56: =-SUMIF('M1 Freelancers'!$A:$A,'M1 Freelancers'!$A$7,'M1 Freelancers'!I:I) -> -133.33333 | G56: =-SUMIF('M1 Freelancers'!$A:$A,'M1 Freelancers'!$A$7,'M1 Freelancers'!J:J) -> -133.33333 | H56: =-SUMIF('M1 Freelancers'!$A:$A,'M1 Freelancers'!$A$7,'M1 Freelancers'!K:K) -> -133.33333 | I56: =-SUMIF('M1 Freelancers'!$A:$A,'M1 Freelancers'!$A$7,'M1 Freelancers'!L:L) -> -133.33333 | J56: =-SUMIF('M1 Freelancers'!$A:$A,'M1 Freelancers'!$A$7,'M1 Freelancers'!M:M) -> -133.33333 | K56: =-SUMIF('M1 Freelancers'!$A:$A,'M1 Freelancers'!$A$7,'M1 Freelancers'!N:N) -> -133.33333
A57: GP | B57: =SUM(B54:B56) -> -1724.7583 | C57: =SUM(C54:C56) -> -1843.5583 | D57: =SUM(D54:D56) -> -1724.7583 | E57: =SUM(E54:E56) -> -1481.2583 | F57: =SUM(F54:F56) -> -1332.7583 | G57: =SUM(G54:G56) -> -1332.7583 | H57: =SUM(H54:H56) -> -1332.7583 | I57: =SUM(I54:I56) -> -1332.7583 | ... K57: =SUM(K54:K56) -> -1332.7583
A58: Other Op costs | B58: =-SUMIF(OH!$A:$A,$A$53,OH!E:E) -> -1029.2 | C58: =-SUMIF(OH!$A:$A,$A$53,OH!F:F) -> -1029.2 | D58: =-SUMIF(OH!$A:$A,$A$53,OH!G:G) -> -862.53333 | E58: =-SUMIF(OH!$A:$A,$A$53,OH!H:H) -> -862.53333 | F58: =-SUMIF(OH!$A:$A,$A$53,OH!I:I) -> -862.53333 | G58: =-SUMIF(OH!$A:$A,$A$53,OH!J:J) -> -862.53333 | H58: =-SUMIF(OH!$A:$A,$A$53,OH!K:K) -> -862.53333 | I58: =-SUMIF(OH!$A:$A,$A$53,OH!L:L) -> -862.53333 | J58: =-SUMIF(OH!$A:$A,$A$53,OH!M:M) -> -862.53333 | K58: =-SUMIF(OH!$A:$A,$A$53,OH!N:N) -> -862.53333
A59: Contribution | B59: =SUM(B57:B58) -> -2753.9583 | C59: =SUM(C57:C58) -> -2872.7583 | D59: =SUM(D57:D58) -> -2587.2917 | E59: =SUM(E57:E58) -> -2343.7917 | F59: =SUM(F57:F58) -> -2195.2917 | G59: =SUM(G57:G58) -> -2195.2917 | H59: =SUM(H57:H58) -> -2195.2917 | I59: =SUM(I57:I58) -> -2195.2917 | ... K59: =SUM(K57:K58) -> -2195.2917
A62: X
A63: Turnover | B63: 0 | C63: 0 | D63: 0 | E63: 0 | F63: 0 | G63: 0 | H63: 0 | I63: 0 | J63: 0 | K63: 0
A64: CoS - Staff costs | B64: =-SUMIF('M1 Staff costs'!$A:$A,$A$62,'M1 Staff costs'!I:I) -> -796.95 | C64: =-SUMIF('M1 Staff costs'!$A:$A,$A$62,'M1 Staff costs'!J:J) -> -1034.55 | D64: =-SUMIF('M1 Staff costs'!$A:$A,$A$62,'M1 Staff costs'!K:K) -> -796.95 | E64: =-SUMIF('M1 Staff costs'!$A:$A,$A$62,'M1 Staff costs'!L:L) -> -648.45 | F64: =-SUMIF('M1 Staff costs'!$A:$A,$A$62,'M1 Staff costs'!M:M) -> -499.95 | G64: =-SUMIF('M1 Staff costs'!$A:$A,$A$62,'M1 Staff costs'!N:N) -> -499.95 | H64: =-SUMIF('M1 Staff costs'!$A:$A,$A$62,'M1 Staff costs'!O:O) -> -499.95 | I64: =-SUMIF('M1 Staff costs'!$A:$A,$A$62,'M1 Staff costs'!P:P) -> -499.95 | J64: =-SUMIF('M1 Staff costs'!$A:$A,$A$62,'M1 Staff costs'!Q:Q) -> -499.95 | K64: =-SUMIF('M1 Staff costs'!$A:$A,$A$62,'M1 Staff costs'!R:R) -> -499.95
A65: CoS - Freelancers | B65: =-SUMIF('M1 Freelancers'!$A:$A,'M1 Freelancers'!$A$9,'M1 Freelancers'!E:E) -> -133.33333 | C65: =-SUMIF('M1 Freelancers'!$A:$A,'M1 Freelancers'!$A$9,'M1 Freelancers'!F:F) -> -133.33333 | D65: =-SUMIF('M1 Freelancers'!$A:$A,'M1 Freelancers'!$A$9,'M1 Freelancers'!G:G) -> -133.33333 | E65: =-SUMIF('M1 Freelancers'!$A:$A,'M1 Freelancers'!$A$9,'M1 Freelancers'!H:H) -> -133.33333 | F65: =-SUMIF('M1 Freelancers'!$A:$A,'M1 Freelancers'!$A$9,'M1 Freelancers'!I:I) -> -133.33333 | G65: =-SUMIF('M1 Freelancers'!$A:$A,'M1 Freelancers'!$A$9,'M1 Freelancers'!J:J) -> -133.33333 | H65: =-SUMIF('M1 Freelancers'!$A:$A,'M1 Freelancers'!$A$9,'M1 Freelancers'!K:K) -> -133.33333 | I65: =-SUMIF('M1 Freelancers'!$A:$A,'M1 Freelancers'!$A$9,'M1 Freelancers'!L:L) -> -133.33333 | J65: =-SUMIF('M1 Freelancers'!$A:$A,'M1 Freelancers'!$A$9,'M1 Freelancers'!M:M) -> -133.33333 | K65: =-SUMIF('M1 Freelancers'!$A:$A,'M1 Freelancers'!$A$9,'M1 Freelancers'!N:N) -> -133.33333
A66: GP | B66: =SUM(B63:B65) -> -930.28333 | C66: =SUM(C63:C65) -> -1167.8833 | D66: =SUM(D63:D65) -> -930.28333 | E66: =SUM(E63:E65) -> -781.78333 | F66: =SUM(F63:F65) -> -633.28333 | G66: =SUM(G63:G65) -> -633.28333 | H66: =SUM(H63:H65) -> -633.28333 | I66: =SUM(I63:I65) -> -633.28333 | ... K66: =SUM(K63:K65) -> -633.28333
A67: Other Op costs | B67: =-SUMIF(OH!$A:$A,$A$62,OH!E:E) -> -851.6 | C67: =-SUMIF(OH!$A:$A,$A$62,OH!F:F) -> -851.6 | D67: =-SUMIF(OH!$A:$A,$A$62,OH!G:G) -> -684.93333 | E67: =-SUMIF(OH!$A:$A,$A$62,OH!H:H) -> -684.93333 | F67: =-SUMIF(OH!$A:$A,$A$62,OH!I:I) -> -684.93333 | G67: =-SUMIF(OH!$A:$A,$A$62,OH!J:J) -> -684.93333 | H67: =-SUMIF(OH!$A:$A,$A$62,OH!K:K) -> -684.93333 | I67: =-SUMIF(OH!$A:$A,$A$62,OH!L:L) -> -684.93333 | J67: =-SUMIF(OH!$A:$A,$A$62,OH!M:M) -> -684.93333 | K67: =-SUMIF(OH!$A:$A,$A$62,OH!N:N) -> -684.93333
A68: Contribution | B68: =SUM(B66:B67) -> -1781.8833 | C68: =SUM(C66:C67) -> -2019.4833 | D68: =SUM(D66:D67) -> -1615.2167 | E68: =SUM(E66:E67) -> -1466.7167 | F68: =SUM(F66:F67) -> -1318.2167 | G68: =SUM(G66:G67) -> -1318.2167 | H68: =SUM(H66:H67) -> -1318.2167 | I68: =SUM(I66:I67) -> -1318.2167 | ... K68: =SUM(K66:K67) -> -1318.2167
A71: Recharge
A72: Turnover
A73: CoS - Staff costs | B73: =-SUMIF('M1 Staff costs'!$A:$A,$A$71,'M1 Staff costs'!I:I) -> 2200.8333 | C73: =-SUMIF('M1 Staff costs'!$A:$A,$A$71,'M1 Staff costs'!J:J) -> 2200.8333 | D73: =-SUMIF('M1 Staff costs'!$A:$A,$A$71,'M1 Staff costs'!K:K) -> 1650.625 | E73: =-SUMIF('M1 Staff costs'!$A:$A,$A$71,'M1 Staff costs'!L:L) -> 0 | F73: =-SUMIF('M1 Staff costs'!$A:$A,$A$71,'M1 Staff costs'!M:M) -> 0 | G73: =-SUMIF('M1 Staff costs'!$A:$A,$A$71,'M1 Staff costs'!N:N) -> 0 | H73: =-SUMIF('M1 Staff costs'!$A:$A,$A$71,'M1 Staff costs'!O:O) -> 0 | I73: =-SUMIF('M1 Staff costs'!$A:$A,$A$71,'M1 Staff costs'!P:P) -> 0 | J73: =-SUMIF('M1 Staff costs'!$A:$A,$A$71,'M1 Staff costs'!Q:Q) -> 0 | K73: =-SUMIF('M1 Staff costs'!$A:$A,$A$71,'M1 Staff costs'!R:R) -> 0
A74: CoS - Freelancers
A75: GP
A76: Other Op costs
A77: Contribution
A79: Total | B79: 45992 | C79: 46023 | D79: 46054 | E79: 46082 | F79: 46113 | G79: 46143 | H79: 46174 | I79: 46204 | J79: 46235 | K79: 46266
A80: Turnover | B80: =B4+B10+B19+B27+B36+B45+B54+B63+B72 -> 26566.667 | C80: =C4+C10+C19+C27+C36+C45+C54+C63+C72 -> 14833.333 | D80: =D4+D10+D19+D27+D36+D45+D54+D63+D72 -> 14833.333 | E80: =E4+E10+E19+E27+E36+E45+E54+E63+E72 -> 14833.333 | F80: =F4+F10+F19+F27+F36+F45+F54+F63+F72 -> 14833.333 | G80: =G4+G10+G19+G27+G36+G45+G54+G63+G72 -> 14833.333 | H80: =H4+H10+H19+H27+H36+H45+H54+H63+H72 -> 14833.333 | I80: =I4+I10+I19+I27+I36+I45+I54+I63+I72 -> 14833.333 | ... K80: =K4+K10+K19+K27+K36+K45+K54+K63+K72 -> 14833.333
A81: CoS - Staff costs | B81: =B5+B11+B20+B28+B37+B46+B55+B64+B73 -> -11962.998 | C81: =C5+C11+C20+C28+C37+C46+C55+C64+C73 -> -14101.398 | D81: =D5+D11+D20+D28+D37+D46+D55+D64+D73 -> -11794.561 | E81: =E5+E11+E20+E28+E37+E46+E55+E64+E73 -> -10654.5 | F81: =F5+F11+F20+F28+F37+F46+F55+F64+F73 -> -9912 | G81: =G5+G11+G20+G28+G37+G46+G55+G64+G73 -> -9912 | H81: =H5+H11+H20+H28+H37+H46+H55+H64+H73 -> -9912 | I81: =I5+I11+I20+I28+I37+I46+I55+I64+I73 -> -9912 | ... K81: =K5+K11+K20+K28+K37+K46+K55+K64+K73 -> -9912
A82: CoS - Freelancers | B82: =B6+B12+B21+B29+B38+B47+B56+B65+B74 -> -1000 | C82: =C6+C12+C21+C29+C38+C47+C56+C65+C74 -> -1000 | D82: =D6+D12+D21+D29+D38+D47+D56+D65+D74 -> -1000 | E82: =E6+E12+E21+E29+E38+E47+E56+E65+E74 -> -1000 | F82: =F6+F12+F21+F29+F38+F47+F56+F65+F74 -> -1000 | G82: =G6+G12+G21+G29+G38+G47+G56+G65+G74 -> -1000 | H82: =H6+H12+H21+H29+H38+H47+H56+H65+H74 -> -1000 | I82: =I6+I12+I21+I29+I38+I47+I56+I65+I74 -> -1000 | ... K82: =K6+K12+K21+K29+K38+K47+K56+K65+K74 -> -1000
A83: GP | B83: =SUM(B80:B82) -> 13603.669 | C83: =SUM(C80:C82) -> -268.06433 | D83: =SUM(D80:D82) -> 2038.772 | E83: =SUM(E80:E82) -> 3178.8333 | F83: =SUM(F80:F82) -> 3921.3333 | G83: =SUM(G80:G82) -> 3921.3333 | H83: =SUM(H80:H82) -> 3921.3333 | I83: =SUM(I80:I82) -> 3921.3333 | ... K83: =SUM(K80:K82) -> 3921.3333
A84: Other Op costs | B84: =B8+B14+B23+B31+B40+B49+B58+B67+B78 -> -4968.4 | C84: =C8+C14+C23+C31+C40+C49+C58+C67+C78 -> -4968.4 | D84: =D8+D14+D23+D31+D40+D49+D58+D67+D78 -> -4135.0667 | E84: =E8+E14+E23+E31+E40+E49+E58+E67+E78 -> -4135.0667 | F84: =F8+F14+F23+F31+F40+F49+F58+F67+F78 -> -4135.0667 | G84: =G8+G14+G23+G31+G40+G49+G58+G67+G78 -> -4135.0667 | H84: =H8+H14+H23+H31+H40+H49+H58+H67+H78 -> -4135.0667 | I84: =I8+I14+I23+I31+I40+I49+I58+I67+I78 -> -4135.0667 | ... K84: =K8+K14+K23+K31+K40+K49+K58+K67+K78 -> -4135.0667
A85: Contribution | B85: =SUM(B83:B84) -> 8635.269 | C85: =SUM(C83:C84) -> -5236.4643 | D85: =SUM(D83:D84) -> -2096.2947 | E85: =SUM(E83:E84) -> -956.23333 | F85: =SUM(F83:F84) -> -213.73333 | G85: =SUM(G83:G84) -> -213.73333 | H85: =SUM(H83:H84) -> -213.73333 | I85: =SUM(I83:I84) -> -213.73333 | ... K85: =SUM(K83:K84) -> -213.73333
C87: FY26 | D87: =SUM(B85:K85) -> -936.12333

Sheet Summary - Magazine M1
A1: BN - P&L | B1: Actuals | C1: Actuals | D1: Forecast | E1: Forecast | F1: Forecast | G1: Forecast | H1: Forecast | I1: Forecast | J1: Forecast | K1: Forecast | L1: Forecast | M1: Forecast
B2: 45931 | C2: 45962 | D2: 45992 | E2: 46023 | F2: 46054 | G2: 46082 | H2: 46113 | I2: 46143 | J2: 46174 | K2: 46204 | L2: 46235 | M2: 46266 | N2: FY26
A3: Subsribers | E3: 1500 | F3: 1500 | G3: 1500 | H3: 1500 | I3: 1500 | J3: 1500 | K3: 1500 | L3: 1500 | M3: 1500
A4: In shop purchases | E4: 1000 | F4: 1000 | G4: 1000 | H4: 1000 | I4: 1000 | J4: 1000 | K4: 1000 | L4: 1000 | M4: 1000
A6: Subscription price | E6: 9.99 | F6: 9.99 | G6: 9.99 | H6: 9.99 | I6: 9.99 | J6: 9.99 | K6: 9.99 | L6: 9.99 | M6: 9.99
A7: In shop price | E7: 11.99 | F7: 11.99 | G7: 11.99 | H7: 11.99 | I7: 11.99 | J7: 11.99 | K7: 11.99 | L7: 11.99 | M7: 11.99
A8: Commission | E8: 0.35 | F8: 0.35 | G8: 0.35 | H8: 0.35 | I8: 0.35 | J8: 0.35 | K8: 0.35 | L8: 0.35 | M8: 0.35
A10: Subscription | E10: =E3*E6 -> 14985 | F10: =F3*F6 -> 14985 | G10: =G3*G6 -> 14985 | H10: =H3*H6 -> 14985 | I10: =I3*I6 -> 14985 | J10: =J3*J6 -> 14985 | K10: =K3*K6 -> 14985 | L10: =L3*L6 -> 14985 | M10: =M3*M6 -> 14985
A11: In Shop | E11: =E4*SUM(E7*E8) -> 4196.5 | F11: =F4*SUM(F7*F8) -> 4196.5 | G11: =G4*SUM(G7*G8) -> 4196.5 | H11: =H4*SUM(H7*H8) -> 4196.5 | I11: =I4*SUM(I7*I8) -> 4196.5 | J11: =J4*SUM(J7*J8) -> 4196.5 | K11: =K4*SUM(K7*K8) -> 4196.5 | L11: =L4*SUM(L7*L8) -> 4196.5 | M11: =M4*SUM(M7*M8) -> 4196.5
A13: Total | B13: =SUM(B11:B12) -> 0 | C13: =SUM(C11:C12) -> 0 | E13: =SUM(E10:E11) -> 19181.5 | F13: =SUM(F10:F11) -> 19181.5 | G13: =SUM(G10:G11) -> 19181.5 | H13: =SUM(H10:H11) -> 19181.5 | I13: =SUM(I10:I11) -> 19181.5 | J13: =SUM(J10:J11) -> 19181.5 | K13: =SUM(K10:K11) -> 19181.5 | L13: =SUM(L10:L11) -> 19181.5 | M13: =SUM(M10:M11) -> 19181.5
A15: Other Income
A16: Sponsorship | E16: 500 | F16: 500 | G16: 500 | H16: 500 | I16: 500 | J16: 500 | K16: 500 | L16: 500 | M16: 500
A17: Apple | E17: 300 | F17: 300 | G17: 300 | H17: 300 | I17: 300 | J17: 300 | K17: 300 | L17: 300 | M17: 300
A18: Jellfish | E18: 250 | F18: 250 | G18: 250 | H18: 250 | I18: 250 | J18: 250 | K18: 250 | L18: 250 | M18: 250
A19: Isubscribe / Bolin | E19: 110 | F19: 110 | G19: 110 | H19: 110 | I19: 110 | J19: 110 | K19: 110 | L19: 110 | M19: 110
A22: Total Revenue | B22: =B13+#REF!+#REF!+#REF! -> #REF! | C22: =C13+#REF!+#REF!+#REF! -> #REF! | D22: =D13 -> 0 | E22: =E13+SUM(E16:E19) -> 20341.5 | F22: =F13+SUM(F16:F19) -> 20341.5 | G22: =G13+SUM(G16:G19) -> 20341.5 | H22: =H13+SUM(H16:H19) -> 20341.5 | I22: =I13+SUM(I16:I19) -> 20341.5 | J22: =J13+SUM(J16:J19) -> 20341.5 | K22: =K13+SUM(K16:K19) -> 20341.5 | L22: =L13+SUM(L16:L19) -> 20341.5 | M22: =M13+SUM(M16:M19) -> 20341.5
A25: Costs
A26: Oliver Fennell | D26: -3200 | E26: -3200 | F26: -3200 | G26: -3200 | H26: -3200 | I26: -3200 | J26: -3200 | K26: -3200 | L26: -3200 | M26: -3200
A27: Freelancers - other | D27: -2161 | E27: -2161 | F27: -2161 | G27: -2161 | H27: -2161 | I27: -2161 | J27: -2161 | K27: -2161 | L27: -2161 | M27: -2161 | O27: Make sure to track this carefully each month
A28: Freelancers - per staff cost schedule | D28: =-SUMIF('M1 Staff costs'!$A:$A,'M1 Staff costs'!$A$5,'M1 Staff costs'!I:I) -> -6535.881 | E28: =-SUMIF('M1 Staff costs'!$A:$A,'M1 Staff costs'!$A$5,'M1 Staff costs'!J:J) -> -6595.281 | F28: =-SUMIF('M1 Staff costs'!$A:$A,'M1 Staff costs'!$A$5,'M1 Staff costs'!K:K) -> -5817.2363 | G28: =-SUMIF('M1 Staff costs'!$A:$A,'M1 Staff costs'!$A$5,'M1 Staff costs'!L:L) -> -4925.6333 | H28: =-SUMIF('M1 Staff costs'!$A:$A,'M1 Staff costs'!$A$5,'M1 Staff costs'!M:M) -> -4183.1333 | I28: =-SUMIF('M1 Staff costs'!$A:$A,'M1 Staff costs'!$A$5,'M1 Staff costs'!N:N) -> -4183.1333 | J28: =-SUMIF('M1 Staff costs'!$A:$A,'M1 Staff costs'!$A$5,'M1 Staff costs'!O:O) -> -4183.1333 | K28: =-SUMIF('M1 Staff costs'!$A:$A,'M1 Staff costs'!$A$5,'M1 Staff costs'!P:P) -> -4183.1333 | L28: =-SUMIF('M1 Staff costs'!$A:$A,'M1 Staff costs'!$A$5,'M1 Staff costs'!Q:Q) -> -4183.1333 | M28: =-SUMIF('M1 Staff costs'!$A:$A,'M1 Staff costs'!$A$5,'M1 Staff costs'!R:R) -> -4183.1333
A29: Staff costs | D29: =SUM(D26:D28) -> -11896.881 | E29: =SUM(E26:E28) -> -11956.281 | F29: =SUM(F26:F28) -> -11178.236 | G29: =SUM(G26:G28) -> -10286.633 | H29: =SUM(H26:H28) -> -9544.1333 | I29: =SUM(I26:I28) -> -9544.1333 | J29: =SUM(J26:J28) -> -9544.1333 | K29: =SUM(K26:K28) -> -9544.1333 | ... M29: =SUM(M26:M28) -> -9544.1333
A33: Monthly Print Costs | D33: -4850 | E33: -4850 | F33: -4850 | G33: -4850 | H33: -4850 | I33: -4850 | J33: -4850 | K33: -4850 | L33: -4850 | M33: -4850
A34: Monthly Mailing Fee | D34: -2000 | E34: -2000 | F34: -2000 | G34: -2000 | H34: -2000 | I34: -2000 | J34: -2000 | K34: -2000 | L34: -2000 | M34: -2000
A35: Warehouse | D35: -2240 | E35: -2240 | F35: -2240 | G35: -2240 | H35: -2240 | I35: -2240 | J35: -2240 | K35: -2240 | L35: -2240 | M35: -2240
A36: Sub's management | D36: -1056 | E36: -1056 | F36: -1056 | G36: -1056 | H36: -1056 | I36: -1056 | J36: -1056 | K36: -1056 | L36: -1056 | M36: -1056
A37: Jellyfish | D37: -300 | E37: -300 | F37: -300 | G37: -300 | H37: -300 | I37: -300 | J37: -300 | K37: -300 | L37: -300 | M37: -300
A38: Other Operating costs | D38: =-SUMIF(OH!$A:$A,OH!$A$21,OH!E:E) -> -1047.6 | E38: =-SUMIF(OH!$A:$A,OH!$A$21,OH!F:F) -> -1047.6 | F38: =-SUMIF(OH!$A:$A,OH!$A$21,OH!G:G) -> -880.93333 | G38: =-SUMIF(OH!$A:$A,OH!$A$21,OH!H:H) -> -880.93333 | H38: =-SUMIF(OH!$A:$A,OH!$A$21,OH!I:I) -> -880.93333 | I38: =-SUMIF(OH!$A:$A,OH!$A$21,OH!J:J) -> -880.93333 | J38: =-SUMIF(OH!$A:$A,OH!$A$21,OH!K:K) -> -880.93333 | K38: =-SUMIF(OH!$A:$A,OH!$A$21,OH!L:L) -> -880.93333 | L38: =-SUMIF(OH!$A:$A,OH!$A$21,OH!M:M) -> -880.93333 | M38: =-SUMIF(OH!$A:$A,OH!$A$21,OH!N:N) -> -880.93333
D39: =SUM(D33:D38) -> -11493.6 | E39: =SUM(E33:E38) -> -11493.6 | F39: =SUM(F33:F38) -> -11326.933 | G39: =SUM(G33:G38) -> -11326.933 | H39: =SUM(H33:H38) -> -11326.933 | I39: =SUM(I33:I38) -> -11326.933 | J39: =SUM(J33:J38) -> -11326.933 | K39: =SUM(K33:K38) -> -11326.933 | ... M39: =SUM(M33:M38) -> -11326.933
A42: Contribution | D42: =D22+D29+D39 -> -23390.481 | E42: =E22+E29+E39 -> -3108.381 | F42: =F22+F29+F39 -> -2163.6697 | G42: =G22+G29+G39 -> -1272.0667 | H42: =H22+H29+H39 -> -529.56667 | I42: =I22+I29+I39 -> -529.56667 | J42: =J22+J29+J39 -> -529.56667 | K42: =K22+K29+K39 -> -529.56667 | ... M42: =M22+M29+M39 -> -529.56667
D45: FY | E45: =SUM(E42:M42) -> -9721.5173

Sheet Revenue - Digital
A1: BN - P&L | B1: Actuals | C1: Actuals | D1: Forecast | E1: Forecast | F1: Forecast | G1: Forecast | H1: Forecast | I1: Forecast | J1: Forecast | K1: Forecast | L1: Forecast | M1: Forecast
B2: 45931 | C2: 45962 | D2: 45992 | E2: 46023 | F2: 46054 | G2: 46082 | H2: 46113 | I2: 46143 | J2: 46174 | K2: 46204 | L2: 46235 | M2: 46266 | N2: FY26
A3: Facebook
A4: B2B | E4: =50000/2/12 -> 2083.3333 | F4: =50000/2/12 -> 2083.3333 | G4: =50000/2/12 -> 2083.3333 | H4: =50000/2/12 -> 2083.3333 | I4: =50000/2/12 -> 2083.3333 | J4: =50000/2/12 -> 2083.3333 | K4: =50000/2/12 -> 2083.3333 | L4: =50000/2/12 -> 2083.3333 | M4: =50000/2/12 -> 2083.3333 | O4: Assumes £50k split across Facebook and Instagram
A5: PR | D5: =80000/12 -> 6666.6667 | E5: =80000/12 -> 6666.6667 | F5: =80000/12 -> 6666.6667 | G5: =80000/12 -> 6666.6667 | H5: =80000/12 -> 6666.6667 | I5: =80000/12 -> 6666.6667 | J5: =80000/12 -> 6666.6667 | K5: =80000/12 -> 6666.6667 | ... M5: =80000/12 -> 6666.6667 | O5: £80k
A6: Total | B6: =SUM(B4:B5) -> 0 | C6: =SUM(C4:C5) -> 0 | D6: =SUM(D4:D5) -> 6666.6667 | E6: =SUM(E4:E5) -> 8750 | F6: =SUM(F4:F5) -> 8750 | G6: =SUM(G4:G5) -> 8750 | H6: =SUM(H4:H5) -> 8750 | I6: =SUM(I4:I5) -> 8750 | ... M6: =SUM(M4:M5) -> 8750
A9: Website
A10: Turnover | B10: 188 | C10: 18900 | D10: 18900 | E10: 3000 | F10: 3000 | G10: 3000 | H10: 3000 | I10: 3000 | J10: 3000 | K10: 3000 | L10: 3000 | M10: 3000 | O10: Strong Nov/Dec performance
A12: Total | B12: =SUM(B10:B11) -> 188 | C12: =SUM(C10:C11) -> 18900 | D12: =SUM(D10:D11) -> 18900 | E12: =SUM(E10:E11) -> 3000 | F12: =SUM(F10:F11) -> 3000 | G12: =SUM(G10:G11) -> 3000 | H12: =SUM(H10:H11) -> 3000 | I12: =SUM(I10:I11) -> 3000 | ... M12: =SUM(M10:M11) -> 3000
A15: Youtube
A16: B2B
A17: PR | D17: 1000 | E17: 1000 | F17: 1000 | G17: 1000 | H17: 1000 | I17: 1000 | J17: 1000 | K17: 1000 | L17: 1000 | M17: 1000 | O17: In line with current performance
A18: Total | B18: =SUM(B16:B17) -> 0 | C18: =SUM(C16:C17) -> 0 | D18: =SUM(D16:D17) -> 1000 | E18: =SUM(E16:E17) -> 1000 | F18: =SUM(F16:F17) -> 1000 | G18: =SUM(G16:G17) -> 1000 | H18: =SUM(H16:H17) -> 1000 | I18: =SUM(I16:I17) -> 1000 | ... M18: =SUM(M16:M17) -> 1000
A21: Instagram
A22: B2B | E22: =50000/2/12 -> 2083.3333 | F22: =50000/2/12 -> 2083.3333 | G22: =50000/2/12 -> 2083.3333 | H22: =50000/2/12 -> 2083.3333 | I22: =50000/2/12 -> 2083.3333 | J22: =50000/2/12 -> 2083.3333 | K22: =50000/2/12 -> 2083.3333 | L22: =50000/2/12 -> 2083.3333 | M22: =50000/2/12 -> 2083.3333 | O22: Assumes £50k split across Facebook and Instagram
A23: PR
A24: Total | B24: =SUM(B22:B23) -> 0 | C24: =SUM(C22:C23) -> 0 | D24: =SUM(D22:D23) -> 0 | E24: =SUM(E22:E23) -> 2083.3333 | F24: =SUM(F22:F23) -> 2083.3333 | G24: =SUM(G22:G23) -> 2083.3333 | H24: =SUM(H22:H23) -> 2083.3333 | I24: =SUM(I22:I23) -> 2083.3333 | ... M24: =SUM(M22:M23) -> 2083.3333
A27: Total | B27: =B6+B12+B18+B24 -> 188 | C27: =C6+C12+C18+C24 -> 18900 | D27: =D6+D12+D18+D24 -> 26566.667 | E27: =E6+E12+E18+E24 -> 14833.333 | F27: =F6+F12+F18+F24 -> 14833.333 | G27: =G6+G12+G18+G24 -> 14833.333 | H27: =H6+H12+H18+H24 -> 14833.333 | I27: =I6+I12+I18+I24 -> 14833.333 | ... M27: =M6+M12+M18+M24 -> 14833.333

Sheet M1 Staff costs
C1: Current | E1: Proposed | G1: Actuals | H1: Actuals | I1: Forecast | J1: Forecast | K1: Forecast | L1: Forecast | M1: Forecast | N1: Forecast | O1: Forecast | P1: Forecast | Q1: Forecast | R1: Forecast
A2: Employee Name | B2: Allocation | C2: Gross Salary | D2: NI + Pension | E2: Bonus | F2: NI + Pension | G2: 45931 | H2: 45962 | I2: 45992 | J2: 46023 | K2: 46054 | L2: 46082 | M2: 46113 | N2: 46143 | O2: 46174 | P2: 46204 | Q2: 46235 | R2: 46266 | S2: FY26
A3: Ryan Elliot | C3: 38000 | D3: =C3*0.188 -> 7144 | E3: 2000 | F3: =E3*0.188 -> 376
A4: Facebook | B4: 0.25 | G4: =SUM($C$3:$D$3)/12*$B4 -> 940.5 | H4: =SUM($C$3:$D$3)/12*$B4 -> 940.5 | I4: =SUM($C$3:$D$3)/12*$B4 -> 940.5 | J4: =SUM($C$3:$D$3)/12*$B4+SUM($E$3:$F$3)*$B4 -> 1534.5 | K4: =SUM($C$3:$D$3)/12*$B4 -> 940.5 | L4: =SUM($C$3:$D$3)/12*$B4 -> 940.5 | M4: =SUM($C$3:$D$3)/12*$B4 -> 940.5 | N4: =SUM($C$3:$D$3)/12*$B4 -> 940.5 | O4: =SUM($C$3:$D$3)/12*$B4 -> 940.5 | P4: =SUM($C$3:$D$3)/12*$B4 -> 940.5 | Q4: =SUM($C$3:$D$3)/12*$B4 -> 940.5 | R4: =SUM($C$3:$D$3)/12*$B4 -> 940.5 | S4: =SUM(G4:R4) -> 11880
A5: Magazine | B5: 0.025 | G5: =SUM($C$3:$D$3)/12*$B5 -> 94.05 | H5: =SUM($C$3:$D$3)/12*$B5 -> 94.05 | I5: =SUM($C$3:$D$3)/12*$B5 -> 94.05 | J5: =SUM($C$3:$D$3)/12*$B5+SUM($E$3:$F$3)*$B5 -> 153.45 | K5: =SUM($C$3:$D$3)/12*$B5 -> 94.05 | L5: =SUM($C$3:$D$3)/12*$B5 -> 94.05 | M5: =SUM($C$3:$D$3)/12*$B5 -> 94.05 | N5: =SUM($C$3:$D$3)/12*$B5 -> 94.05 | O5: =SUM($C$3:$D$3)/12*$B5 -> 94.05 | P5: =SUM($C$3:$D$3)/12*$B5 -> 94.05 | Q5: =SUM($C$3:$D$3)/12*$B5 -> 94.05 | R5: =SUM($C$3:$D$3)/12*$B5 -> 94.05 | S5: =SUM(G5:R5) -> 1188
A6: Youtube | B6: 0.25 | G6: =SUM($C$3:$D$3)/12*$B6 -> 940.5 | H6: =SUM($C$3:$D$3)/12*$B6 -> 940.5 | I6: =SUM($C$3:$D$3)/12*$B6 -> 940.5 | J6: =SUM($C$3:$D$3)/12*$B6+SUM($E$3:$F$3)*$B6 -> 1534.5 | K6: =SUM($C$3:$D$3)/12*$B6 -> 940.5 | L6: =SUM($C$3:$D$3)/12*$B6 -> 940.5 | M6: =SUM($C$3:$D$3)/12*$B6 -> 940.5 | N6: =SUM($C$3:$D$3)/12*$B6 -> 940.5 | O6: =SUM($C$3:$D$3)/12*$B6 -> 940.5 | P6: =SUM($C$3:$D$3)/12*$B6 -> 940.5 | Q6: =SUM($C$3:$D$3)/12*$B6 -> 940.5 | R6: =SUM($C$3:$D$3)/12*$B6 -> 940.5 | S6: =SUM(G6:R6) -> 11880
A7: Instagram | B7: 0.25 | G7: =SUM($C$3:$D$3)/12*$B7 -> 940.5 | H7: =SUM($C$3:$D$3)/12*$B7 -> 940.5 | I7: =SUM($C$3:$D$3)/12*$B7 -> 940.5 | J7: =SUM($C$3:$D$3)/12*$B7+SUM($E$3:$F$3)*$B7 -> 1534.5 | K7: =SUM($C$3:$D$3)/12*$B7 -> 940.5 | L7: =SUM($C$3:$D$3)/12*$B7 -> 940.5 | M7: =SUM($C$3:$D$3)/12*$B7 -> 940.5 | N7: =SUM($C$3:$D$3)/12*$B7 -> 940.5 | O7: =SUM($C$3:$D$3)/12*$B7 -> 940.5 | P7: =SUM($C$3:$D$3)/12*$B7 -> 940.5 | Q7: =SUM($C$3:$D$3)/12*$B7 -> 940.5 | R7: =SUM($C$3:$D$3)/12*$B7 -> 940.5 | S7: =SUM(G7:R7) -> 11880
A8: TikTok | B8: 0.05 | G8: =SUM($C$3:$D$3)/12*$B8 -> 188.1 | H8: =SUM($C$3:$D$3)/12*$B8 -> 188.1 | I8: =SUM($C$3:$D$3)/12*$B8 -> 188.1 | J8: =SUM($C$3:$D$3)/12*$B8+SUM($E$3:$F$3)*$B8 -> 306.9 | K8: =SUM($C$3:$D$3)/12*$B8 -> 188.1 | L8: =SUM($C$3:$D$3)/12*$B8 -> 188.1 | M8: =SUM($C$3:$D$3)/12*$B8 -> 188.1 | N8: =SUM($C$3:$D$3)/12*$B8 -> 188.1 | O8: =SUM($C$3:$D$3)/12*$B8 -> 188.1 | P8: =SUM($C$3:$D$3)/12*$B8 -> 188.1 | Q8: =SUM($C$3:$D$3)/12*$B8 -> 188.1 | R8: =SUM($C$3:$D$3)/12*$B8 -> 188.1 | S8: =SUM(G8:R8) -> 2376
A9: X | B9: 0.1 | G9: =SUM($C$3:$D$3)/12*$B9 -> 376.2 | H9: =SUM($C$3:$D$3)/12*$B9 -> 376.2 | I9: =SUM($C$3:$D$3)/12*$B9 -> 376.2 | J9: =SUM($C$3:$D$3)/12*$B9+SUM($E$3:$F$3)*$B9 -> 613.8 | K9: =SUM($C$3:$D$3)/12*$B9 -> 376.2 | L9: =SUM($C$3:$D$3)/12*$B9 -> 376.2 | M9: =SUM($C$3:$D$3)/12*$B9 -> 376.2 | N9: =SUM($C$3:$D$3)/12*$B9 -> 376.2 | O9: =SUM($C$3:$D$3)/12*$B9 -> 376.2 | P9: =SUM($C$3:$D$3)/12*$B9 -> 376.2 | Q9: =SUM($C$3:$D$3)/12*$B9 -> 376.2 | R9: =SUM($C$3:$D$3)/12*$B9 -> 376.2 | S9: =SUM(G9:R9) -> 4752
A10: B2B | B10: 0.075 | G10: =SUM($C$3:$D$3)/12*$B10 -> 282.15 | H10: =SUM($C$3:$D$3)/12*$B10 -> 282.15 | I10: =SUM($C$3:$D$3)/12*$B10 -> 282.15 | J10: =SUM($C$3:$D$3)/12*$B10+SUM($E$3:$F$3)*$B10 -> 460.35 | K10: =SUM($C$3:$D$3)/12*$B10 -> 282.15 | L10: =SUM($C$3:$D$3)/12*$B10 -> 282.15 | M10: =SUM($C$3:$D$3)/12*$B10 -> 282.15 | N10: =SUM($C$3:$D$3)/12*$B10 -> 282.15 | O10: =SUM($C$3:$D$3)/12*$B10 -> 282.15 | P10: =SUM($C$3:$D$3)/12*$B10 -> 282.15 | Q10: =SUM($C$3:$D$3)/12*$B10 -> 282.15 | R10: =SUM($C$3:$D$3)/12*$B10 -> 282.15 | S10: =SUM(G10:R10) -> 3564
A12: Total | G12: =SUM(G4:G11) -> 3762 | H12: =SUM(H4:H11) -> 3762 | I12: =SUM(I4:I11) -> 3762 | J12: =SUM(J4:J11) -> 6138 | K12: =SUM(K4:K11) -> 3762 | L12: =SUM(L4:L11) -> 3762 | M12: =SUM(M4:M11) -> 3762 | N12: =SUM(N4:N11) -> 3762 | ... S12: =SUM(S4:S11) -> 47520
S13: =S12-F3-E3-D3-C3 -> 0
A14: Danny Gilfilen | C14: 25000 | D14: =C14*0.188 -> 4700
A15: Facebook | B15: 0.3 | G15: =SUM($C$14:$D$14)/12*$B15 -> 742.5 | H15: =SUM($C$14:$D$14)/12*$B15 -> 742.5 | I15: =SUM($C$14:$D$14)/12*$B15 -> 742.5 | J15: =SUM($C$14:$D$14)/12*$B15 -> 742.5 | K15: =SUM($C$14:$D$14)/12*$B15 -> 742.5 | L15: =SUM($C$14:$D$14)/12*$B15 -> 742.5 | M15: =SUM($C$14:$D$14)/12*$B15 -> 742.5 | N15: =SUM($C$14:$D$14)/12*$B15 -> 742.5 | ... R15: =SUM($C$14:$D$14)/12*$B15 -> 742.5 | S15: =SUM(G15:R15) -> 8910
A16: Magazine | B16: 0 | G16: =SUM($C$14:$D$14)/12*$B16 -> 0 | H16: =SUM($C$14:$D$14)/12*$B16 -> 0 | I16: =SUM($C$14:$D$14)/12*$B16 -> 0 | J16: =SUM($C$14:$D$14)/12*$B16 -> 0 | K16: =SUM($C$14:$D$14)/12*$B16 -> 0 | L16: =SUM($C$14:$D$14)/12*$B16 -> 0 | M16: =SUM($C$14:$D$14)/12*$B16 -> 0 | N16: =SUM($C$14:$D$14)/12*$B16 -> 0 | ... R16: =SUM($C$14:$D$14)/12*$B16 -> 0 | S16: =SUM(G16:R16) -> 0
A17: Youtube | B17: 0.3 | G17: =SUM($C$14:$D$14)/12*$B17 -> 742.5 | H17: =SUM($C$14:$D$14)/12*$B17 -> 742.5 | I17: =SUM($C$14:$D$14)/12*$B17 -> 742.5 | J17: =SUM($C$14:$D$14)/12*$B17 -> 742.5 | K17: =SUM($C$14:$D$14)/12*$B17 -> 742.5 | L17: =SUM($C$14:$D$14)/12*$B17 -> 742.5 | M17: =SUM($C$14:$D$14)/12*$B17 -> 742.5 | N17: =SUM($C$14:$D$14)/12*$B17 -> 742.5 | ... R17: =SUM($C$14:$D$14)/12*$B17 -> 742.5 | S17: =SUM(G17:R17) -> 8910
A18: Instagram | B18: 0.175 | G18: =SUM($C$14:$D$14)/12*$B18 -> 433.125 | H18: =SUM($C$14:$D$14)/12*$B18 -> 433.125 | I18: =SUM($C$14:$D$14)/12*$B18 -> 433.125 | J18: =SUM($C$14:$D$14)/12*$B18 -> 433.125 | K18: =SUM($C$14:$D$14)/12*$B18 -> 433.125 | L18: =SUM($C$14:$D$14)/12*$B18 -> 433.125 | M18: =SUM($C$14:$D$14)/12*$B18 -> 433.125 | N18: =SUM($C$14:$D$14)/12*$B18 -> 433.125 | ... R18: =SUM($C$14:$D$14)/12*$B18 -> 433.125 | S18: =SUM(G18:R18) -> 5197.5
A19: TikTok | B19: 0.175 | G19: =SUM($C$14:$D$14)/12*$B19 -> 433.125 | H19: =SUM($C$14:$D$14)/12*$B19 -> 433.125 | I19: =SUM($C$14:$D$14)/12*$B19 -> 433.125 | J19: =SUM($C$14:$D$14)/12*$B19 -> 433.125 | K19: =SUM($C$14:$D$14)/12*$B19 -> 433.125 | L19: =SUM($C$14:$D$14)/12*$B19 -> 433.125 | M19: =SUM($C$14:$D$14)/12*$B19 -> 433.125 | N19: =SUM($C$14:$D$14)/12*$B19 -> 433.125 | ... R19: =SUM($C$14:$D$14)/12*$B19 -> 433.125 | S19: =SUM(G19:R19) -> 5197.5
A20: X | B20: 0.05 | G20: =SUM($C$14:$D$14)/12*$B20 -> 123.75 | H20: =SUM($C$14:$D$14)/12*$B20 -> 123.75 | I20: =SUM($C$14:$D$14)/12*$B20 -> 123.75 | J20: =SUM($C$14:$D$14)/12*$B20 -> 123.75 | K20: =SUM($C$14:$D$14)/12*$B20 -> 123.75 | L20: =SUM($C$14:$D$14)/12*$B20 -> 123.75 | M20: =SUM($C$14:$D$14)/12*$B20 -> 123.75 | N20: =SUM($C$14:$D$14)/12*$B20 -> 123.75 | ... R20: =SUM($C$14:$D$14)/12*$B20 -> 123.75 | S20: =SUM(G20:R20) -> 1485
A21: B2B | B21: 0 | G21: =SUM($C$14:$D$14)/12*$B21 -> 0 | H21: =SUM($C$14:$D$14)/12*$B21 -> 0 | I21: =SUM($C$14:$D$14)/12*$B21 -> 0 | J21: =SUM($C$14:$D$14)/12*$B21 -> 0 | K21: =SUM($C$14:$D$14)/12*$B21 -> 0 | L21: =SUM($C$14:$D$14)/12*$B21 -> 0 | M21: =SUM($C$14:$D$14)/12*$B21 -> 0 | N21: =SUM($C$14:$D$14)/12*$B21 -> 0 | ... R21: =SUM($C$14:$D$14)/12*$B21 -> 0 | S21: =SUM(G21:R21) -> 0
A23: Total | G23: =SUM(G15:G22) -> 2475 | H23: =SUM(H15:H22) -> 2475 | I23: =SUM(I15:I22) -> 2475 | J23: =SUM(J15:J22) -> 2475 | K23: =SUM(K15:K22) -> 2475 | L23: =SUM(L15:L22) -> 2475 | M23: =SUM(M15:M22) -> 2475 | N23: =SUM(N15:N22) -> 2475 | ... S23: =SUM(S15:S22) -> 29700
S24: =S23-C14-D14 -> 0
A25: Daniel Greg | C25: 36000 | D25: =C25*0.188 -> 6768
A26: Facebook | B26: 0.1 | G26: =SUM($C$25:$D$25)/12*$B26 -> 356.4 | H26: =SUM($C$25:$D$25)/12*$B26 -> 356.4 | I26: =SUM($C$25:$D$25)/12*$B26 -> 356.4 | J26: =SUM($C$25:$D$25)/12*$B26 -> 356.4 | K26: =SUM($C$25:$D$25)/12*$B26 -> 356.4 | L26: =SUM($C$25:$D$25)/12*$B26 -> 356.4 | M26: =SUM($C$25:$D$25)/12*$B26 -> 356.4 | N26: =SUM($C$25:$D$25)/12*$B26 -> 356.4 | ... R26: =SUM($C$25:$D$25)/12*$B26 -> 356.4 | S26: =SUM(G26:R26) -> 4276.8
A27: Magazine | B27: 0 | G27: =SUM($C$25:$D$25)/12*$B27 -> 0 | H27: =SUM($C$25:$D$25)/12*$B27 -> 0 | I27: =SUM($C$25:$D$25)/12*$B27 -> 0 | J27: =SUM($C$25:$D$25)/12*$B27 -> 0 | K27: =SUM($C$25:$D$25)/12*$B27 -> 0 | L27: =SUM($C$25:$D$25)/12*$B27 -> 0 | M27: =SUM($C$25:$D$25)/12*$B27 -> 0 | N27: =SUM($C$25:$D$25)/12*$B27 -> 0 | ... R27: =SUM($C$25:$D$25)/12*$B27 -> 0 | S27: =SUM(G27:R27) -> 0
A28: Youtube | B28: 0.6 | G28: =SUM($C$25:$D$25)/12*$B28 -> 2138.4 | H28: =SUM($C$25:$D$25)/12*$B28 -> 2138.4 | I28: =SUM($C$25:$D$25)/12*$B28 -> 2138.4 | J28: =SUM($C$25:$D$25)/12*$B28 -> 2138.4 | K28: =SUM($C$25:$D$25)/12*$B28 -> 2138.4 | L28: =SUM($C$25:$D$25)/12*$B28 -> 2138.4 | M28: =SUM($C$25:$D$25)/12*$B28 -> 2138.4 | N28: =SUM($C$25:$D$25)/12*$B28 -> 2138.4 | ... R28: =SUM($C$25:$D$25)/12*$B28 -> 2138.4 | S28: =SUM(G28:R28) -> 25660.8
A29: Instagram | B29: 0.05 | G29: =SUM($C$25:$D$25)/12*$B29 -> 178.2 | H29: =SUM($C$25:$D$25)/12*$B29 -> 178.2 | I29: =SUM($C$25:$D$25)/12*$B29 -> 178.2 | J29: =SUM($C$25:$D$25)/12*$B29 -> 178.2 | K29: =SUM($C$25:$D$25)/12*$B29 -> 178.2 | L29: =SUM($C$25:$D$25)/12*$B29 -> 178.2 | M29: =SUM($C$25:$D$25)/12*$B29 -> 178.2 | N29: =SUM($C$25:$D$25)/12*$B29 -> 178.2 | ... R29: =SUM($C$25:$D$25)/12*$B29 -> 178.2 | S29: =SUM(G29:R29) -> 2138.4
A30: TikTok | B30: 0.05 | G30: =SUM($C$25:$D$25)/12*$B30 -> 178.2 | H30: =SUM($C$25:$D$25)/12*$B30 -> 178.2 | I30: =SUM($C$25:$D$25)/12*$B30 -> 178.2 | J30: =SUM($C$25:$D$25)/12*$B30 -> 178.2 | K30: =SUM($C$25:$D$25)/12*$B30 -> 178.2 | L30: =SUM($C$25:$D$25)/12*$B30 -> 178.2 | M30: =SUM($C$25:$D$25)/12*$B30 -> 178.2 | N30: =SUM($C$25:$D$25)/12*$B30 -> 178.2 | ... R30: =SUM($C$25:$D$25)/12*$B30 -> 178.2 | S30: =SUM(G30:R30) -> 2138.4
A31: X | B31: 0 | G31: =SUM($C$25:$D$25)/12*$B31 -> 0 | H31: =SUM($C$25:$D$25)/12*$B31 -> 0 | I31: =SUM($C$25:$D$25)/12*$B31 -> 0 | J31: =SUM($C$25:$D$25)/12*$B31 -> 0 | K31: =SUM($C$25:$D$25)/12*$B31 -> 0 | L31: =SUM($C$25:$D$25)/12*$B31 -> 0 | M31: =SUM($C$25:$D$25)/12*$B31 -> 0 | N31: =SUM($C$25:$D$25)/12*$B31 -> 0 | ... R31: =SUM($C$25:$D$25)/12*$B31 -> 0 | S31: =SUM(G31:R31) -> 0
A32: B2B | B32: 0 | G32: =SUM($C$25:$D$25)/12*$B32 -> 0 | H32: =SUM($C$25:$D$25)/12*$B32 -> 0 | I32: =SUM($C$25:$D$25)/12*$B32 -> 0 | J32: =SUM($C$25:$D$25)/12*$B32 -> 0 | K32: =SUM($C$25:$D$25)/12*$B32 -> 0 | L32: =SUM($C$25:$D$25)/12*$B32 -> 0 | M32: =SUM($C$25:$D$25)/12*$B32 -> 0 | N32: =SUM($C$25:$D$25)/12*$B32 -> 0 | ... R32: =SUM($C$25:$D$25)/12*$B32 -> 0 | S32: =SUM(G32:R32) -> 0
A33: Total | G33: =SUM(G26:G32) -> 2851.2 | H33: =SUM(H26:H32) -> 2851.2 | I33: =SUM(I26:I32) -> 2851.2 | J33: =SUM(J26:J32) -> 2851.2 | K33: =SUM(K26:K32) -> 2851.2 | L33: =SUM(L26:L32) -> 2851.2 | M33: =SUM(M26:M32) -> 2851.2 | N33: =SUM(N26:N32) -> 2851.2 | ... S33: =SUM(S26:S32) -> 34214.4
A35: PSM Recharge | B35: 0.2 | G35: =SUM($C$25:$D$25)/12*$B35 -> 712.8 | H35: =SUM($C$25:$D$25)/12*$B35 -> 712.8 | I35: =SUM($C$25:$D$25)/12*$B35 -> 712.8 | J35: =SUM($C$25:$D$25)/12*$B35 -> 712.8 | K35: =SUM($C$25:$D$25)/12*$B35 -> 712.8 | L35: =SUM($C$25:$D$25)/12*$B35 -> 712.8 | M35: =SUM($C$25:$D$25)/12*$B35 -> 712.8 | N35: =SUM($C$25:$D$25)/12*$B35 -> 712.8 | ... R35: =SUM($C$25:$D$25)/12*$B35 -> 712.8 | S35: =SUM(G35:R35) -> 8553.6
A37: Nick Bond | C37: 50000 | D37: =C37*0.188 -> 9400 | E37: =4000*12 -> 48000
A38: Facebook | B38: 0.1 | G38: =SUM($C$37:$D$37)/12*$B38 -> 495 | H38: =SUM($C$37:$D$37)/12*$B38 -> 495 | I38: =SUM($C$37:$D$37)/12*$B38 -> 495 | J38: =SUM($C$37:$D$37)/12*$B38 -> 495 | K38: =SUM($C$37:$D$37)/12*$B38 -> 495 | L38: =SUM($E$37)/12*$B38 -> 400 | M38: =SUM($E$37)/12*$B38 -> 400 | N38: =SUM($E$37)/12*$B38 -> 400 | O38: =SUM($E$37)/12*$B38 -> 400 | P38: =SUM($E$37)/12*$B38 -> 400 | Q38: =SUM($E$37)/12*$B38 -> 400 | R38: =SUM($E$37)/12*$B38 -> 400 | S38: =SUM(G38:R38) -> 5275
A39: Magazine | B39: 0.5 | G39: =SUM($C$37:$D$37)/12*$B39 -> 2475 | H39: =SUM($C$37:$D$37)/12*$B39 -> 2475 | I39: =SUM($C$37:$D$37)/12*$B39 -> 2475 | J39: =SUM($C$37:$D$37)/12*$B39 -> 2475 | K39: =SUM($C$37:$D$37)/12*$B39 -> 2475 | L39: =SUM($E$37)/12*$B39 -> 2000 | M39: =SUM($E$37)/12*$B39 -> 2000 | N39: =SUM($E$37)/12*$B39 -> 2000 | O39: =SUM($E$37)/12*$B39 -> 2000 | P39: =SUM($E$37)/12*$B39 -> 2000 | Q39: =SUM($E$37)/12*$B39 -> 2000 | R39: =SUM($E$37)/12*$B39 -> 2000 | S39: =SUM(G39:R39) -> 26375
A40: Youtube | G40: =SUM($C$37:$D$37)/12*$B40 -> 0 | H40: =SUM($C$37:$D$37)/12*$B40 -> 0 | I40: =SUM($C$37:$D$37)/12*$B40 -> 0 | J40: =SUM($C$37:$D$37)/12*$B40 -> 0 | K40: =SUM($C$37:$D$37)/12*$B40 -> 0 | L40: =SUM($E$37)/12*$B40 -> 0 | M40: =SUM($E$37)/12*$B40 -> 0 | N40: =SUM($E$37)/12*$B40 -> 0 | O40: =SUM($E$37)/12*$B40 -> 0 | P40: =SUM($E$37)/12*$B40 -> 0 | Q40: =SUM($E$37)/12*$B40 -> 0 | R40: =SUM($E$37)/12*$B40 -> 0 | S40: =SUM(G40:R40) -> 0
A41: Instagram | B41: 0.1 | G41: =SUM($C$37:$D$37)/12*$B41 -> 495 | H41: =SUM($C$37:$D$37)/12*$B41 -> 495 | I41: =SUM($C$37:$D$37)/12*$B41 -> 495 | J41: =SUM($C$37:$D$37)/12*$B41 -> 495 | K41: =SUM($C$37:$D$37)/12*$B41 -> 495 | L41: =SUM($E$37)/12*$B41 -> 400 | M41: =SUM($E$37)/12*$B41 -> 400 | N41: =SUM($E$37)/12*$B41 -> 400 | O41: =SUM($E$37)/12*$B41 -> 400 | P41: =SUM($E$37)/12*$B41 -> 400 | Q41: =SUM($E$37)/12*$B41 -> 400 | R41: =SUM($E$37)/12*$B41 -> 400 | S41: =SUM(G41:R41) -> 5275
A42: TikTok | B42: 0.1 | G42: =SUM($C$37:$D$37)/12*$B42 -> 495 | H42: =SUM($C$37:$D$37)/12*$B42 -> 495 | I42: =SUM($C$37:$D$37)/12*$B42 -> 495 | J42: =SUM($C$37:$D$37)/12*$B42 -> 495 | K42: =SUM($C$37:$D$37)/12*$B42 -> 495 | L42: =SUM($E$37)/12*$B42 -> 400 | M42: =SUM($E$37)/12*$B42 -> 400 | N42: =SUM($E$37)/12*$B42 -> 400 | O42: =SUM($E$37)/12*$B42 -> 400 | P42: =SUM($E$37)/12*$B42 -> 400 | Q42: =SUM($E$37)/12*$B42 -> 400 | R42: =SUM($E$37)/12*$B42 -> 400 | S42: =SUM(G42:R42) -> 5275
A43: X | G43: =SUM($C$37:$D$37)/12*$B43 -> 0 | H43: =SUM($C$37:$D$37)/12*$B43 -> 0 | I43: =SUM($C$37:$D$37)/12*$B43 -> 0 | J43: =SUM($C$37:$D$37)/12*$B43 -> 0 | K43: =SUM($C$37:$D$37)/12*$B43 -> 0 | L43: =SUM($E$37)/12*$B43 -> 0 | M43: =SUM($E$37)/12*$B43 -> 0 | N43: =SUM($E$37)/12*$B43 -> 0 | O43: =SUM($E$37)/12*$B43 -> 0 | P43: =SUM($E$37)/12*$B43 -> 0 | Q43: =SUM($E$37)/12*$B43 -> 0 | R43: =SUM($E$37)/12*$B43 -> 0 | S43: =SUM(G43:R43) -> 0
A44: B2B | G44: =SUM($C$37:$D$37)/12*$B44 -> 0 | H44: =SUM($C$37:$D$37)/12*$B44 -> 0 | I44: =SUM($C$37:$D$37)/12*$B44 -> 0 | J44: =SUM($C$37:$D$37)/12*$B44 -> 0 | K44: =SUM($C$37:$D$37)/12*$B44 -> 0 | L44: =SUM($E$37)/12*$B44 -> 0 | M44: =SUM($E$37)/12*$B44 -> 0 | N44: =SUM($E$37)/12*$B44 -> 0 | O44: =SUM($E$37)/12*$B44 -> 0 | P44: =SUM($E$37)/12*$B44 -> 0 | Q44: =SUM($E$37)/12*$B44 -> 0 | R44: =SUM($E$37)/12*$B44 -> 0 | S44: =SUM(G44:R44) -> 0
A45: Total | G45: =SUM(G38:G44) -> 3960 | H45: =SUM(H38:H44) -> 3960 | I45: =SUM(I38:I44) -> 3960 | J45: =SUM(J38:J44) -> 3960 | K45: =SUM(K38:K44) -> 3960 | L45: =SUM(L38:L44) -> 3200 | M45: =SUM(M38:M44) -> 3200 | N45: =SUM(N38:N44) -> 3200 | ... S45: =SUM(S38:S44) -> 42200
A47: PSM Recharge | B47: 0.2 | G47: =SUM($C$37:$D$37)/12*$B47 -> 990 | H47: =SUM($C$37:$D$37)/12*$B47 -> 990 | I47: =SUM($C$37:$D$37)/12*$B47 -> 990 | J47: =SUM($C$37:$D$37)/12*$B47 -> 990 | K47: =SUM($C$37:$D$37)/12*$B47 -> 990 | L47: =SUM($E$37)/12*$B47 -> 800 | M47: =SUM($E$37)/12*$B47 -> 800 | N47: =SUM($E$37)/12*$B47 -> 800 | O47: =SUM($E$37)/12*$B47 -> 800 | P47: =SUM($E$37)/12*$B47 -> 800 | Q47: =SUM($E$37)/12*$B47 -> 800 | R47: =SUM($E$37)/12*$B47 -> 800 | S47: =SUM(G47:R47) -> 10550
A50: Harry Payne | C50: 30000 | D50: =C50*0.188 -> 5640
A51: Facebook | B51: 0.1 | G51: =SUM($C$50:$D$50)/12*$B51 -> 297 | H51: =SUM($C$50:$D$50)/12*$B51 -> 297 | I51: =SUM($C$50:$D$50)/12*$B51 -> 297 | J51: =SUM($C$50:$D$50)/12*$B51 -> 297 | K51: =SUM($C$50:$D$50)/12*$B51 -> 297 | L51: =SUM($C$50:$D$50)/12*$B51/2 -> 148.5 | M51: 0 | N51: 0 | O51: 0 | P51: 0 | Q51: 0 | R51: 0 | S51: =SUM(G51:R51) -> 1633.5
A52: Magazine | B52: 0.5 | G52: =SUM($C$50:$D$50)/12*$B52 -> 1485 | H52: =SUM($C$50:$D$50)/12*$B52 -> 1485 | I52: =SUM($C$50:$D$50)/12*$B52 -> 1485 | J52: =SUM($C$50:$D$50)/12*$B52 -> 1485 | K52: =SUM($C$50:$D$50)/12*$B52 -> 1485 | L52: =SUM($C$50:$D$50)/12*$B52/2 -> 742.5 | M52: 0 | N52: 0 | O52: 0 | P52: 0 | Q52: 0 | R52: 0 | S52: =SUM(G52:R52) -> 8167.5
A53: Youtube | B53: 0.1 | G53: =SUM($C$50:$D$50)/12*$B53 -> 297 | H53: =SUM($C$50:$D$50)/12*$B53 -> 297 | I53: =SUM($C$50:$D$50)/12*$B53 -> 297 | J53: =SUM($C$50:$D$50)/12*$B53 -> 297 | K53: =SUM($C$50:$D$50)/12*$B53 -> 297 | L53: =SUM($C$50:$D$50)/12*$B53/2 -> 148.5 | M53: 0 | N53: 0 | O53: 0 | P53: 0 | Q53: 0 | R53: 0 | S53: =SUM(G53:R53) -> 1633.5
A54: Instagram | B54: 0.1 | G54: =SUM($C$50:$D$50)/12*$B54 -> 297 | H54: =SUM($C$50:$D$50)/12*$B54 -> 297 | I54: =SUM($C$50:$D$50)/12*$B54 -> 297 | J54: =SUM($C$50:$D$50)/12*$B54 -> 297 | K54: =SUM($C$50:$D$50)/12*$B54 -> 297 | L54: =SUM($C$50:$D$50)/12*$B54/2 -> 148.5 | M54: 0 | N54: 0 | O54: 0 | P54: 0 | Q54: 0 | R54: 0 | S54: =SUM(G54:R54) -> 1633.5
A55: TikTok | B55: 0.1 | G55: =SUM($C$50:$D$50)/12*$B55 -> 297 | H55: =SUM($C$50:$D$50)/12*$B55 -> 297 | I55: =SUM($C$50:$D$50)/12*$B55 -> 297 | J55: =SUM($C$50:$D$50)/12*$B55 -> 297 | K55: =SUM($C$50:$D$50)/12*$B55 -> 297 | L55: =SUM($C$50:$D$50)/12*$B55/2 -> 148.5 | M55: 0 | N55: 0 | O55: 0 | P55: 0 | Q55: 0 | R55: 0 | S55: =SUM(G55:R55) -> 1633.5
A56: X | B56: 0.1 | G56: =SUM($C$50:$D$50)/12*$B56 -> 297 | H56: =SUM($C$50:$D$50)/12*$B56 -> 297 | I56: =SUM($C$50:$D$50)/12*$B56 -> 297 | J56: =SUM($C$50:$D$50)/12*$B56 -> 297 | K56: =SUM($C$50:$D$50)/12*$B56 -> 297 | L56: =SUM($C$50:$D$50)/12*$B56/2 -> 148.5 | M56: 0 | N56: 0 | O56: 0 | P56: 0 | Q56: 0 | R56: 0 | S56: =SUM(G56:R56) -> 1633.5
A57: B2B | G57: =SUM($C$50:$D$50)/12*$B57 -> 0 | H57: =SUM($C$50:$D$50)/12*$B57 -> 0 | I57: =SUM($C$50:$D$50)/12*$B57 -> 0 | J57: =SUM($C$50:$D$50)/12*$B57 -> 0 | K57: =SUM($C$50:$D$50)/12*$B57 -> 0 | L57: =SUM($C$50:$D$50)/12*$B57/2 -> 0 | M57: 0 | N57: 0 | O57: 0 | P57: 0 | Q57: 0 | R57: 0 | S57: =SUM(G57:R57) -> 0
A58: Total | G58: =SUM(G51:G57) -> 2970 | H58: =SUM(H51:H57) -> 2970 | I58: =SUM(I51:I57) -> 2970 | J58: =SUM(J51:J57) -> 2970 | K58: =SUM(K51:K57) -> 2970 | L58: =SUM(L51:L57) -> 1485 | M58: =SUM(M51:M57) -> 0 | N58: =SUM(N51:N57) -> 0 | ... S58: =SUM(S51:S57) -> 16335
A60: Shaun Brown | C60: 26820 | D60: =C60*0.188 -> 5042.16 | E60: =C60/2 -> 13410
A61: Facebook | G61: =SUM($C$60:$D$60)/12*$B61 -> 0 | H61: =SUM($C$60:$D$60)/12*$B61 -> 0 | I61: =SUM($C$60:$D$60)/12*$B61 -> 0 | J61: =SUM($C$60:$D$60)/12*$B61 -> 0 | K61: 0 | L61: 0 | M61: 0 | N61: 0 | O61: 0 | P61: 0 | Q61: 0 | R61: 0 | S61: =SUM(G61:R61) -> 0
A62: Magazine | B62: 0.45 | G62: =SUM($C$60:$D$60)/12*$B62 -> 1194.831 | H62: =SUM($C$60:$D$60)/12*$B62 -> 1194.831 | I62: =SUM($C$60:$D$60)/12*$B62 -> 1194.831 | J62: =SUM($C$60:$D$60)/12*$B62 -> 1194.831 | K62: =SUM($C$60:$D$60)/12*$B62/2+SUM($E$60/12/2*B62) -> 848.853 | L62: =SUM($E$60)/12*0.9 -> 1005.75 | M62: =SUM($E$60)/12*0.9 -> 1005.75 | N62: =SUM($E$60)/12*0.9 -> 1005.75 | O62: =SUM($E$60)/12*0.9 -> 1005.75 | P62: =SUM($E$60)/12*0.9 -> 1005.75 | Q62: =SUM($E$60)/12*0.9 -> 1005.75 | R62: =SUM($E$60)/12*0.9 -> 1005.75 | S62: =SUM(G62:R62) -> 12668.427
A63: Youtube | G63: =SUM($C$60:$D$60)/12*$B63 -> 0 | H63: =SUM($C$60:$D$60)/12*$B63 -> 0 | I63: =SUM($C$60:$D$60)/12*$B63 -> 0 | J63: =SUM($C$60:$D$60)/12*$B63 -> 0 | K63: 0 | L63: 0 | M63: 0 | N63: 0 | O63: 0 | P63: 0 | Q63: 0 | R63: 0 | S63: =SUM(G63:R63) -> 0
A64: Instagram | G64: =SUM($C$60:$D$60)/12*$B64 -> 0 | H64: =SUM($C$60:$D$60)/12*$B64 -> 0 | I64: =SUM($C$60:$D$60)/12*$B64 -> 0 | J64: =SUM($C$60:$D$60)/12*$B64 -> 0 | K64: 0 | L64: 0 | M64: 0 | N64: 0 | O64: 0 | P64: 0 | Q64: 0 | R64: 0 | S64: =SUM(G64:R64) -> 0
A65: TikTok | G65: =SUM($C$60:$D$60)/12*$B65 -> 0 | H65: =SUM($C$60:$D$60)/12*$B65 -> 0 | I65: =SUM($C$60:$D$60)/12*$B65 -> 0 | J65: =SUM($C$60:$D$60)/12*$B65 -> 0 | K65: 0 | L65: 0 | M65: 0 | N65: 0 | O65: 0 | P65: 0 | Q65: 0 | R65: 0 | S65: =SUM(G65:R65) -> 0
A66: X | G66: =SUM($C$60:$D$60)/12*$B66 -> 0 | H66: =SUM($C$60:$D$60)/12*$B66 -> 0 | I66: =SUM($C$60:$D$60)/12*$B66 -> 0 | J66: =SUM($C$60:$D$60)/12*$B66 -> 0 | K66: 0 | L66: 0 | M66: 0 | N66: 0 | O66: 0 | P66: 0 | Q66: 0 | R66: 0 | S66: =SUM(G66:R66) -> 0
A67: B2B | G67: =SUM($C$60:$D$60)/12*$B67 -> 0 | H67: =SUM($C$60:$D$60)/12*$B67 -> 0 | I67: =SUM($C$60:$D$60)/12*$B67 -> 0 | J67: =SUM($C$60:$D$60)/12*$B67 -> 0 | K67: 0 | L67: 0 | M67: 0 | N67: 0 | O67: 0 | P67: 0 | Q67: 0 | R67: 0 | S67: =SUM(G67:R67) -> 0
A68: Website | B68: 0.45 | G68: =SUM($C$60:$D$60)/12*$B68 -> 1194.831 | H68: =SUM($C$60:$D$60)/12*$B68 -> 1194.831 | I68: =SUM($C$60:$D$60)/12*$B68 -> 1194.831 | J68: =SUM($C$60:$D$60)/12*$B68 -> 1194.831 | K68: =SUM($C$60:$D$60)/12*$B68/2+SUM($E$60/12/2*B68) -> 848.853 | L68: 0 | M68: 0 | N68: 0 | O68: 0 | P68: 0 | Q68: 0 | R68: 0 | S68: =SUM(G68:R68) -> 5628.177
A69: Recharge | B69: -0.5 | G69: =SUM($C$60)/12*$B69 -> -1117.5 | H69: =SUM($C$60)/12*$B69 -> -1117.5 | I69: =SUM($C$60)/12*$B69 -> -1117.5 | J69: =SUM($C$60)/12*$B69 -> -1117.5 | K69: =SUM($C$60)/12*$B69/2+SUM($E$60/12/2*B69) -> -838.125 | L69: 0 | M69: 0 | N69: 0 | O69: 0 | P69: 0 | Q69: 0 | R69: 0 | S69: =SUM(G69:R69) -> -5308.125
A70: Total | G70: =SUM(G61:G69) -> 1272.162 | H70: =SUM(H61:H69) -> 1272.162 | I70: =SUM(I61:I69) -> 1272.162 | J70: =SUM(J61:J69) -> 1272.162 | K70: =SUM(K61:K69) -> 859.581 | L70: =SUM(L61:L69) -> 1005.75 | M70: =SUM(M61:M69) -> 1005.75 | N70: =SUM(N61:N69) -> 1005.75 | ... R70: =SUM(R61:R69) -> 1005.75 | S70: =SUM(S61:S67) -> 12668.427
A72: PSM Recharge | B72: 0.1 | G72: =SUM($C$60:$D$60)/12*$B72 -> 265.518 | H72: =SUM($C$60:$D$60)/12*$B72 -> 265.518 | I72: =SUM($C$60:$D$60)/12*$B72 -> 265.518 | J72: =SUM($C$60:$D$60)/12*$B72 -> 265.518 | K72: =SUM($C$60:$D$60)/12*$B72/2+SUM($E$60/12/2*B72) -> 188.634 | L72: =SUM($E$60)/12*0.1 -> 111.75 | M72: =SUM($E$60)/12*0.1 -> 111.75 | N72: =SUM($E$60)/12*0.1 -> 111.75 | O72: =SUM($E$60)/12*0.1 -> 111.75 | P72: =SUM($E$60)/12*0.1 -> 111.75 | Q72: =SUM($E$60)/12*0.1 -> 111.75 | R72: =SUM($E$60)/12*0.1 -> 111.75 | S72: =SUM(G72:R72) -> 2032.956
A74: Oscar Pick | C74: 26000 | D74: =C74*0.188 -> 4888 | E74: =C74/2 -> 13000
A75: Facebook | G75: =SUM($C$74:$D$74)/12*$B75 -> 0 | H75: =SUM($C$74:$D$74)/12*$B75 -> 0 | I75: =SUM($C$74:$D$74)/12*$B75 -> 0 | J75: =SUM($C$74:$D$74)/12*$B75 -> 0 | K75: =SUM($C$74:$D$74)/12*$B75/2+SUM($E$74/12/2*B75) -> 0 | L75: =SUM($E$74)/12*$B75 -> 0 | M75: =SUM($E$74)/12*$B75 -> 0 | N75: =SUM($E$74)/12*$B75 -> 0 | O75: =SUM($E$74)/12*$B75 -> 0 | P75: =SUM($E$74)/12*$B75 -> 0 | Q75: =SUM($E$74)/12*$B75 -> 0 | R75: =SUM($E$74)/12*$B75 -> 0 | S75: =SUM(G75:R75) -> 0
A76: Magazine | B76: 0.5 | G76: =SUM($C$74:$D$74)/12*$B76 -> 1287 | H76: =SUM($C$74:$D$74)/12*$B76 -> 1287 | I76: =SUM($C$74:$D$74)/12*$B76 -> 1287 | J76: =SUM($C$74:$D$74)/12*$B76 -> 1287 | K76: =SUM($C$74:$D$74)/12*$B76/2+SUM($E$74/12/2*B76) -> 914.33333 | L76: =SUM($E$74)/12*$B76*2 -> 1083.3333 | M76: =SUM($E$74)/12*$B76*2 -> 1083.3333 | N76: =SUM($E$74)/12*$B76*2 -> 1083.3333 | O76: =SUM($E$74)/12*$B76*2 -> 1083.3333 | P76: =SUM($E$74)/12*$B76*2 -> 1083.3333 | Q76: =SUM($E$74)/12*$B76*2 -> 1083.3333 | R76: =SUM($E$74)/12*$B76*2 -> 1083.3333 | S76: =SUM(G76:R76) -> 13645.667
A77: Youtube | G77: =SUM($C$74:$D$74)/12*$B77 -> 0 | H77: =SUM($C$74:$D$74)/12*$B77 -> 0 | I77: =SUM($C$74:$D$74)/12*$B77 -> 0 | J77: =SUM($C$74:$D$74)/12*$B77 -> 0 | K77: =SUM($C$74:$D$74)/12*$B77/2+SUM($E$74/12/2*B77) -> 0 | L77: =SUM($E$74)/12*$B77 -> 0 | M77: =SUM($E$74)/12*$B77 -> 0 | N77: =SUM($E$74)/12*$B77 -> 0 | O77: =SUM($E$74)/12*$B77 -> 0 | P77: =SUM($E$74)/12*$B77 -> 0 | Q77: =SUM($E$74)/12*$B77 -> 0 | R77: =SUM($E$74)/12*$B77 -> 0 | S77: =SUM(G77:R77) -> 0
A78: Instagram | G78: =SUM($C$74:$D$74)/12*$B78 -> 0 | H78: =SUM($C$74:$D$74)/12*$B78 -> 0 | I78: =SUM($C$74:$D$74)/12*$B78 -> 0 | J78: =SUM($C$74:$D$74)/12*$B78 -> 0 | K78: =SUM($C$74:$D$74)/12*$B78/2+SUM($E$74/12/2*B78) -> 0 | L78: =SUM($E$74)/12*$B78 -> 0 | M78: =SUM($E$74)/12*$B78 -> 0 | N78: =SUM($E$74)/12*$B78 -> 0 | O78: =SUM($E$74)/12*$B78 -> 0 | P78: =SUM($E$74)/12*$B78 -> 0 | Q78: =SUM($E$74)/12*$B78 -> 0 | R78: =SUM($E$74)/12*$B78 -> 0 | S78: =SUM(G78:R78) -> 0
A79: TikTok | G79: =SUM($C$74:$D$74)/12*$B79 -> 0 | H79: =SUM($C$74:$D$74)/12*$B79 -> 0 | I79: =SUM($C$74:$D$74)/12*$B79 -> 0 | J79: =SUM($C$74:$D$74)/12*$B79 -> 0 | K79: =SUM($C$74:$D$74)/12*$B79/2+SUM($E$74/12/2*B79) -> 0 | L79: =SUM($E$74)/12*$B79 -> 0 | M79: =SUM($E$74)/12*$B79 -> 0 | N79: =SUM($E$74)/12*$B79 -> 0 | O79: =SUM($E$74)/12*$B79 -> 0 | P79: =SUM($E$74)/12*$B79 -> 0 | Q79: =SUM($E$74)/12*$B79 -> 0 | R79: =SUM($E$74)/12*$B79 -> 0 | S79: =SUM(G79:R79) -> 0
A80: X | G80: =SUM($C$74:$D$74)/12*$B80 -> 0 | H80: =SUM($C$74:$D$74)/12*$B80 -> 0 | I80: =SUM($C$74:$D$74)/12*$B80 -> 0 | J80: =SUM($C$74:$D$74)/12*$B80 -> 0 | K80: =SUM($C$74:$D$74)/12*$B80/2+SUM($E$74/12/2*B80) -> 0 | L80: =SUM($E$74)/12*$B80 -> 0 | M80: =SUM($E$74)/12*$B80 -> 0 | N80: =SUM($E$74)/12*$B80 -> 0 | O80: =SUM($E$74)/12*$B80 -> 0 | P80: =SUM($E$74)/12*$B80 -> 0 | Q80: =SUM($E$74)/12*$B80 -> 0 | R80: =SUM($E$74)/12*$B80 -> 0 | S80: =SUM(G80:R80) -> 0
A81: B2B | G81: =SUM($C$74:$D$74)/12*$B81 -> 0 | H81: =SUM($C$74:$D$74)/12*$B81 -> 0 | I81: =SUM($C$74:$D$74)/12*$B81 -> 0 | J81: =SUM($C$74:$D$74)/12*$B81 -> 0 | K81: =SUM($C$74:$D$74)/12*$B81/2+SUM($E$74/12/2*B81) -> 0 | L81: =SUM($E$74)/12*$B81 -> 0 | M81: =SUM($E$74)/12*$B81 -> 0 | N81: =SUM($E$74)/12*$B81 -> 0 | O81: =SUM($E$74)/12*$B81 -> 0 | P81: =SUM($E$74)/12*$B81 -> 0 | Q81: =SUM($E$74)/12*$B81 -> 0 | R81: =SUM($E$74)/12*$B81 -> 0 | S81: =SUM(G81:R81) -> 0
A82: Website | B82: 0.5 | G82: =SUM($C$74:$D$74)/12*$B82 -> 1287 | H82: =SUM($C$74:$D$74)/12*$B82 -> 1287 | I82: =SUM($C$74:$D$74)/12*$B82 -> 1287 | J82: =SUM($C$74:$D$74)/12*$B82 -> 1287 | K82: =SUM($C$74:$D$74)/12*$B82/2+SUM($E$74/12/2*B82) -> 914.33333 | L82: 0 | M82: 0 | N82: 0 | O82: 0 | P82: 0 | Q82: 0 | R82: 0 | S82: =SUM(G82:R82) -> 6062.3333
A83: Recharge | B83: -0.5 | G83: =SUM($C$74)/12*$B83 -> -1083.3333 | H83: =SUM($C$74)/12*$B83 -> -1083.3333 | I83: =SUM($C$74)/12*$B83 -> -1083.3333 | J83: =SUM($C$74)/12*$B83 -> -1083.3333 | K83: =SUM($C$74)/12*$B83/2+SUM($E$74/12/2*B83) -> -812.5 | L83: 0 | M83: 0 | N83: 0 | O83: 0 | P83: 0 | Q83: 0 | R83: 0 | S83: =SUM(G83:R83) -> -5145.8333
A84: Total | G84: =SUM(G75:G83) -> 1490.6667 | H84: =SUM(H75:H83) -> 1490.6667 | I84: =SUM(I75:I83) -> 1490.6667 | J84: =SUM(J75:J83) -> 1490.6667 | K84: =SUM(K75:K83) -> 1016.1667 | L84: =SUM(L75:L83) -> 1083.3333 | M84: =SUM(M75:M83) -> 1083.3333 | N84: =SUM(N75:N83) -> 1083.3333 | ... R84: =SUM(R75:R83) -> 1083.3333 | S84: =SUM(S75:S81) -> 13645.667
G88: =G12+G23+G33+G45+G58+G70+G84 -> 18781.029 | H88: =H12+H23+H33+H45+H58+H70+H84 -> 18781.029 | I88: =I12+I23+I33+I45+I58+I70+I84 -> 18781.029 | J88: =J12+J23+J33+J45+J58+J70+J84 -> 21157.029 | K88: =K12+K23+K33+K45+K58+K70+K84 -> 17893.948 | L88: =L12+L23+L33+L45+L58+L70+L84 -> 15862.283 | M88: =M12+M23+M33+M45+M58+M70+M84 -> 14377.283 | N88: =N12+N23+N33+N45+N58+N70+N84 -> 14377.283 | ... R88: =R12+R23+R33+R45+R58+R70+R84 -> 14377.283
G89: =SUM(G5+G16+G27+G39+G52+G62+G76)*-1 -> -6535.881 | H89: =SUM(H5+H16+H27+H39+H52+H62+H76)*-1 -> -6535.881 | I89: =SUM(I5+I16+I27+I39+I52+I62+I76)*-1 -> -6535.881 | J89: =SUM(J5+J16+J27+J39+J52+J62+J76)*-1 -> -6595.281 | K89: =SUM(K5+K16+K27+K39+K52+K62+K76)*-1 -> -5817.2363 | L89: =SUM(L5+L16+L27+L39+L52+L62+L76)*-1 -> -4925.6333 | M89: =SUM(M5+M16+M27+M39+M52+M62+M76)*-1 -> -4183.1333 | N89: =SUM(N5+N16+N27+N39+N52+N62+N76)*-1 -> -4183.1333 | ... R89: =SUM(R5+R16+R27+R39+R52+R62+R76)*-1 -> -4183.1333
G90: =SUM(G88:G89) -> 12245.148 | H90: =SUM(H88:H89) -> 12245.148 | I90: =SUM(I88:I89) -> 12245.148 | J90: =SUM(J88:J89) -> 14561.748 | K90: =SUM(K88:K89) -> 12076.711 | L90: =SUM(L88:L89) -> 10936.65 | M90: =SUM(M88:M89) -> 10194.15 | N90: =SUM(N88:N89) -> 10194.15 | ... R90: =SUM(R88:R89) -> 10194.15
I92: FY | J92: 126000
A98: Exceptionals
A99: Nick Bond | B99: Redundancy | C99: 4000 | D99: 46082
A100: Harry Payne | B100: Redundancy | C100: 2000 | D100: 46082
A101: Shaun Brown | B101: Redundancy | C101: 2500 | D101: 14th Feb

Sheet M1 Freelancers
C1: Actuals | D1: Actuals | E1: Forecast | F1: Forecast | G1: Forecast | H1: Forecast | I1: Forecast | J1: Forecast | K1: Forecast | L1: Forecast | M1: Forecast | N1: Forecast
A2: Employee Name | B2: Allocation | C2: 45931 | D2: 45962 | E2: 45992 | F2: 46023 | G2: 46054 | H2: 46082 | I2: 46113 | J2: 46143 | K2: 46174 | L2: 46204 | M2: 46235 | N2: 46266 | O2: FY26
B3: =12000/12 -> 1000
A5: Facebook | B5: 0.3 | C5: =$B$3*$B5 -> 300 | D5: =$B$3*$B5 -> 300 | E5: =$B$3*$B5 -> 300 | F5: =$B$3*$B5 -> 300 | G5: =$B$3*$B5 -> 300 | H5: =$B$3*$B5 -> 300 | I5: =$B$3*$B5 -> 300 | J5: =$B$3*$B5 -> 300 | ... N5: =$B$3*$B5 -> 300 | O5: =SUM(C5:N5) -> 3600
A6: Instagram | B6: 0.3 | C6: =$B$3*$B6 -> 300 | D6: =$B$3*$B6 -> 300 | E6: =$B$3*$B6 -> 300 | F6: =$B$3*$B6 -> 300 | G6: =$B$3*$B6 -> 300 | H6: =$B$3*$B6 -> 300 | I6: =$B$3*$B6 -> 300 | J6: =$B$3*$B6 -> 300 | ... N6: =$B$3*$B6 -> 300 | O6: =SUM(C6:N6) -> 3600
A7: TikTok | B7: =0.4/3 -> 0.13333333 | C7: =$B$3*$B7 -> 133.33333 | D7: =$B$3*$B7 -> 133.33333 | E7: =$B$3*$B7 -> 133.33333 | F7: =$B$3*$B7 -> 133.33333 | G7: =$B$3*$B7 -> 133.33333 | H7: =$B$3*$B7 -> 133.33333 | I7: =$B$3*$B7 -> 133.33333 | J7: =$B$3*$B7 -> 133.33333 | ... N7: =$B$3*$B7 -> 133.33333 | O7: =SUM(C7:N7) -> 1600
A8: Youtube | B8: =0.4/3 -> 0.13333333 | C8: =$B$3*$B8 -> 133.33333 | D8: =$B$3*$B8 -> 133.33333 | E8: =$B$3*$B8 -> 133.33333 | F8: =$B$3*$B8 -> 133.33333 | G8: =$B$3*$B8 -> 133.33333 | H8: =$B$3*$B8 -> 133.33333 | I8: =$B$3*$B8 -> 133.33333 | J8: =$B$3*$B8 -> 133.33333 | ... N8: =$B$3*$B8 -> 133.33333 | O8: =SUM(C8:N8) -> 1600
A9: X | B9: =0.4/3 -> 0.13333333 | C9: =$B$3*$B9 -> 133.33333 | D9: =$B$3*$B9 -> 133.33333 | E9: =$B$3*$B9 -> 133.33333 | F9: =$B$3*$B9 -> 133.33333 | G9: =$B$3*$B9 -> 133.33333 | H9: =$B$3*$B9 -> 133.33333 | I9: =$B$3*$B9 -> 133.33333 | J9: =$B$3*$B9 -> 133.33333 | ... N9: =$B$3*$B9 -> 133.33333 | O9: =SUM(C9:N9) -> 1600
A11: Total | C11: =SUM(C5:C10) -> 1000 | D11: =SUM(D5:D10) -> 1000 | E11: =SUM(E5:E10) -> 1000 | F11: =SUM(F5:F10) -> 1000 | G11: =SUM(G5:G10) -> 1000 | H11: =SUM(H5:H10) -> 1000 | I11: =SUM(I5:I10) -> 1000 | J11: =SUM(J5:J10) -> 1000 | ... O11: =SUM(O5:O10) -> 12000

Sheet M2 Staff costs 
C1: Current | E1: Proposed | G1: Actuals | H1: Actuals | I1: Forecast | J1: Forecast | K1: Forecast | L1: Forecast | M1: Forecast | N1: Forecast | O1: Forecast | P1: Forecast | Q1: Forecast | R1: Forecast
A2: Employee Name | B2: Allocation | C2: Gross Salary | D2: NI + Pension | E2: Bonus | F2: NI + Pension | G2: 45931 | H2: 45962 | I2: 45992 | J2: 46023 | K2: 46054 | L2: 46082 | M2: 46113 | N2: 46143 | O2: 46174 | P2: 46204 | Q2: 46235 | R2: 46266 | S2: FY26
A3: Ryan Elliot | C3: 38000 | D3: =C3*0.188 -> 7144 | E3: 2000 | F3: =E3*0.188 -> 376
A4: Facebook | B4: 0.25 | G4: =SUM($C$3:$D$3)/12*$B4 -> 940.5 | H4: =SUM($C$3:$D$3)/12*$B4 -> 940.5 | I4: =SUM($C$3:$D$3)/12*$B4 -> 940.5 | J4: =SUM($C$3:$D$3)/12*$B4+SUM($E$3:$F$3)*$B4 -> 1534.5 | K4: =SUM($C$3:$D$3)/12*$B4 -> 940.5 | L4: =SUM($C$3:$D$3)/12*$B4 -> 940.5 | M4: =SUM($C$3:$D$3)/12*$B4 -> 940.5 | N4: =SUM($C$3:$D$3)/12*$B4 -> 940.5 | O4: =SUM($C$3:$D$3)/12*$B4 -> 940.5 | P4: =SUM($C$3:$D$3)/12*$B4 -> 940.5 | Q4: =SUM($C$3:$D$3)/12*$B4 -> 940.5 | R4: =SUM($C$3:$D$3)/12*$B4 -> 940.5 | S4: =SUM(G4:R4) -> 11880
A5: Magazine | B5: 0.025 | G5: =SUM($C$3:$D$3)/12*$B5 -> 94.05 | H5: =SUM($C$3:$D$3)/12*$B5 -> 94.05 | I5: =SUM($C$3:$D$3)/12*$B5 -> 94.05 | J5: =SUM($C$3:$D$3)/12*$B5+SUM($E$3:$F$3)*$B5 -> 153.45 | K5: =SUM($C$3:$D$3)/12*$B5 -> 94.05 | L5: =SUM($C$3:$D$3)/12*$B5 -> 94.05 | M5: =SUM($C$3:$D$3)/12*$B5 -> 94.05 | N5: =SUM($C$3:$D$3)/12*$B5 -> 94.05 | O5: =SUM($C$3:$D$3)/12*$B5 -> 94.05 | P5: =SUM($C$3:$D$3)/12*$B5 -> 94.05 | Q5: =SUM($C$3:$D$3)/12*$B5 -> 94.05 | R5: =SUM($C$3:$D$3)/12*$B5 -> 94.05 | S5: =SUM(G5:R5) -> 1188
A6: Youtube | B6: 0.25 | G6: =SUM($C$3:$D$3)/12*$B6 -> 940.5 | H6: =SUM($C$3:$D$3)/12*$B6 -> 940.5 | I6: =SUM($C$3:$D$3)/12*$B6 -> 940.5 | J6: =SUM($C$3:$D$3)/12*$B6+SUM($E$3:$F$3)*$B6 -> 1534.5 | K6: =SUM($C$3:$D$3)/12*$B6 -> 940.5 | L6: =SUM($C$3:$D$3)/12*$B6 -> 940.5 | M6: =SUM($C$3:$D$3)/12*$B6 -> 940.5 | N6: =SUM($C$3:$D$3)/12*$B6 -> 940.5 | O6: =SUM($C$3:$D$3)/12*$B6 -> 940.5 | P6: =SUM($C$3:$D$3)/12*$B6 -> 940.5 | Q6: =SUM($C$3:$D$3)/12*$B6 -> 940.5 | R6: =SUM($C$3:$D$3)/12*$B6 -> 940.5 | S6: =SUM(G6:R6) -> 11880
A7: Instagram | B7: 0.25 | G7: =SUM($C$3:$D$3)/12*$B7 -> 940.5 | H7: =SUM($C$3:$D$3)/12*$B7 -> 940.5 | I7: =SUM($C$3:$D$3)/12*$B7 -> 940.5 | J7: =SUM($C$3:$D$3)/12*$B7+SUM($E$3:$F$3)*$B7 -> 1534.5 | K7: =SUM($C$3:$D$3)/12*$B7 -> 940.5 | L7: =SUM($C$3:$D$3)/12*$B7 -> 940.5 | M7: =SUM($C$3:$D$3)/12*$B7 -> 940.5 | N7: =SUM($C$3:$D$3)/12*$B7 -> 940.5 | O7: =SUM($C$3:$D$3)/12*$B7 -> 940.5 | P7: =SUM($C$3:$D$3)/12*$B7 -> 940.5 | Q7: =SUM($C$3:$D$3)/12*$B7 -> 940.5 | R7: =SUM($C$3:$D$3)/12*$B7 -> 940.5 | S7: =SUM(G7:R7) -> 11880
A8: TikTok | B8: 0.05 | G8: =SUM($C$3:$D$3)/12*$B8 -> 188.1 | H8: =SUM($C$3:$D$3)/12*$B8 -> 188.1 | I8: =SUM($C$3:$D$3)/12*$B8 -> 188.1 | J8: =SUM($C$3:$D$3)/12*$B8+SUM($E$3:$F$3)*$B8 -> 306.9 | K8: =SUM($C$3:$D$3)/12*$B8 -> 188.1 | L8: =SUM($C$3:$D$3)/12*$B8 -> 188.1 | M8: =SUM($C$3:$D$3)/12*$B8 -> 188.1 | N8: =SUM($C$3:$D$3)/12*$B8 -> 188.1 | O8: =SUM($C$3:$D$3)/12*$B8 -> 188.1 | P8: =SUM($C$3:$D$3)/12*$B8 -> 188.1 | Q8: =SUM($C$3:$D$3)/12*$B8 -> 188.1 | R8: =SUM($C$3:$D$3)/12*$B8 -> 188.1 | S8: =SUM(G8:R8) -> 2376
A9: X | B9: 0.1 | G9: =SUM($C$3:$D$3)/12*$B9 -> 376.2 | H9: =SUM($C$3:$D$3)/12*$B9 -> 376.2 | I9: =SUM($C$3:$D$3)/12*$B9 -> 376.2 | J9: =SUM($C$3:$D$3)/12*$B9+SUM($E$3:$F$3)*$B9 -> 613.8 | K9: =SUM($C$3:$D$3)/12*$B9 -> 376.2 | L9: =SUM($C$3:$D$3)/12*$B9 -> 376.2 | M9: =SUM($C$3:$D$3)/12*$B9 -> 376.2 | N9: =SUM($C$3:$D$3)/12*$B9 -> 376.2 | O9: =SUM($C$3:$D$3)/12*$B9 -> 376.2 | P9: =SUM($C$3:$D$3)/12*$B9 -> 376.2 | Q9: =SUM($C$3:$D$3)/12*$B9 -> 376.2 | R9: =SUM($C$3:$D$3)/12*$B9 -> 376.2 | S9: =SUM(G9:R9) -> 4752
A10: B2B | B10: 0.075 | G10: =SUM($C$3:$D$3)/12*$B10 -> 282.15 | H10: =SUM($C$3:$D$3)/12*$B10 -> 282.15 | I10: =SUM($C$3:$D$3)/12*$B10 -> 282.15 | J10: =SUM($C$3:$D$3)/12*$B10+SUM($E$3:$F$3)*$B10 -> 460.35 | K10: =SUM($C$3:$D$3)/12*$B10 -> 282.15 | L10: =SUM($C$3:$D$3)/12*$B10 -> 282.15 | M10: =SUM($C$3:$D$3)/12*$B10 -> 282.15 | N10: =SUM($C$3:$D$3)/12*$B10 -> 282.15 | O10: =SUM($C$3:$D$3)/12*$B10 -> 282.15 | P10: =SUM($C$3:$D$3)/12*$B10 -> 282.15 | Q10: =SUM($C$3:$D$3)/12*$B10 -> 282.15 | R10: =SUM($C$3:$D$3)/12*$B10 -> 282.15 | S10: =SUM(G10:R10) -> 3564
A12: Total | G12: =SUM(G4:G11) -> 3762 | H12: =SUM(H4:H11) -> 3762 | I12: =SUM(I4:I11) -> 3762 | J12: =SUM(J4:J11) -> 6138 | K12: =SUM(K4:K11) -> 3762 | L12: =SUM(L4:L11) -> 3762 | M12: =SUM(M4:M11) -> 3762 | N12: =SUM(N4:N11) -> 3762 | ... S12: =SUM(S4:S11) -> 47520
S13: =S12-F3-E3-D3-C3 -> 0
A14: Danny Gilfilen | C14: 25000 | D14: =C14*0.188 -> 4700
A15: Facebook | B15: 0.3 | G15: =SUM($C$14:$D$14)/12*$B15 -> 742.5 | H15: =SUM($C$14:$D$14)/12*$B15 -> 742.5 | I15: =SUM($C$14:$D$14)/12*$B15 -> 742.5 | J15: =SUM($C$14:$D$14)/12*$B15 -> 742.5 | K15: =SUM($C$14:$D$14)/12*$B15 -> 742.5 | L15: =SUM($C$14:$D$14)/12*$B15 -> 742.5 | M15: =SUM($C$14:$D$14)/12*$B15 -> 742.5 | N15: =SUM($C$14:$D$14)/12*$B15 -> 742.5 | ... R15: =SUM($C$14:$D$14)/12*$B15 -> 742.5 | S15: =SUM(G15:R15) -> 8910
A16: Magazine | B16: 0 | G16: =SUM($C$14:$D$14)/12*$B16 -> 0 | H16: =SUM($C$14:$D$14)/12*$B16 -> 0 | I16: =SUM($C$14:$D$14)/12*$B16 -> 0 | J16: =SUM($C$14:$D$14)/12*$B16 -> 0 | K16: =SUM($C$14:$D$14)/12*$B16 -> 0 | L16: =SUM($C$14:$D$14)/12*$B16 -> 0 | M16: =SUM($C$14:$D$14)/12*$B16 -> 0 | N16: =SUM($C$14:$D$14)/12*$B16 -> 0 | ... R16: =SUM($C$14:$D$14)/12*$B16 -> 0 | S16: =SUM(G16:R16) -> 0
A17: Youtube | B17: 0.3 | G17: =SUM($C$14:$D$14)/12*$B17 -> 742.5 | H17: =SUM($C$14:$D$14)/12*$B17 -> 742.5 | I17: =SUM($C$14:$D$14)/12*$B17 -> 742.5 | J17: =SUM($C$14:$D$14)/12*$B17 -> 742.5 | K17: =SUM($C$14:$D$14)/12*$B17 -> 742.5 | L17: =SUM($C$14:$D$14)/12*$B17 -> 742.5 | M17: =SUM($C$14:$D$14)/12*$B17 -> 742.5 | N17: =SUM($C$14:$D$14)/12*$B17 -> 742.5 | ... R17: =SUM($C$14:$D$14)/12*$B17 -> 742.5 | S17: =SUM(G17:R17) -> 8910
A18: Instagram | B18: 0.175 | G18: =SUM($C$14:$D$14)/12*$B18 -> 433.125 | H18: =SUM($C$14:$D$14)/12*$B18 -> 433.125 | I18: =SUM($C$14:$D$14)/12*$B18 -> 433.125 | J18: =SUM($C$14:$D$14)/12*$B18 -> 433.125 | K18: =SUM($C$14:$D$14)/12*$B18 -> 433.125 | L18: =SUM($C$14:$D$14)/12*$B18 -> 433.125 | M18: =SUM($C$14:$D$14)/12*$B18 -> 433.125 | N18: =SUM($C$14:$D$14)/12*$B18 -> 433.125 | ... R18: =SUM($C$14:$D$14)/12*$B18 -> 433.125 | S18: =SUM(G18:R18) -> 5197.5
A19: TikTok | B19: 0.175 | G19: =SUM($C$14:$D$14)/12*$B19 -> 433.125 | H19: =SUM($C$14:$D$14)/12*$B19 -> 433.125 | I19: =SUM($C$14:$D$14)/12*$B19 -> 433.125 | J19: =SUM($C$14:$D$14)/12*$B19 -> 433.125 | K19: =SUM($C$14:$D$14)/12*$B19 -> 433.125 | L19: =SUM($C$14:$D$14)/12*$B19 -> 433.125 | M19: =SUM($C$14:$D$14)/12*$B19 -> 433.125 | N19: =SUM($C$14:$D$14)/12*$B19 -> 433.125 | ... R19: =SUM($C$14:$D$14)/12*$B19 -> 433.125 | S19: =SUM(G19:R19) -> 5197.5
A20: X | B20: 0.05 | G20: =SUM($C$14:$D$14)/12*$B20 -> 123.75 | H20: =SUM($C$14:$D$14)/12*$B20 -> 123.75 | I20: =SUM($C$14:$D$14)/12*$B20 -> 123.75 | J20: =SUM($C$14:$D$14)/12*$B20 -> 123.75 | K20: =SUM($C$14:$D$14)/12*$B20 -> 123.75 | L20: =SUM($C$14:$D$14)/12*$B20 -> 123.75 | M20: =SUM($C$14:$D$14)/12*$B20 -> 123.75 | N20: =SUM($C$14:$D$14)/12*$B20 -> 123.75 | ... R20: =SUM($C$14:$D$14)/12*$B20 -> 123.75 | S20: =SUM(G20:R20) -> 1485
A21: B2B | B21: 0 | G21: =SUM($C$14:$D$14)/12*$B21 -> 0 | H21: =SUM($C$14:$D$14)/12*$B21 -> 0 | I21: =SUM($C$14:$D$14)/12*$B21 -> 0 | J21: =SUM($C$14:$D$14)/12*$B21 -> 0 | K21: =SUM($C$14:$D$14)/12*$B21 -> 0 | L21: =SUM($C$14:$D$14)/12*$B21 -> 0 | M21: =SUM($C$14:$D$14)/12*$B21 -> 0 | N21: =SUM($C$14:$D$14)/12*$B21 -> 0 | ... R21: =SUM($C$14:$D$14)/12*$B21 -> 0 | S21: =SUM(G21:R21) -> 0
A23: Total | G23: =SUM(G15:G22) -> 2475 | H23: =SUM(H15:H22) -> 2475 | I23: =SUM(I15:I22) -> 2475 | J23: =SUM(J15:J22) -> 2475 | K23: =SUM(K15:K22) -> 2475 | L23: =SUM(L15:L22) -> 2475 | M23: =SUM(M15:M22) -> 2475 | N23: =SUM(N15:N22) -> 2475 | ... S23: =SUM(S15:S22) -> 29700
S24: =S23-C14-D14 -> 0
A25: Daniel Greg | B25: Assumes leave in Mar 26 | C25: 36000 | D25: =C25*0.188 -> 6768
A26: Facebook | B26: 0.1 | G26: =SUM($C$25:$D$25)/12*$B26 -> 356.4 | H26: =SUM($C$25:$D$25)/12*$B26 -> 356.4 | I26: =SUM($C$25:$D$25)/12*$B26 -> 356.4 | J26: =SUM($C$25:$D$25)/12*$B26 -> 356.4 | K26: =SUM($C$25:$D$25)/12*$B26 -> 356.4 | S26: =SUM(G26:R26) -> 1782
A27: Magazine | B27: 0 | G27: =SUM($C$25:$D$25)/12*$B27 -> 0 | H27: =SUM($C$25:$D$25)/12*$B27 -> 0 | I27: =SUM($C$25:$D$25)/12*$B27 -> 0 | J27: =SUM($C$25:$D$25)/12*$B27 -> 0 | K27: =SUM($C$25:$D$25)/12*$B27 -> 0 | S27: =SUM(G27:R27) -> 0
A28: Youtube | B28: 0.6 | G28: =SUM($C$25:$D$25)/12*$B28 -> 2138.4 | H28: =SUM($C$25:$D$25)/12*$B28 -> 2138.4 | I28: =SUM($C$25:$D$25)/12*$B28 -> 2138.4 | J28: =SUM($C$25:$D$25)/12*$B28 -> 2138.4 | K28: =SUM($C$25:$D$25)/12*$B28 -> 2138.4 | S28: =SUM(G28:R28) -> 10692
A29: Instagram | B29: 0.05 | G29: =SUM($C$25:$D$25)/12*$B29 -> 178.2 | H29: =SUM($C$25:$D$25)/12*$B29 -> 178.2 | I29: =SUM($C$25:$D$25)/12*$B29 -> 178.2 | J29: =SUM($C$25:$D$25)/12*$B29 -> 178.2 | K29: =SUM($C$25:$D$25)/12*$B29 -> 178.2 | S29: =SUM(G29:R29) -> 891
A30: TikTok | B30: 0.05 | G30: =SUM($C$25:$D$25)/12*$B30 -> 178.2 | H30: =SUM($C$25:$D$25)/12*$B30 -> 178.2 | I30: =SUM($C$25:$D$25)/12*$B30 -> 178.2 | J30: =SUM($C$25:$D$25)/12*$B30 -> 178.2 | K30: =SUM($C$25:$D$25)/12*$B30 -> 178.2 | S30: =SUM(G30:R30) -> 891
A31: X | B31: 0 | G31: =SUM($C$25:$D$25)/12*$B31 -> 0 | H31: =SUM($C$25:$D$25)/12*$B31 -> 0 | I31: =SUM($C$25:$D$25)/12*$B31 -> 0 | J31: =SUM($C$25:$D$25)/12*$B31 -> 0 | K31: =SUM($C$25:$D$25)/12*$B31 -> 0 | S31: =SUM(G31:R31) -> 0
A32: B2B | B32: 0 | G32: =SUM($C$25:$D$25)/12*$B32 -> 0 | H32: =SUM($C$25:$D$25)/12*$B32 -> 0 | I32: =SUM($C$25:$D$25)/12*$B32 -> 0 | J32: =SUM($C$25:$D$25)/12*$B32 -> 0 | K32: =SUM($C$25:$D$25)/12*$B32 -> 0 | S32: =SUM(G32:R32) -> 0
A33: Total | G33: =SUM(G26:G32) -> 2851.2 | H33: =SUM(H26:H32) -> 2851.2 | I33: =SUM(I26:I32) -> 2851.2 | J33: =SUM(J26:J32) -> 2851.2 | K33: =SUM(K26:K32) -> 2851.2 | L33: =SUM(L26:L32) -> 0 | M33: =SUM(M26:M32) -> 0 | N33: =SUM(N26:N32) -> 0 | ... S33: =SUM(S26:S32) -> 14256
A35: PSM Recharge | B35: 0.2 | G35: =SUM($C$25:$D$25)/12*$B35 -> 712.8 | H35: =SUM($C$25:$D$25)/12*$B35 -> 712.8 | I35: =SUM($C$25:$D$25)/12*$B35 -> 712.8 | J35: =SUM($C$25:$D$25)/12*$B35 -> 712.8 | K35: =SUM($C$25:$D$25)/12*$B35 -> 712.8 | S35: =SUM(G35:R35) -> 3564
A37: Nick Bond | C37: 50000 | D37: =C37*0.188 -> 9400 | E37: =4000*12 -> 48000
A38: Facebook | B38: 0.1 | G38: =SUM($C$37:$D$37)/12*$B38 -> 495 | H38: =SUM($C$37:$D$37)/12*$B38 -> 495 | I38: =SUM($C$37:$D$37)/12*$B38 -> 495 | J38: =SUM($C$37:$D$37)/12*$B38 -> 495 | K38: =SUM($C$37:$D$37)/12*$B38 -> 495 | L38: =SUM($E$37)/12*$B38 -> 400 | M38: =SUM($E$37)/12*$B38 -> 400 | N38: =SUM($E$37)/12*$B38 -> 400 | O38: =SUM($E$37)/12*$B38 -> 400 | P38: =SUM($E$37)/12*$B38 -> 400 | Q38: =SUM($E$37)/12*$B38 -> 400 | R38: =SUM($E$37)/12*$B38 -> 400 | S38: =SUM(G38:R38) -> 5275
A39: Magazine | B39: 0.5 | G39: =SUM($C$37:$D$37)/12*$B39 -> 2475 | H39: =SUM($C$37:$D$37)/12*$B39 -> 2475 | I39: =SUM($C$37:$D$37)/12*$B39 -> 2475 | J39: =SUM($C$37:$D$37)/12*$B39 -> 2475 | K39: =SUM($C$37:$D$37)/12*$B39 -> 2475 | L39: =SUM($E$37)/12*$B39 -> 2000 | M39: =SUM($E$37)/12*$B39 -> 2000 | N39: =SUM($E$37)/12*$B39 -> 2000 | O39: =SUM($E$37)/12*$B39 -> 2000 | P39: =SUM($E$37)/12*$B39 -> 2000 | Q39: =SUM($E$37)/12*$B39 -> 2000 | R39: =SUM($E$37)/12*$B39 -> 2000 | S39: =SUM(G39:R39) -> 26375
A40: Youtube | G40: =SUM($C$37:$D$37)/12*$B40 -> 0 | H40: =SUM($C$37:$D$37)/12*$B40 -> 0 | I40: =SUM($C$37:$D$37)/12*$B40 -> 0 | J40: =SUM($C$37:$D$37)/12*$B40 -> 0 | K40: =SUM($C$37:$D$37)/12*$B40 -> 0 | L40: =SUM($E$37)/12*$B40 -> 0 | M40: =SUM($E$37)/12*$B40 -> 0 | N40: =SUM($E$37)/12*$B40 -> 0 | O40: =SUM($E$37)/12*$B40 -> 0 | P40: =SUM($E$37)/12*$B40 -> 0 | Q40: =SUM($E$37)/12*$B40 -> 0 | R40: =SUM($E$37)/12*$B40 -> 0 | S40: =SUM(G40:R40) -> 0
A41: Instagram | B41: 0.1 | G41: =SUM($C$37:$D$37)/12*$B41 -> 495 | H41: =SUM($C$37:$D$37)/12*$B41 -> 495 | I41: =SUM($C$37:$D$37)/12*$B41 -> 495 | J41: =SUM($C$37:$D$37)/12*$B41 -> 495 | K41: =SUM($C$37:$D$37)/12*$B41 -> 495 | L41: =SUM($E$37)/12*$B41 -> 400 | M41: =SUM($E$37)/12*$B41 -> 400 | N41: =SUM($E$37)/12*$B41 -> 400 | O41: =SUM($E$37)/12*$B41 -> 400 | P41: =SUM($E$37)/12*$B41 -> 400 | Q41: =SUM($E$37)/12*$B41 -> 400 | R41: =SUM($E$37)/12*$B41 -> 400 | S41: =SUM(G41:R41) -> 5275
A42: TikTok | B42: 0.1 | G42: =SUM($C$37:$D$37)/12*$B42 -> 495 | H42: =SUM($C$37:$D$37)/12*$B42 -> 495 | I42: =SUM($C$37:$D$37)/12*$B42 -> 495 | J42: =SUM($C$37:$D$37)/12*$B42 -> 495 | K42: =SUM($C$37:$D$37)/12*$B42 -> 495 | L42: =SUM($E$37)/12*$B42 -> 400 | M42: =SUM($E$37)/12*$B42 -> 400 | N42: =SUM($E$37)/12*$B42 -> 400 | O42: =SUM($E$37)/12*$B42 -> 400 | P42: =SUM($E$37)/12*$B42 -> 400 | Q42: =SUM($E$37)/12*$B42 -> 400 | R42: =SUM($E$37)/12*$B42 -> 400 | S42: =SUM(G42:R42) -> 5275
A43: X | G43: =SUM($C$37:$D$37)/12*$B43 -> 0 | H43: =SUM($C$37:$D$37)/12*$B43 -> 0 | I43: =SUM($C$37:$D$37)/12*$B43 -> 0 | J43: =SUM($C$37:$D$37)/12*$B43 -> 0 | K43: =SUM($C$37:$D$37)/12*$B43 -> 0 | L43: =SUM($E$37)/12*$B43 -> 0 | M43: =SUM($E$37)/12*$B43 -> 0 | N43: =SUM($E$37)/12*$B43 -> 0 | O43: =SUM($E$37)/12*$B43 -> 0 | P43: =SUM($E$37)/12*$B43 -> 0 | Q43: =SUM($E$37)/12*$B43 -> 0 | R43: =SUM($E$37)/12*$B43 -> 0 | S43: =SUM(G43:R43) -> 0
A44: B2B | G44: =SUM($C$37:$D$37)/12*$B44 -> 0 | H44: =SUM($C$37:$D$37)/12*$B44 -> 0 | I44: =SUM($C$37:$D$37)/12*$B44 -> 0 | J44: =SUM($C$37:$D$37)/12*$B44 -> 0 | K44: =SUM($C$37:$D$37)/12*$B44 -> 0 | L44: =SUM($E$37)/12*$B44 -> 0 | M44: =SUM($E$37)/12*$B44 -> 0 | N44: =SUM($E$37)/12*$B44 -> 0 | O44: =SUM($E$37)/12*$B44 -> 0 | P44: =SUM($E$37)/12*$B44 -> 0 | Q44: =SUM($E$37)/12*$B44 -> 0 | R44: =SUM($E$37)/12*$B44 -> 0 | S44: =SUM(G44:R44) -> 0
A45: Total | G45: =SUM(G38:G44) -> 3960 | H45: =SUM(H38:H44) -> 3960 | I45: =SUM(I38:I44) -> 3960 | J45: =SUM(J38:J44) -> 3960 | K45: =SUM(K38:K44) -> 3960 | L45: =SUM(L38:L44) -> 3200 | M45: =SUM(M38:M44) -> 3200 | N45: =SUM(N38:N44) -> 3200 | ... S45: =SUM(S38:S44) -> 42200
A47: PSM Recharge | B47: 0.2 | G47: =SUM($C$37:$D$37)/12*$B47 -> 990 | H47: =SUM($C$37:$D$37)/12*$B47 -> 990 | I47: =SUM($C$37:$D$37)/12*$B47 -> 990 | J47: =SUM($C$37:$D$37)/12*$B47 -> 990 | K47: =SUM($C$37:$D$37)/12*$B47 -> 990 | L47: =SUM($E$37)/12*$B47 -> 800 | M47: =SUM($E$37)/12*$B47 -> 800 | N47: =SUM($E$37)/12*$B47 -> 800 | O47: =SUM($E$37)/12*$B47 -> 800 | P47: =SUM($E$37)/12*$B47 -> 800 | Q47: =SUM($E$37)/12*$B47 -> 800 | R47: =SUM($E$37)/12*$B47 -> 800 | S47: =SUM(G47:R47) -> 10550
A50: Harry Payne | B50: Assumes leaves Mid-Mar 26 | C50: 30000 | D50: =C50*0.188 -> 5640
A51: Facebook | B51: 0.1 | G51: =SUM($C$50:$D$50)/12*$B51 -> 297 | H51: =SUM($C$50:$D$50)/12*$B51 -> 297 | I51: =SUM($C$50:$D$50)/12*$B51 -> 297 | J51: =SUM($C$50:$D$50)/12*$B51 -> 297 | K51: =SUM($C$50:$D$50)/12*$B51 -> 297 | L51: =SUM($C$50:$D$50)/12*$B51/2 -> 148.5 | S51: =SUM(G51:R51) -> 1633.5
A52: Magazine | B52: 0.5 | G52: =SUM($C$50:$D$50)/12*$B52 -> 1485 | H52: =SUM($C$50:$D$50)/12*$B52 -> 1485 | I52: =SUM($C$50:$D$50)/12*$B52 -> 1485 | J52: =SUM($C$50:$D$50)/12*$B52 -> 1485 | K52: =SUM($C$50:$D$50)/12*$B52 -> 1485 | L52: =SUM($C$50:$D$50)/12*$B52/2 -> 742.5 | S52: =SUM(G52:R52) -> 8167.5
A53: Youtube | B53: 0.1 | G53: =SUM($C$50:$D$50)/12*$B53 -> 297 | H53: =SUM($C$50:$D$50)/12*$B53 -> 297 | I53: =SUM($C$50:$D$50)/12*$B53 -> 297 | J53: =SUM($C$50:$D$50)/12*$B53 -> 297 | K53: =SUM($C$50:$D$50)/12*$B53 -> 297 | L53: =SUM($C$50:$D$50)/12*$B53/2 -> 148.5 | S53: =SUM(G53:R53) -> 1633.5
A54: Instagram | B54: 0.1 | G54: =SUM($C$50:$D$50)/12*$B54 -> 297 | H54: =SUM($C$50:$D$50)/12*$B54 -> 297 | I54: =SUM($C$50:$D$50)/12*$B54 -> 297 | J54: =SUM($C$50:$D$50)/12*$B54 -> 297 | K54: =SUM($C$50:$D$50)/12*$B54 -> 297 | L54: =SUM($C$50:$D$50)/12*$B54/2 -> 148.5 | S54: =SUM(G54:R54) -> 1633.5
A55: TikTok | B55: 0.1 | G55: =SUM($C$50:$D$50)/12*$B55 -> 297 | H55: =SUM($C$50:$D$50)/12*$B55 -> 297 | I55: =SUM($C$50:$D$50)/12*$B55 -> 297 | J55: =SUM($C$50:$D$50)/12*$B55 -> 297 | K55: =SUM($C$50:$D$50)/12*$B55 -> 297 | L55: =SUM($C$50:$D$50)/12*$B55/2 -> 148.5 | S55: =SUM(G55:R55) -> 1633.5
A56: X | B56: 0.1 | G56: =SUM($C$50:$D$50)/12*$B56 -> 297 | H56: =SUM($C$50:$D$50)/12*$B56 -> 297 | I56: =SUM($C$50:$D$50)/12*$B56 -> 297 | J56: =SUM($C$50:$D$50)/12*$B56 -> 297 | K56: =SUM($C$50:$D$50)/12*$B56 -> 297 | L56: =SUM($C$50:$D$50)/12*$B56/2 -> 148.5 | S56: =SUM(G56:R56) -> 1633.5
A57: B2B | G57: =SUM($C$50:$D$50)/12*$B57 -> 0 | H57: =SUM($C$50:$D$50)/12*$B57 -> 0 | I57: =SUM($C$50:$D$50)/12*$B57 -> 0 | J57: =SUM($C$50:$D$50)/12*$B57 -> 0 | K57: =SUM($C$50:$D$50)/12*$B57 -> 0 | L57: =SUM($C$50:$D$50)/12*$B57/2 -> 0 | S57: =SUM(G57:R57) -> 0
A58: Total | G58: =SUM(G51:G57) -> 2970 | H58: =SUM(H51:H57) -> 2970 | I58: =SUM(I51:I57) -> 2970 | J58: =SUM(J51:J57) -> 2970 | K58: =SUM(K51:K57) -> 2970 | L58: =SUM(L51:L57) -> 1485 | M58: =SUM(M51:M57) -> 0 | N58: =SUM(N51:N57) -> 0 | ... S58: =SUM(S51:S57) -> 16335
A60: Shaun Brown | C60: 26820 | D60: =C60*0.188 -> 5042.16 | E60: =C60/2 -> 13410
A61: Facebook | G61: =SUM($C$60:$D$60)/12*$B61 -> 0 | H61: =SUM($C$60:$D$60)/12*$B61 -> 0 | I61: =SUM($C$60:$D$60)/12*$B61 -> 0 | J61: =SUM($C$60:$D$60)/12*$B61 -> 0 | K61: 0 | L61: 0 | M61: 0 | N61: 0 | O61: 0 | P61: 0 | Q61: 0 | R61: 0 | S61: =SUM(G61:R61) -> 0
A62: Magazine | B62: 0.45 | G62: =SUM($C$60:$D$60)/12*$B62 -> 1194.831 | H62: =SUM($C$60:$D$60)/12*$B62 -> 1194.831 | I62: =SUM($C$60:$D$60)/12*$B62 -> 1194.831 | J62: =SUM($C$60:$D$60)/12*$B62 -> 1194.831 | K62: =SUM($C$60:$D$60)/12*$B62/2+SUM($E$60/12/2*B62) -> 848.853 | L62: =SUM($E$60)/12*0.9 -> 1005.75 | M62: =SUM($E$60)/12*0.9 -> 1005.75 | N62: =SUM($E$60)/12*0.9 -> 1005.75 | O62: =SUM($E$60)/12*0.9 -> 1005.75 | P62: =SUM($E$60)/12*0.9 -> 1005.75 | Q62: =SUM($E$60)/12*0.9 -> 1005.75 | R62: =SUM($E$60)/12*0.9 -> 1005.75 | S62: =SUM(G62:R62) -> 12668.427
A63: Youtube | G63: =SUM($C$60:$D$60)/12*$B63 -> 0 | H63: =SUM($C$60:$D$60)/12*$B63 -> 0 | I63: =SUM($C$60:$D$60)/12*$B63 -> 0 | J63: =SUM($C$60:$D$60)/12*$B63 -> 0 | K63: 0 | L63: 0 | M63: 0 | N63: 0 | O63: 0 | P63: 0 | Q63: 0 | R63: 0 | S63: =SUM(G63:R63) -> 0
A64: Instagram | G64: =SUM($C$60:$D$60)/12*$B64 -> 0 | H64: =SUM($C$60:$D$60)/12*$B64 -> 0 | I64: =SUM($C$60:$D$60)/12*$B64 -> 0 | J64: =SUM($C$60:$D$60)/12*$B64 -> 0 | K64: 0 | L64: 0 | M64: 0 | N64: 0 | O64: 0 | P64: 0 | Q64: 0 | R64: 0 | S64: =SUM(G64:R64) -> 0
A65: TikTok | G65: =SUM($C$60:$D$60)/12*$B65 -> 0 | H65: =SUM($C$60:$D$60)/12*$B65 -> 0 | I65: =SUM($C$60:$D$60)/12*$B65 -> 0 | J65: =SUM($C$60:$D$60)/12*$B65 -> 0 | K65: 0 | L65: 0 | M65: 0 | N65: 0 | O65: 0 | P65: 0 | Q65: 0 | R65: 0 | S65: =SUM(G65:R65) -> 0
A66: X | G66: =SUM($C$60:$D$60)/12*$B66 -> 0 | H66: =SUM($C$60:$D$60)/12*$B66 -> 0 | I66: =SUM($C$60:$D$60)/12*$B66 -> 0 | J66: =SUM($C$60:$D$60)/12*$B66 -> 0 | K66: 0 | L66: 0 | M66: 0 | N66: 0 | O66: 0 | P66: 0 | Q66: 0 | R66: 0 | S66: =SUM(G66:R66) -> 0
A67: B2B | G67: =SUM($C$60:$D$60)/12*$B67 -> 0 | H67: =SUM($C$60:$D$60)/12*$B67 -> 0 | I67: =SUM($C$60:$D$60)/12*$B67 -> 0 | J67: =SUM($C$60:$D$60)/12*$B67 -> 0 | K67: 0 | L67: 0 | M67: 0 | N67: 0 | O67: 0 | P67: 0 | Q67: 0 | R67: 0 | S67: =SUM(G67:R67) -> 0
A68: Website | B68: 0.45 | G68: =SUM($C$60:$D$60)/12*$B68 -> 1194.831 | H68: =SUM($C$60:$D$60)/12*$B68 -> 1194.831 | I68: =SUM($C$60:$D$60)/12*$B68 -> 1194.831 | J68: =SUM($C$60:$D$60)/12*$B68 -> 1194.831 | K68: =SUM($C$60:$D$60)/12*$B68/2+SUM($E$60/12/2*B68) -> 848.853 | L68: 0 | M68: 0 | N68: 0 | O68: 0 | P68: 0 | Q68: 0 | R68: 0 | S68: =SUM(G68:R68) -> 5628.177
A69: Recharge | B69: -0.5 | G69: =SUM($C$60)/12*$B69 -> -1117.5 | H69: =SUM($C$60)/12*$B69 -> -1117.5 | I69: =SUM($C$60)/12*$B69 -> -1117.5 | J69: =SUM($C$60)/12*$B69 -> -1117.5 | K69: =SUM($C$60)/12*$B69/2+SUM($E$60/12/2*B69) -> -838.125 | L69: 0 | M69: 0 | N69: 0 | O69: 0 | P69: 0 | Q69: 0 | R69: 0 | S69: =SUM(G69:R69) -> -5308.125
A70: Total | G70: =SUM(G61:G69) -> 1272.162 | H70: =SUM(H61:H69) -> 1272.162 | I70: =SUM(I61:I69) -> 1272.162 | J70: =SUM(J61:J69) -> 1272.162 | K70: =SUM(K61:K69) -> 859.581 | L70: =SUM(L61:L69) -> 1005.75 | M70: =SUM(M61:M69) -> 1005.75 | N70: =SUM(N61:N69) -> 1005.75 | ... R70: =SUM(R61:R69) -> 1005.75 | S70: =SUM(S61:S67) -> 12668.427
A72: PSM Recharge | B72: 0.1 | G72: =SUM($C$60:$D$60)/12*$B72 -> 265.518 | H72: =SUM($C$60:$D$60)/12*$B72 -> 265.518 | I72: =SUM($C$60:$D$60)/12*$B72 -> 265.518 | J72: =SUM($C$60:$D$60)/12*$B72 -> 265.518 | K72: =SUM($C$60:$D$60)/12*$B72/2+SUM($E$60/12/2*B72) -> 188.634 | L72: =SUM($E$60)/12*0.1 -> 111.75 | M72: =SUM($E$60)/12*0.1 -> 111.75 | N72: =SUM($E$60)/12*0.1 -> 111.75 | O72: =SUM($E$60)/12*0.1 -> 111.75 | P72: =SUM($E$60)/12*0.1 -> 111.75 | Q72: =SUM($E$60)/12*0.1 -> 111.75 | R72: =SUM($E$60)/12*0.1 -> 111.75 | S72: =SUM(G72:R72) -> 2032.956
A74: Oscar Pick | C74: 26000 | D74: =C74*0.188 -> 4888 | E74: =C74/2 -> 13000
A75: Facebook | G75: =SUM($C$74:$D$74)/12*$B75 -> 0 | H75: =SUM($C$74:$D$74)/12*$B75 -> 0 | I75: =SUM($C$74:$D$74)/12*$B75 -> 0 | J75: =SUM($C$74:$D$74)/12*$B75 -> 0 | K75: =SUM($C$74:$D$74)/12*$B75/2+SUM($E$74/12/2*B75) -> 0 | L75: =SUM($E$74)/12*$B75 -> 0 | M75: =SUM($E$74)/12*$B75 -> 0 | N75: =SUM($E$74)/12*$B75 -> 0 | O75: =SUM($E$74)/12*$B75 -> 0 | P75: =SUM($E$74)/12*$B75 -> 0 | Q75: =SUM($E$74)/12*$B75 -> 0 | R75: =SUM($E$74)/12*$B75 -> 0 | S75: =SUM(G75:R75) -> 0
A76: Magazine | B76: 0.5 | G76: =SUM($C$74:$D$74)/12*$B76 -> 1287 | H76: =SUM($C$74:$D$74)/12*$B76 -> 1287 | I76: =SUM($C$74:$D$74)/12*$B76 -> 1287 | J76: =SUM($C$74:$D$74)/12*$B76 -> 1287 | K76: =SUM($C$74:$D$74)/12*$B76/2+SUM($E$74/12/2*B76) -> 914.33333 | L76: =SUM($E$74)/12*$B76 -> 541.66667 | M76: =SUM($E$74)/12*$B76 -> 541.66667 | N76: =SUM($E$74)/12*$B76 -> 541.66667 | O76: =SUM($E$74)/12*$B76 -> 541.66667 | P76: =SUM($E$74)/12*$B76 -> 541.66667 | Q76: =SUM($E$74)/12*$B76 -> 541.66667 | R76: =SUM($E$74)/12*$B76 -> 541.66667 | S76: =SUM(G76:R76) -> 9854
A77: Youtube | G77: =SUM($C$74:$D$74)/12*$B77 -> 0 | H77: =SUM($C$74:$D$74)/12*$B77 -> 0 | I77: =SUM($C$74:$D$74)/12*$B77 -> 0 | J77: =SUM($C$74:$D$74)/12*$B77 -> 0 | K77: =SUM($C$74:$D$74)/12*$B77/2+SUM($E$74/12/2*B77) -> 0 | L77: =SUM($E$74)/12*$B77 -> 0 | M77: =SUM($E$74)/12*$B77 -> 0 | N77: =SUM($E$74)/12*$B77 -> 0 | O77: =SUM($E$74)/12*$B77 -> 0 | P77: =SUM($E$74)/12*$B77 -> 0 | Q77: =SUM($E$74)/12*$B77 -> 0 | R77: =SUM($E$74)/12*$B77 -> 0 | S77: =SUM(G77:R77) -> 0
A78: Instagram | G78: =SUM($C$74:$D$74)/12*$B78 -> 0 | H78: =SUM($C$74:$D$74)/12*$B78 -> 0 | I78: =SUM($C$74:$D$74)/12*$B78 -> 0 | J78: =SUM($C$74:$D$74)/12*$B78 -> 0 | K78: =SUM($C$74:$D$74)/12*$B78/2+SUM($E$74/12/2*B78) -> 0 | L78: =SUM($E$74)/12*$B78 -> 0 | M78: =SUM($E$74)/12*$B78 -> 0 | N78: =SUM($E$74)/12*$B78 -> 0 | O78: =SUM($E$74)/12*$B78 -> 0 | P78: =SUM($E$74)/12*$B78 -> 0 | Q78: =SUM($E$74)/12*$B78 -> 0 | R78: =SUM($E$74)/12*$B78 -> 0 | S78: =SUM(G78:R78) -> 0
A79: TikTok | G79: =SUM($C$74:$D$74)/12*$B79 -> 0 | H79: =SUM($C$74:$D$74)/12*$B79 -> 0 | I79: =SUM($C$74:$D$74)/12*$B79 -> 0 | J79: =SUM($C$74:$D$74)/12*$B79 -> 0 | K79: =SUM($C$74:$D$74)/12*$B79/2+SUM($E$74/12/2*B79) -> 0 | L79: =SUM($E$74)/12*$B79 -> 0 | M79: =SUM($E$74)/12*$B79 -> 0 | N79: =SUM($E$74)/12*$B79 -> 0 | O79: =SUM($E$74)/12*$B79 -> 0 | P79: =SUM($E$74)/12*$B79 -> 0 | Q79: =SUM($E$74)/12*$B79 -> 0 | R79: =SUM($E$74)/12*$B79 -> 0 | S79: =SUM(G79:R79) -> 0
A80: X | G80: =SUM($C$74:$D$74)/12*$B80 -> 0 | H80: =SUM($C$74:$D$74)/12*$B80 -> 0 | I80: =SUM($C$74:$D$74)/12*$B80 -> 0 | J80: =SUM($C$74:$D$74)/12*$B80 -> 0 | K80: =SUM($C$74:$D$74)/12*$B80/2+SUM($E$74/12/2*B80) -> 0 | L80: =SUM($E$74)/12*$B80 -> 0 | M80: =SUM($E$74)/12*$B80 -> 0 | N80: =SUM($E$74)/12*$B80 -> 0 | O80: =SUM($E$74)/12*$B80 -> 0 | P80: =SUM($E$74)/12*$B80 -> 0 | Q80: =SUM($E$74)/12*$B80 -> 0 | R80: =SUM($E$74)/12*$B80 -> 0 | S80: =SUM(G80:R80) -> 0
A81: B2B | G81: =SUM($C$74:$D$74)/12*$B81 -> 0 | H81: =SUM($C$74:$D$74)/12*$B81 -> 0 | I81: =SUM($C$74:$D$74)/12*$B81 -> 0 | J81: =SUM($C$74:$D$74)/12*$B81 -> 0 | K81: =SUM($C$74:$D$74)/12*$B81/2+SUM($E$74/12/2*B81) -> 0 | L81: =SUM($E$74)/12*$B81 -> 0 | M81: =SUM($E$74)/12*$B81 -> 0 | N81: =SUM($E$74)/12*$B81 -> 0 | O81: =SUM($E$74)/12*$B81 -> 0 | P81: =SUM($E$74)/12*$B81 -> 0 | Q81: =SUM($E$74)/12*$B81 -> 0 | R81: =SUM($E$74)/12*$B81 -> 0 | S81: =SUM(G81:R81) -> 0
A82: Website | B82: 0.5 | G82: =SUM($C$74:$D$74)/12*$B82 -> 1287 | H82: =SUM($C$74:$D$74)/12*$B82 -> 1287 | I82: =SUM($C$74:$D$74)/12*$B82 -> 1287 | J82: =SUM($C$74:$D$74)/12*$B82 -> 1287 | K82: =SUM($C$74:$D$74)/12*$B82/2+SUM($E$74/12/2*B82) -> 914.33333 | L82: =SUM($E$74)/12*$B82 -> 541.66667 | M82: =SUM($E$74)/12*$B82 -> 541.66667 | N82: =SUM($E$74)/12*$B82 -> 541.66667 | O82: =SUM($E$74)/12*$B82 -> 541.66667 | P82: =SUM($E$74)/12*$B82 -> 541.66667 | Q82: =SUM($E$74)/12*$B82 -> 541.66667 | R82: =SUM($E$74)/12*$B82 -> 541.66667 | S82: =SUM(G82:R82) -> 9854
A83: Recharge | B83: -0.5 | G83: =SUM($C$74)/12*$B83 -> -1083.3333 | H83: =SUM($C$74)/12*$B83 -> -1083.3333 | I83: =SUM($C$74)/12*$B83 -> -1083.3333 | J83: =SUM($C$74)/12*$B83 -> -1083.3333 | K83: =SUM($C$74)/12*$B83/2+SUM($E$74/12/2*B83) -> -812.5 | L83: 0 | M83: 0 | N83: 0 | O83: 0 | P83: 0 | Q83: 0 | R83: 0 | S83: =SUM(G83:R83) -> -5145.8333
A84: Total | G84: =SUM(G75:G83) -> 1490.6667 | H84: =SUM(H75:H83) -> 1490.6667 | I84: =SUM(I75:I83) -> 1490.6667 | J84: =SUM(J75:J83) -> 1490.6667 | K84: =SUM(K75:K83) -> 1016.1667 | L84: =SUM(L75:L83) -> 1083.3333 | M84: =SUM(M75:M83) -> 1083.3333 | N84: =SUM(N75:N83) -> 1083.3333 | ... R84: =SUM(R75:R83) -> 1083.3333 | S84: =SUM(S75:S81) -> 9854
G88: =G12+G23+G33+G45+G58+G70+G84 -> 18781.029 | H88: =H12+H23+H33+H45+H58+H70+H84 -> 18781.029 | I88: =I12+I23+I33+I45+I58+I70+I84 -> 18781.029 | J88: =J12+J23+J33+J45+J58+J70+J84 -> 21157.029 | K88: =K12+K23+K33+K45+K58+K70+K84 -> 17893.948 | L88: =L12+L23+L33+L45+L58+L70+L84 -> 13011.083 | M88: =M12+M23+M33+M45+M58+M70+M84 -> 11526.083 | N88: =N12+N23+N33+N45+N58+N70+N84 -> 11526.083 | ... R88: =R12+R23+R33+R45+R58+R70+R84 -> 11526.083
G89: =SUM(G5+G16+G27+G39+G52+G62+G76)*-1 -> -6535.881 | H89: =SUM(H5+H16+H27+H39+H52+H62+H76)*-1 -> -6535.881 | I89: =SUM(I5+I16+I27+I39+I52+I62+I76)*-1 -> -6535.881 | J89: =SUM(J5+J16+J27+J39+J52+J62+J76)*-1 -> -6595.281 | K89: =SUM(K5+K16+K27+K39+K52+K62+K76)*-1 -> -5817.2363 | L89: =SUM(L5+L16+L27+L39+L52+L62+L76)*-1 -> -4383.9667 | M89: =SUM(M5+M16+M27+M39+M52+M62+M76)*-1 -> -3641.4667 | N89: =SUM(N5+N16+N27+N39+N52+N62+N76)*-1 -> -3641.4667 | ... R89: =SUM(R5+R16+R27+R39+R52+R62+R76)*-1 -> -3641.4667
G90: =SUM(G88:G89) -> 12245.148 | H90: =SUM(H88:H89) -> 12245.148 | I90: =SUM(I88:I89) -> 12245.148 | J90: =SUM(J88:J89) -> 14561.748 | K90: =SUM(K88:K89) -> 12076.711 | L90: =SUM(L88:L89) -> 8627.1167 | M90: =SUM(M88:M89) -> 7884.6167 | N90: =SUM(N88:N89) -> 7884.6167 | ... R90: =SUM(R88:R89) -> 7884.6167
H93: FY | I93: =95000+16000 -> 111000

Sheet M2 Freelancers
C1: Actuals | D1: Actuals | E1: Forecast | F1: Forecast | G1: Forecast | H1: Forecast | I1: Forecast | J1: Forecast | K1: Forecast | L1: Forecast | M1: Forecast | N1: Forecast
A2: Employee Name | B2: Allocation | C2: 45931 | D2: 45962 | E2: 45992 | F2: 46023 | G2: 46054 | H2: 46082 | I2: 46113 | J2: 46143 | K2: 46174 | L2: 46204 | M2: 46235 | N2: 46266 | O2: FY26
B3: =30000/12 -> 2500
A5: Facebook | B5: =0.5/3 -> 0.16666667 | I5: =$B$3*$B5 -> 416.66667 | J5: =$B$3*$B5 -> 416.66667 | K5: =$B$3*$B5 -> 416.66667 | L5: =$B$3*$B5 -> 416.66667 | M5: =$B$3*$B5 -> 416.66667 | N5: =$B$3*$B5 -> 416.66667 | O5: =SUM(C5:N5) -> 2500
A6: Instagram | B6: =0.5/3 -> 0.16666667 | I6: =$B$3*$B6 -> 416.66667 | J6: =$B$3*$B6 -> 416.66667 | K6: =$B$3*$B6 -> 416.66667 | L6: =$B$3*$B6 -> 416.66667 | M6: =$B$3*$B6 -> 416.66667 | N6: =$B$3*$B6 -> 416.66667 | O6: =SUM(C6:N6) -> 2500
A7: TikTok | B7: =0.5/3 -> 0.16666667 | I7: =$B$3*$B7 -> 416.66667 | J7: =$B$3*$B7 -> 416.66667 | K7: =$B$3*$B7 -> 416.66667 | L7: =$B$3*$B7 -> 416.66667 | M7: =$B$3*$B7 -> 416.66667 | N7: =$B$3*$B7 -> 416.66667 | O7: =SUM(C7:N7) -> 2500
A8: Youtube | B8: 0.5 | I8: =$B$3*$B8 -> 1250 | J8: =$B$3*$B8 -> 1250 | K8: =$B$3*$B8 -> 1250 | L8: =$B$3*$B8 -> 1250 | M8: =$B$3*$B8 -> 1250 | N8: =$B$3*$B8 -> 1250 | O8: =SUM(C8:N8) -> 7500
A10: Total | C10: =SUM(C5:C9) -> 0 | D10: =SUM(D5:D9) -> 0 | E10: =SUM(E5:E9) -> 0 | F10: =SUM(F5:F9) -> 0 | G10: =SUM(G5:G9) -> 0 | H10: =SUM(H5:H9) -> 0 | I10: =SUM(I5:I9) -> 2500 | J10: =SUM(J5:J9) -> 2500 | ... O10: =SUM(O5:O9) -> 15000

Sheet M3 Staff costs
C1: Current | E1: Proposed | G1: Actuals | H1: Actuals | I1: Forecast | J1: Forecast | K1: Forecast | L1: Forecast | M1: Forecast | N1: Forecast | O1: Forecast | P1: Forecast | Q1: Forecast | R1: Forecast
A2: Employee Name | B2: Allocation | C2: Gross Salary | D2: NI + Pension | E2: Bonus | F2: NI + Pension | G2: 45931 | H2: 45962 | I2: 45992 | J2: 46023 | K2: 46054 | L2: 46082 | M2: 46113 | N2: 46143 | O2: 46174 | P2: 46204 | Q2: 46235 | R2: 46266 | S2: FY26
A3: Ryan Elliot | C3: 38000 | D3: =C3*0.188 -> 7144 | E3: 2000 | F3: =E3*0.188 -> 376
A4: Facebook | B4: 0.25 | G4: =SUM($C$3:$D$3)/12*$B4 -> 940.5 | H4: =SUM($C$3:$D$3)/12*$B4 -> 940.5 | I4: =SUM($C$3:$D$3)/12*$B4 -> 940.5 | J4: =SUM($C$3:$D$3)/12*$B4+SUM($E$3:$F$3)*$B4 -> 1534.5 | K4: =SUM($C$3:$D$3)/12*$B4 -> 940.5 | L4: =SUM($C$3:$D$3)/12*$B4 -> 940.5 | M4: =SUM($C$3:$D$3)/12*$B4 -> 940.5 | N4: =SUM($C$3:$D$3)/12*$B4 -> 940.5 | O4: =SUM($C$3:$D$3)/12*$B4 -> 940.5 | P4: =SUM($C$3:$D$3)/12*$B4 -> 940.5 | Q4: =SUM($C$3:$D$3)/12*$B4 -> 940.5 | R4: =SUM($C$3:$D$3)/12*$B4 -> 940.5 | S4: =SUM(G4:R4) -> 11880
A5: Magazine | B5: 0.025 | G5: =SUM($C$3:$D$3)/12*$B5 -> 94.05 | H5: =SUM($C$3:$D$3)/12*$B5 -> 94.05 | I5: =SUM($C$3:$D$3)/12*$B5 -> 94.05 | J5: =SUM($C$3:$D$3)/12*$B5+SUM($E$3:$F$3)*$B5 -> 153.45 | K5: =SUM($C$3:$D$3)/12*$B5 -> 94.05 | L5: =SUM($C$3:$D$3)/12*$B5 -> 94.05 | M5: =SUM($C$3:$D$3)/12*$B5 -> 94.05 | N5: =SUM($C$3:$D$3)/12*$B5 -> 94.05 | O5: =SUM($C$3:$D$3)/12*$B5 -> 94.05 | P5: =SUM($C$3:$D$3)/12*$B5 -> 94.05 | Q5: =SUM($C$3:$D$3)/12*$B5 -> 94.05 | R5: =SUM($C$3:$D$3)/12*$B5 -> 94.05 | S5: =SUM(G5:R5) -> 1188
A6: Youtube | B6: 0.25 | G6: =SUM($C$3:$D$3)/12*$B6 -> 940.5 | H6: =SUM($C$3:$D$3)/12*$B6 -> 940.5 | I6: =SUM($C$3:$D$3)/12*$B6 -> 940.5 | J6: =SUM($C$3:$D$3)/12*$B6+SUM($E$3:$F$3)*$B6 -> 1534.5 | K6: =SUM($C$3:$D$3)/12*$B6 -> 940.5 | L6: =SUM($C$3:$D$3)/12*$B6 -> 940.5 | M6: =SUM($C$3:$D$3)/12*$B6 -> 940.5 | N6: =SUM($C$3:$D$3)/12*$B6 -> 940.5 | O6: =SUM($C$3:$D$3)/12*$B6 -> 940.5 | P6: =SUM($C$3:$D$3)/12*$B6 -> 940.5 | Q6: =SUM($C$3:$D$3)/12*$B6 -> 940.5 | R6: =SUM($C$3:$D$3)/12*$B6 -> 940.5 | S6: =SUM(G6:R6) -> 11880
A7: Instagram | B7: 0.25 | G7: =SUM($C$3:$D$3)/12*$B7 -> 940.5 | H7: =SUM($C$3:$D$3)/12*$B7 -> 940.5 | I7: =SUM($C$3:$D$3)/12*$B7 -> 940.5 | J7: =SUM($C$3:$D$3)/12*$B7+SUM($E$3:$F$3)*$B7 -> 1534.5 | K7: =SUM($C$3:$D$3)/12*$B7 -> 940.5 | L7: =SUM($C$3:$D$3)/12*$B7 -> 940.5 | M7: =SUM($C$3:$D$3)/12*$B7 -> 940.5 | N7: =SUM($C$3:$D$3)/12*$B7 -> 940.5 | O7: =SUM($C$3:$D$3)/12*$B7 -> 940.5 | P7: =SUM($C$3:$D$3)/12*$B7 -> 940.5 | Q7: =SUM($C$3:$D$3)/12*$B7 -> 940.5 | R7: =SUM($C$3:$D$3)/12*$B7 -> 940.5 | S7: =SUM(G7:R7) -> 11880
A8: TikTok | B8: 0.05 | G8: =SUM($C$3:$D$3)/12*$B8 -> 188.1 | H8: =SUM($C$3:$D$3)/12*$B8 -> 188.1 | I8: =SUM($C$3:$D$3)/12*$B8 -> 188.1 | J8: =SUM($C$3:$D$3)/12*$B8+SUM($E$3:$F$3)*$B8 -> 306.9 | K8: =SUM($C$3:$D$3)/12*$B8 -> 188.1 | L8: =SUM($C$3:$D$3)/12*$B8 -> 188.1 | M8: =SUM($C$3:$D$3)/12*$B8 -> 188.1 | N8: =SUM($C$3:$D$3)/12*$B8 -> 188.1 | O8: =SUM($C$3:$D$3)/12*$B8 -> 188.1 | P8: =SUM($C$3:$D$3)/12*$B8 -> 188.1 | Q8: =SUM($C$3:$D$3)/12*$B8 -> 188.1 | R8: =SUM($C$3:$D$3)/12*$B8 -> 188.1 | S8: =SUM(G8:R8) -> 2376
A9: X | B9: 0.1 | G9: =SUM($C$3:$D$3)/12*$B9 -> 376.2 | H9: =SUM($C$3:$D$3)/12*$B9 -> 376.2 | I9: =SUM($C$3:$D$3)/12*$B9 -> 376.2 | J9: =SUM($C$3:$D$3)/12*$B9+SUM($E$3:$F$3)*$B9 -> 613.8 | K9: =SUM($C$3:$D$3)/12*$B9 -> 376.2 | L9: =SUM($C$3:$D$3)/12*$B9 -> 376.2 | M9: =SUM($C$3:$D$3)/12*$B9 -> 376.2 | N9: =SUM($C$3:$D$3)/12*$B9 -> 376.2 | O9: =SUM($C$3:$D$3)/12*$B9 -> 376.2 | P9: =SUM($C$3:$D$3)/12*$B9 -> 376.2 | Q9: =SUM($C$3:$D$3)/12*$B9 -> 376.2 | R9: =SUM($C$3:$D$3)/12*$B9 -> 376.2 | S9: =SUM(G9:R9) -> 4752
A10: B2B | B10: 0.075 | G10: =SUM($C$3:$D$3)/12*$B10 -> 282.15 | H10: =SUM($C$3:$D$3)/12*$B10 -> 282.15 | I10: =SUM($C$3:$D$3)/12*$B10 -> 282.15 | J10: =SUM($C$3:$D$3)/12*$B10+SUM($E$3:$F$3)*$B10 -> 460.35 | K10: =SUM($C$3:$D$3)/12*$B10 -> 282.15 | L10: =SUM($C$3:$D$3)/12*$B10 -> 282.15 | M10: =SUM($C$3:$D$3)/12*$B10 -> 282.15 | N10: =SUM($C$3:$D$3)/12*$B10 -> 282.15 | O10: =SUM($C$3:$D$3)/12*$B10 -> 282.15 | P10: =SUM($C$3:$D$3)/12*$B10 -> 282.15 | Q10: =SUM($C$3:$D$3)/12*$B10 -> 282.15 | R10: =SUM($C$3:$D$3)/12*$B10 -> 282.15 | S10: =SUM(G10:R10) -> 3564
A12: Total | G12: =SUM(G4:G11) -> 3762 | H12: =SUM(H4:H11) -> 3762 | I12: =SUM(I4:I11) -> 3762 | J12: =SUM(J4:J11) -> 6138 | K12: =SUM(K4:K11) -> 3762 | L12: =SUM(L4:L11) -> 3762 | M12: =SUM(M4:M11) -> 3762 | N12: =SUM(N4:N11) -> 3762 | ... S12: =SUM(S4:S11) -> 47520
S13: =S12-F3-E3-D3-C3 -> 0
A14: Danny Gilfilen | C14: 25000 | D14: =C14*0.188 -> 4700
A15: Facebook | B15: 0.3 | G15: =SUM($C$14:$D$14)/12*$B15 -> 742.5 | H15: =SUM($C$14:$D$14)/12*$B15 -> 742.5 | I15: =SUM($C$14:$D$14)/12*$B15 -> 742.5 | J15: =SUM($C$14:$D$14)/12*$B15 -> 742.5 | K15: =SUM($C$14:$D$14)/12*$B15 -> 742.5 | L15: =SUM($C$14:$D$14)/12*$B15 -> 742.5 | M15: =SUM($C$14:$D$14)/12*$B15 -> 742.5 | N15: =SUM($C$14:$D$14)/12*$B15 -> 742.5 | ... R15: =SUM($C$14:$D$14)/12*$B15 -> 742.5 | S15: =SUM(G15:R15) -> 8910
A16: Magazine | B16: 0 | G16: =SUM($C$14:$D$14)/12*$B16 -> 0 | H16: =SUM($C$14:$D$14)/12*$B16 -> 0 | I16: =SUM($C$14:$D$14)/12*$B16 -> 0 | J16: =SUM($C$14:$D$14)/12*$B16 -> 0 | K16: =SUM($C$14:$D$14)/12*$B16 -> 0 | L16: =SUM($C$14:$D$14)/12*$B16 -> 0 | M16: =SUM($C$14:$D$14)/12*$B16 -> 0 | N16: =SUM($C$14:$D$14)/12*$B16 -> 0 | ... R16: =SUM($C$14:$D$14)/12*$B16 -> 0 | S16: =SUM(G16:R16) -> 0
A17: Youtube | B17: 0.3 | G17: =SUM($C$14:$D$14)/12*$B17 -> 742.5 | H17: =SUM($C$14:$D$14)/12*$B17 -> 742.5 | I17: =SUM($C$14:$D$14)/12*$B17 -> 742.5 | J17: =SUM($C$14:$D$14)/12*$B17 -> 742.5 | K17: =SUM($C$14:$D$14)/12*$B17 -> 742.5 | L17: =SUM($C$14:$D$14)/12*$B17 -> 742.5 | M17: =SUM($C$14:$D$14)/12*$B17 -> 742.5 | N17: =SUM($C$14:$D$14)/12*$B17 -> 742.5 | ... R17: =SUM($C$14:$D$14)/12*$B17 -> 742.5 | S17: =SUM(G17:R17) -> 8910
A18: Instagram | B18: 0.175 | G18: =SUM($C$14:$D$14)/12*$B18 -> 433.125 | H18: =SUM($C$14:$D$14)/12*$B18 -> 433.125 | I18: =SUM($C$14:$D$14)/12*$B18 -> 433.125 | J18: =SUM($C$14:$D$14)/12*$B18 -> 433.125 | K18: =SUM($C$14:$D$14)/12*$B18 -> 433.125 | L18: =SUM($C$14:$D$14)/12*$B18 -> 433.125 | M18: =SUM($C$14:$D$14)/12*$B18 -> 433.125 | N18: =SUM($C$14:$D$14)/12*$B18 -> 433.125 | ... R18: =SUM($C$14:$D$14)/12*$B18 -> 433.125 | S18: =SUM(G18:R18) -> 5197.5
A19: TikTok | B19: 0.175 | G19: =SUM($C$14:$D$14)/12*$B19 -> 433.125 | H19: =SUM($C$14:$D$14)/12*$B19 -> 433.125 | I19: =SUM($C$14:$D$14)/12*$B19 -> 433.125 | J19: =SUM($C$14:$D$14)/12*$B19 -> 433.125 | K19: =SUM($C$14:$D$14)/12*$B19 -> 433.125 | L19: =SUM($C$14:$D$14)/12*$B19 -> 433.125 | M19: =SUM($C$14:$D$14)/12*$B19 -> 433.125 | N19: =SUM($C$14:$D$14)/12*$B19 -> 433.125 | ... R19: =SUM($C$14:$D$14)/12*$B19 -> 433.125 | S19: =SUM(G19:R19) -> 5197.5
A20: X | B20: 0.05 | G20: =SUM($C$14:$D$14)/12*$B20 -> 123.75 | H20: =SUM($C$14:$D$14)/12*$B20 -> 123.75 | I20: =SUM($C$14:$D$14)/12*$B20 -> 123.75 | J20: =SUM($C$14:$D$14)/12*$B20 -> 123.75 | K20: =SUM($C$14:$D$14)/12*$B20 -> 123.75 | L20: =SUM($C$14:$D$14)/12*$B20 -> 123.75 | M20: =SUM($C$14:$D$14)/12*$B20 -> 123.75 | N20: =SUM($C$14:$D$14)/12*$B20 -> 123.75 | ... R20: =SUM($C$14:$D$14)/12*$B20 -> 123.75 | S20: =SUM(G20:R20) -> 1485
A21: B2B | B21: 0 | G21: =SUM($C$14:$D$14)/12*$B21 -> 0 | H21: =SUM($C$14:$D$14)/12*$B21 -> 0 | I21: =SUM($C$14:$D$14)/12*$B21 -> 0 | J21: =SUM($C$14:$D$14)/12*$B21 -> 0 | K21: =SUM($C$14:$D$14)/12*$B21 -> 0 | L21: =SUM($C$14:$D$14)/12*$B21 -> 0 | M21: =SUM($C$14:$D$14)/12*$B21 -> 0 | N21: =SUM($C$14:$D$14)/12*$B21 -> 0 | ... R21: =SUM($C$14:$D$14)/12*$B21 -> 0 | S21: =SUM(G21:R21) -> 0
A23: Total | G23: =SUM(G15:G22) -> 2475 | H23: =SUM(H15:H22) -> 2475 | I23: =SUM(I15:I22) -> 2475 | J23: =SUM(J15:J22) -> 2475 | K23: =SUM(K15:K22) -> 2475 | L23: =SUM(L15:L22) -> 2475 | M23: =SUM(M15:M22) -> 2475 | N23: =SUM(N15:N22) -> 2475 | ... S23: =SUM(S15:S22) -> 29700
S24: =S23-C14-D14 -> 0
A25: Daniel Greg | C25: 36000 | D25: =C25*0.188 -> 6768
A26: Facebook | B26: 0.1 | G26: =SUM($C$25:$D$25)/12*$B26 -> 356.4 | H26: =SUM($C$25:$D$25)/12*$B26 -> 356.4 | I26: =SUM($C$25:$D$25)/12*$B26 -> 356.4 | J26: =SUM($C$25:$D$25)/12*$B26 -> 356.4 | K26: =SUM($C$25:$D$25)/12*$B26 -> 356.4 | S26: =SUM(G26:R26) -> 1782
A27: Magazine | B27: 0 | G27: =SUM($C$25:$D$25)/12*$B27 -> 0 | H27: =SUM($C$25:$D$25)/12*$B27 -> 0 | I27: =SUM($C$25:$D$25)/12*$B27 -> 0 | J27: =SUM($C$25:$D$25)/12*$B27 -> 0 | K27: =SUM($C$25:$D$25)/12*$B27 -> 0 | S27: =SUM(G27:R27) -> 0
A28: Youtube | B28: 0.6 | G28: =SUM($C$25:$D$25)/12*$B28 -> 2138.4 | H28: =SUM($C$25:$D$25)/12*$B28 -> 2138.4 | I28: =SUM($C$25:$D$25)/12*$B28 -> 2138.4 | J28: =SUM($C$25:$D$25)/12*$B28 -> 2138.4 | K28: =SUM($C$25:$D$25)/12*$B28 -> 2138.4 | S28: =SUM(G28:R28) -> 10692
A29: Instagram | B29: 0.05 | G29: =SUM($C$25:$D$25)/12*$B29 -> 178.2 | H29: =SUM($C$25:$D$25)/12*$B29 -> 178.2 | I29: =SUM($C$25:$D$25)/12*$B29 -> 178.2 | J29: =SUM($C$25:$D$25)/12*$B29 -> 178.2 | K29: =SUM($C$25:$D$25)/12*$B29 -> 178.2 | S29: =SUM(G29:R29) -> 891
A30: TikTok | B30: 0.05 | G30: =SUM($C$25:$D$25)/12*$B30 -> 178.2 | H30: =SUM($C$25:$D$25)/12*$B30 -> 178.2 | I30: =SUM($C$25:$D$25)/12*$B30 -> 178.2 | J30: =SUM($C$25:$D$25)/12*$B30 -> 178.2 | K30: =SUM($C$25:$D$25)/12*$B30 -> 178.2 | S30: =SUM(G30:R30) -> 891
A31: X | B31: 0 | G31: =SUM($C$25:$D$25)/12*$B31 -> 0 | H31: =SUM($C$25:$D$25)/12*$B31 -> 0 | I31: =SUM($C$25:$D$25)/12*$B31 -> 0 | J31: =SUM($C$25:$D$25)/12*$B31 -> 0 | K31: =SUM($C$25:$D$25)/12*$B31 -> 0 | S31: =SUM(G31:R31) -> 0
A32: B2B | B32: 0 | G32: =SUM($C$25:$D$25)/12*$B32 -> 0 | H32: =SUM($C$25:$D$25)/12*$B32 -> 0 | I32: =SUM($C$25:$D$25)/12*$B32 -> 0 | J32: =SUM($C$25:$D$25)/12*$B32 -> 0 | K32: =SUM($C$25:$D$25)/12*$B32 -> 0 | S32: =SUM(G32:R32) -> 0
A33: Total | G33: =SUM(G26:G32) -> 2851.2 | H33: =SUM(H26:H32) -> 2851.2 | I33: =SUM(I26:I32) -> 2851.2 | J33: =SUM(J26:J32) -> 2851.2 | K33: =SUM(K26:K32) -> 2851.2 | L33: =SUM(L26:L32) -> 0 | M33: =SUM(M26:M32) -> 0 | N33: =SUM(N26:N32) -> 0 | ... S33: =SUM(S26:S32) -> 14256
A35: PSM Recharge | B35: 0.2 | G35: =SUM($C$25:$D$25)/12*$B35 -> 712.8 | H35: =SUM($C$25:$D$25)/12*$B35 -> 712.8 | I35: =SUM($C$25:$D$25)/12*$B35 -> 712.8 | J35: =SUM($C$25:$D$25)/12*$B35 -> 712.8 | K35: =SUM($C$25:$D$25)/12*$B35 -> 712.8 | S35: =SUM(G35:R35) -> 3564
A37: Nick Bond | C37: 50000 | D37: =C37*0.188 -> 9400 | E37: =4000*12 -> 48000
A38: Facebook | B38: 0 | G38: =SUM($C$37:$D$37)/12*$B38 -> 0 | H38: =SUM($C$37:$D$37)/12*$B38 -> 0 | I38: =SUM($C$37:$D$37)/12*$B38 -> 0 | J38: =SUM($C$37:$D$37)/12*$B38 -> 0 | K38: =SUM($C$37:$D$37)/12*$B38 -> 0 | L38: =SUM($E$37)/12*$B38 -> 0 | M38: =SUM($E$37)/12*$B38 -> 0 | N38: =SUM($E$37)/12*$B38 -> 0 | O38: =SUM($E$37)/12*$B38 -> 0 | P38: =SUM($E$37)/12*$B38 -> 0 | Q38: =SUM($E$37)/12*$B38 -> 0 | R38: =SUM($E$37)/12*$B38 -> 0 | S38: =SUM(G38:R38) -> 0
A39: Magazine | B39: 0.5 | G39: =SUM($C$37:$D$37)/12*$B39 -> 2475 | H39: =SUM($C$37:$D$37)/12*$B39 -> 2475 | I39: =SUM($C$37:$D$37)/12*$B39 -> 2475 | J39: =SUM($C$37:$D$37)/12*$B39 -> 2475 | K39: =SUM($C$37:$D$37)/12*$B39 -> 2475 | L39: =SUM($E$37)/12*$B39 -> 2000 | M39: =SUM($E$37)/12*$B39 -> 2000 | N39: =SUM($E$37)/12*$B39 -> 2000 | O39: =SUM($E$37)/12*$B39 -> 2000 | P39: =SUM($E$37)/12*$B39 -> 2000 | Q39: =SUM($E$37)/12*$B39 -> 2000 | R39: =SUM($E$37)/12*$B39 -> 2000 | S39: =SUM(G39:R39) -> 26375
A40: Youtube | G40: =SUM($C$37:$D$37)/12*$B40 -> 0 | H40: =SUM($C$37:$D$37)/12*$B40 -> 0 | I40: =SUM($C$37:$D$37)/12*$B40 -> 0 | J40: =SUM($C$37:$D$37)/12*$B40 -> 0 | K40: =SUM($C$37:$D$37)/12*$B40 -> 0 | L40: =SUM($E$37)/12*$B40 -> 0 | M40: =SUM($E$37)/12*$B40 -> 0 | N40: =SUM($E$37)/12*$B40 -> 0 | O40: =SUM($E$37)/12*$B40 -> 0 | P40: =SUM($E$37)/12*$B40 -> 0 | Q40: =SUM($E$37)/12*$B40 -> 0 | R40: =SUM($E$37)/12*$B40 -> 0 | S40: =SUM(G40:R40) -> 0
A41: Instagram | B41: 0 | G41: =SUM($C$37:$D$37)/12*$B41 -> 0 | H41: =SUM($C$37:$D$37)/12*$B41 -> 0 | I41: =SUM($C$37:$D$37)/12*$B41 -> 0 | J41: =SUM($C$37:$D$37)/12*$B41 -> 0 | K41: =SUM($C$37:$D$37)/12*$B41 -> 0 | L41: =SUM($E$37)/12*$B41 -> 0 | M41: =SUM($E$37)/12*$B41 -> 0 | N41: =SUM($E$37)/12*$B41 -> 0 | O41: =SUM($E$37)/12*$B41 -> 0 | P41: =SUM($E$37)/12*$B41 -> 0 | Q41: =SUM($E$37)/12*$B41 -> 0 | R41: =SUM($E$37)/12*$B41 -> 0 | S41: =SUM(G41:R41) -> 0
A42: TikTok | B42: 0 | G42: =SUM($C$37:$D$37)/12*$B42 -> 0 | H42: =SUM($C$37:$D$37)/12*$B42 -> 0 | I42: =SUM($C$37:$D$37)/12*$B42 -> 0 | J42: =SUM($C$37:$D$37)/12*$B42 -> 0 | K42: =SUM($C$37:$D$37)/12*$B42 -> 0 | L42: =SUM($E$37)/12*$B42 -> 0 | M42: =SUM($E$37)/12*$B42 -> 0 | N42: =SUM($E$37)/12*$B42 -> 0 | O42: =SUM($E$37)/12*$B42 -> 0 | P42: =SUM($E$37)/12*$B42 -> 0 | Q42: =SUM($E$37)/12*$B42 -> 0 | R42: =SUM($E$37)/12*$B42 -> 0 | S42: =SUM(G42:R42) -> 0
A43: X | G43: =SUM($C$37:$D$37)/12*$B43 -> 0 | H43: =SUM($C$37:$D$37)/12*$B43 -> 0 | I43: =SUM($C$37:$D$37)/12*$B43 -> 0 | J43: =SUM($C$37:$D$37)/12*$B43 -> 0 | K43: =SUM($C$37:$D$37)/12*$B43 -> 0 | L43: =SUM($E$37)/12*$B43 -> 0 | M43: =SUM($E$37)/12*$B43 -> 0 | N43: =SUM($E$37)/12*$B43 -> 0 | O43: =SUM($E$37)/12*$B43 -> 0 | P43: =SUM($E$37)/12*$B43 -> 0 | Q43: =SUM($E$37)/12*$B43 -> 0 | R43: =SUM($E$37)/12*$B43 -> 0 | S43: =SUM(G43:R43) -> 0
A44: B2B | G44: =SUM($C$37:$D$37)/12*$B44 -> 0 | H44: =SUM($C$37:$D$37)/12*$B44 -> 0 | I44: =SUM($C$37:$D$37)/12*$B44 -> 0 | J44: =SUM($C$37:$D$37)/12*$B44 -> 0 | K44: =SUM($C$37:$D$37)/12*$B44 -> 0 | L44: =SUM($E$37)/12*$B44 -> 0 | M44: =SUM($E$37)/12*$B44 -> 0 | N44: =SUM($E$37)/12*$B44 -> 0 | O44: =SUM($E$37)/12*$B44 -> 0 | P44: =SUM($E$37)/12*$B44 -> 0 | Q44: =SUM($E$37)/12*$B44 -> 0 | R44: =SUM($E$37)/12*$B44 -> 0 | S44: =SUM(G44:R44) -> 0
A45: Total | G45: =SUM(G38:G44) -> 2475 | H45: =SUM(H38:H44) -> 2475 | I45: =SUM(I38:I44) -> 2475 | J45: =SUM(J38:J44) -> 2475 | K45: =SUM(K38:K44) -> 2475 | L45: =SUM(L38:L44) -> 2000 | M45: =SUM(M38:M44) -> 2000 | N45: =SUM(N38:N44) -> 2000 | ... S45: =SUM(S38:S44) -> 26375
A47: PSM Recharge | B47: 0 | G47: =SUM($C$37:$D$37)/12*$B47 -> 0 | H47: =SUM($C$37:$D$37)/12*$B47 -> 0 | I47: =SUM($C$37:$D$37)/12*$B47 -> 0 | J47: =SUM($C$37:$D$37)/12*$B47 -> 0 | K47: =SUM($C$37:$D$37)/12*$B47 -> 0 | L47: =SUM($E$37)/12*$B47 -> 0 | M47: =SUM($E$37)/12*$B47 -> 0 | N47: =SUM($E$37)/12*$B47 -> 0 | O47: =SUM($E$37)/12*$B47 -> 0 | P47: =SUM($E$37)/12*$B47 -> 0 | Q47: =SUM($E$37)/12*$B47 -> 0 | R47: =SUM($E$37)/12*$B47 -> 0 | S47: =SUM(G47:R47) -> 0
A50: Harry Payne | C50: 30000 | D50: =C50*0.188 -> 5640
A51: Facebook | B51: 0.1 | G51: =SUM($C$50:$D$50)/12*$B51 -> 297 | H51: =SUM($C$50:$D$50)/12*$B51 -> 297 | I51: =SUM($C$50:$D$50)/12*$B51 -> 297 | J51: =SUM($C$50:$D$50)/12*$B51 -> 297 | K51: =SUM($C$50:$D$50)/12*$B51 -> 297 | L51: =SUM($C$50:$D$50)/12*$B51/2 -> 148.5 | M51: 0 | N51: 0 | O51: 0 | P51: 0 | Q51: 0 | R51: 0 | S51: =SUM(G51:R51) -> 1633.5
A52: Magazine | B52: 0.5 | G52: =SUM($C$50:$D$50)/12*$B52 -> 1485 | H52: =SUM($C$50:$D$50)/12*$B52 -> 1485 | I52: =SUM($C$50:$D$50)/12*$B52 -> 1485 | J52: =SUM($C$50:$D$50)/12*$B52 -> 1485 | K52: =SUM($C$50:$D$50)/12*$B52 -> 1485 | L52: =SUM($C$50:$D$50)/12*$B52/2 -> 742.5 | M52: 0 | N52: 0 | O52: 0 | P52: 0 | Q52: 0 | R52: 0 | S52: =SUM(G52:R52) -> 8167.5
A53: Youtube | B53: 0.1 | G53: =SUM($C$50:$D$50)/12*$B53 -> 297 | H53: =SUM($C$50:$D$50)/12*$B53 -> 297 | I53: =SUM($C$50:$D$50)/12*$B53 -> 297 | J53: =SUM($C$50:$D$50)/12*$B53 -> 297 | K53: =SUM($C$50:$D$50)/12*$B53 -> 297 | L53: =SUM($C$50:$D$50)/12*$B53/2 -> 148.5 | M53: 0 | N53: 0 | O53: 0 | P53: 0 | Q53: 0 | R53: 0 | S53: =SUM(G53:R53) -> 1633.5
A54: Instagram | B54: 0.1 | G54: =SUM($C$50:$D$50)/12*$B54 -> 297 | H54: =SUM($C$50:$D$50)/12*$B54 -> 297 | I54: =SUM($C$50:$D$50)/12*$B54 -> 297 | J54: =SUM($C$50:$D$50)/12*$B54 -> 297 | K54: =SUM($C$50:$D$50)/12*$B54 -> 297 | L54: =SUM($C$50:$D$50)/12*$B54/2 -> 148.5 | M54: 0 | N54: 0 | O54: 0 | P54: 0 | Q54: 0 | R54: 0 | S54: =SUM(G54:R54) -> 1633.5
A55: TikTok | B55: 0.1 | G55: =SUM($C$50:$D$50)/12*$B55 -> 297 | H55: =SUM($C$50:$D$50)/12*$B55 -> 297 | I55: =SUM($C$50:$D$50)/12*$B55 -> 297 | J55: =SUM($C$50:$D$50)/12*$B55 -> 297 | K55: =SUM($C$50:$D$50)/12*$B55 -> 297 | L55: =SUM($C$50:$D$50)/12*$B55/2 -> 148.5 | M55: 0 | N55: 0 | O55: 0 | P55: 0 | Q55: 0 | R55: 0 | S55: =SUM(G55:R55) -> 1633.5
A56: X | B56: 0.1 | G56: =SUM($C$50:$D$50)/12*$B56 -> 297 | H56: =SUM($C$50:$D$50)/12*$B56 -> 297 | I56: =SUM($C$50:$D$50)/12*$B56 -> 297 | J56: =SUM($C$50:$D$50)/12*$B56 -> 297 | K56: =SUM($C$50:$D$50)/12*$B56 -> 297 | L56: =SUM($C$50:$D$50)/12*$B56/2 -> 148.5 | M56: 0 | N56: 0 | O56: 0 | P56: 0 | Q56: 0 | R56: 0 | S56: =SUM(G56:R56) -> 1633.5
A57: B2B | G57: =SUM($C$50:$D$50)/12*$B57 -> 0 | H57: =SUM($C$50:$D$50)/12*$B57 -> 0 | I57: =SUM($C$50:$D$50)/12*$B57 -> 0 | J57: =SUM($C$50:$D$50)/12*$B57 -> 0 | K57: =SUM($C$50:$D$50)/12*$B57 -> 0 | L57: =SUM($C$50:$D$50)/12*$B57/2 -> 0 | M57: 0 | N57: 0 | O57: 0 | P57: 0 | Q57: 0 | R57: 0 | S57: =SUM(G57:R57) -> 0
A58: Total | G58: =SUM(G51:G57) -> 2970 | H58: =SUM(H51:H57) -> 2970 | I58: =SUM(I51:I57) -> 2970 | J58: =SUM(J51:J57) -> 2970 | K58: =SUM(K51:K57) -> 2970 | L58: =SUM(L51:L57) -> 1485 | M58: =SUM(M51:M57) -> 0 | N58: =SUM(N51:N57) -> 0 | ... S58: =SUM(S51:S57) -> 16335
A60: Shaun Brown | C60: 26820 | D60: =C60*0.188 -> 5042.16 | E60: =C60/2 -> 13410
A61: Facebook | G61: =SUM($C$60:$D$60)/12*$B61 -> 0 | H61: =SUM($C$60:$D$60)/12*$B61 -> 0 | I61: =SUM($C$60:$D$60)/12*$B61 -> 0 | J61: =SUM($C$60:$D$60)/12*$B61 -> 0 | K61: 0 | L61: 0 | M61: 0 | N61: 0 | O61: 0 | P61: 0 | Q61: 0 | R61: 0 | S61: =SUM(G61:R61) -> 0
A62: Magazine | B62: 0.45 | G62: =SUM($C$60:$D$60)/12*$B62 -> 1194.831 | H62: =SUM($C$60:$D$60)/12*$B62 -> 1194.831 | I62: =SUM($C$60:$D$60)/12*$B62 -> 1194.831 | J62: =SUM($C$60:$D$60)/12*$B62 -> 1194.831 | K62: =SUM($C$60:$D$60)/12*$B62/2+SUM($E$60/12/2*B62) -> 848.853 | L62: =SUM($E$60)/12*0.9 -> 1005.75 | M62: =SUM($E$60)/12*0.9 -> 1005.75 | N62: =SUM($E$60)/12*0.9 -> 1005.75 | O62: =SUM($E$60)/12*0.9 -> 1005.75 | P62: =SUM($E$60)/12*0.9 -> 1005.75 | Q62: =SUM($E$60)/12*0.9 -> 1005.75 | R62: =SUM($E$60)/12*0.9 -> 1005.75 | S62: =SUM(G62:R62) -> 12668.427
A63: Youtube | G63: =SUM($C$60:$D$60)/12*$B63 -> 0 | H63: =SUM($C$60:$D$60)/12*$B63 -> 0 | I63: =SUM($C$60:$D$60)/12*$B63 -> 0 | J63: =SUM($C$60:$D$60)/12*$B63 -> 0 | K63: 0 | L63: 0 | M63: 0 | N63: 0 | O63: 0 | P63: 0 | Q63: 0 | R63: 0 | S63: =SUM(G63:R63) -> 0
A64: Instagram | G64: =SUM($C$60:$D$60)/12*$B64 -> 0 | H64: =SUM($C$60:$D$60)/12*$B64 -> 0 | I64: =SUM($C$60:$D$60)/12*$B64 -> 0 | J64: =SUM($C$60:$D$60)/12*$B64 -> 0 | K64: 0 | L64: 0 | M64: 0 | N64: 0 | O64: 0 | P64: 0 | Q64: 0 | R64: 0 | S64: =SUM(G64:R64) -> 0
A65: TikTok | G65: =SUM($C$60:$D$60)/12*$B65 -> 0 | H65: =SUM($C$60:$D$60)/12*$B65 -> 0 | I65: =SUM($C$60:$D$60)/12*$B65 -> 0 | J65: =SUM($C$60:$D$60)/12*$B65 -> 0 | K65: 0 | L65: 0 | M65: 0 | N65: 0 | O65: 0 | P65: 0 | Q65: 0 | R65: 0 | S65: =SUM(G65:R65) -> 0
A66: X | G66: =SUM($C$60:$D$60)/12*$B66 -> 0 | H66: =SUM($C$60:$D$60)/12*$B66 -> 0 | I66: =SUM($C$60:$D$60)/12*$B66 -> 0 | J66: =SUM($C$60:$D$60)/12*$B66 -> 0 | K66: 0 | L66: 0 | M66: 0 | N66: 0 | O66: 0 | P66: 0 | Q66: 0 | R66: 0 | S66: =SUM(G66:R66) -> 0
A67: B2B | G67: =SUM($C$60:$D$60)/12*$B67 -> 0 | H67: =SUM($C$60:$D$60)/12*$B67 -> 0 | I67: =SUM($C$60:$D$60)/12*$B67 -> 0 | J67: =SUM($C$60:$D$60)/12*$B67 -> 0 | K67: 0 | L67: 0 | M67: 0 | N67: 0 | O67: 0 | P67: 0 | Q67: 0 | R67: 0 | S67: =SUM(G67:R67) -> 0
A68: Website | B68: 0.45 | G68: =SUM($C$60:$D$60)/12*$B68 -> 1194.831 | H68: =SUM($C$60:$D$60)/12*$B68 -> 1194.831 | I68: =SUM($C$60:$D$60)/12*$B68 -> 1194.831 | J68: =SUM($C$60:$D$60)/12*$B68 -> 1194.831 | K68: =SUM($C$60:$D$60)/12*$B68/2+SUM($E$60/12/2*B68) -> 848.853 | L68: 0 | M68: 0 | N68: 0 | O68: 0 | P68: 0 | Q68: 0 | R68: 0 | S68: =SUM(G68:R68) -> 5628.177
A69: Recharge | B69: -0.5 | G69: =SUM($C$60)/12*$B69 -> -1117.5 | H69: =SUM($C$60)/12*$B69 -> -1117.5 | I69: =SUM($C$60)/12*$B69 -> -1117.5 | J69: =SUM($C$60)/12*$B69 -> -1117.5 | K69: =SUM($C$60)/12*$B69/2+SUM($E$60/12/2*B69) -> -838.125 | L69: 0 | M69: 0 | N69: 0 | O69: 0 | P69: 0 | Q69: 0 | R69: 0 | S69: =SUM(G69:R69) -> -5308.125
A70: Total | G70: =SUM(G61:G69) -> 1272.162 | H70: =SUM(H61:H69) -> 1272.162 | I70: =SUM(I61:I69) -> 1272.162 | J70: =SUM(J61:J69) -> 1272.162 | K70: =SUM(K61:K69) -> 859.581 | L70: =SUM(L61:L69) -> 1005.75 | M70: =SUM(M61:M69) -> 1005.75 | N70: =SUM(N61:N69) -> 1005.75 | ... R70: =SUM(R61:R69) -> 1005.75 | S70: =SUM(S61:S67) -> 12668.427
A72: PSM Recharge | B72: 0.1 | G72: =SUM($C$60:$D$60)/12*$B72 -> 265.518 | H72: =SUM($C$60:$D$60)/12*$B72 -> 265.518 | I72: =SUM($C$60:$D$60)/12*$B72 -> 265.518 | J72: =SUM($C$60:$D$60)/12*$B72 -> 265.518 | K72: =SUM($C$60:$D$60)/12*$B72/2+SUM($E$60/12/2*B72) -> 188.634 | L72: =SUM($E$60)/12*0.1 -> 111.75 | M72: =SUM($E$60)/12*0.1 -> 111.75 | N72: =SUM($E$60)/12*0.1 -> 111.75 | O72: =SUM($E$60)/12*0.1 -> 111.75 | P72: =SUM($E$60)/12*0.1 -> 111.75 | Q72: =SUM($E$60)/12*0.1 -> 111.75 | R72: =SUM($E$60)/12*0.1 -> 111.75 | S72: =SUM(G72:R72) -> 2032.956
A74: Oscar Pick | C74: 26000 | D74: =C74*0.188 -> 4888 | E74: =C74/2 -> 13000
A75: Facebook | G75: =SUM($C$74:$D$74)/12*$B75 -> 0 | H75: =SUM($C$74:$D$74)/12*$B75 -> 0 | I75: =SUM($C$74:$D$74)/12*$B75 -> 0 | J75: =SUM($C$74:$D$74)/12*$B75 -> 0 | K75: =SUM($C$74:$D$74)/12*$B75/2+SUM($E$74/12/2*B75) -> 0 | L75: =SUM($E$74)/12*$B75 -> 0 | M75: =SUM($E$74)/12*$B75 -> 0 | N75: =SUM($E$74)/12*$B75 -> 0 | O75: =SUM($E$74)/12*$B75 -> 0 | P75: =SUM($E$74)/12*$B75 -> 0 | Q75: =SUM($E$74)/12*$B75 -> 0 | R75: =SUM($E$74)/12*$B75 -> 0 | S75: =SUM(G75:R75) -> 0
A76: Magazine | B76: 0.5 | G76: =SUM($C$74:$D$74)/12*$B76 -> 1287 | H76: =SUM($C$74:$D$74)/12*$B76 -> 1287 | I76: =SUM($C$74:$D$74)/12*$B76 -> 1287 | J76: =SUM($C$74:$D$74)/12*$B76 -> 1287 | K76: =SUM($C$74:$D$74)/12*$B76/2+SUM($E$74/12/2*B76) -> 914.33333 | L76: =SUM($E$74)/12*$B76 -> 541.66667 | M76: =SUM($E$74)/12*$B76 -> 541.66667 | N76: =SUM($E$74)/12*$B76 -> 541.66667 | O76: =SUM($E$74)/12*$B76 -> 541.66667 | P76: =SUM($E$74)/12*$B76 -> 541.66667 | Q76: =SUM($E$74)/12*$B76 -> 541.66667 | R76: =SUM($E$74)/12*$B76 -> 541.66667 | S76: =SUM(G76:R76) -> 9854
A77: Youtube | G77: =SUM($C$74:$D$74)/12*$B77 -> 0 | H77: =SUM($C$74:$D$74)/12*$B77 -> 0 | I77: =SUM($C$74:$D$74)/12*$B77 -> 0 | J77: =SUM($C$74:$D$74)/12*$B77 -> 0 | K77: =SUM($C$74:$D$74)/12*$B77/2+SUM($E$74/12/2*B77) -> 0 | L77: =SUM($E$74)/12*$B77 -> 0 | M77: =SUM($E$74)/12*$B77 -> 0 | N77: =SUM($E$74)/12*$B77 -> 0 | O77: =SUM($E$74)/12*$B77 -> 0 | P77: =SUM($E$74)/12*$B77 -> 0 | Q77: =SUM($E$74)/12*$B77 -> 0 | R77: =SUM($E$74)/12*$B77 -> 0 | S77: =SUM(G77:R77) -> 0
A78: Instagram | G78: =SUM($C$74:$D$74)/12*$B78 -> 0 | H78: =SUM($C$74:$D$74)/12*$B78 -> 0 | I78: =SUM($C$74:$D$74)/12*$B78 -> 0 | J78: =SUM($C$74:$D$74)/12*$B78 -> 0 | K78: =SUM($C$74:$D$74)/12*$B78/2+SUM($E$74/12/2*B78) -> 0 | L78: =SUM($E$74)/12*$B78 -> 0 | M78: =SUM($E$74)/12*$B78 -> 0 | N78: =SUM($E$74)/12*$B78 -> 0 | O78: =SUM($E$74)/12*$B78 -> 0 | P78: =SUM($E$74)/12*$B78 -> 0 | Q78: =SUM($E$74)/12*$B78 -> 0 | R78: =SUM($E$74)/12*$B78 -> 0 | S78: =SUM(G78:R78) -> 0
A79: TikTok | G79: =SUM($C$74:$D$74)/12*$B79 -> 0 | H79: =SUM($C$74:$D$74)/12*$B79 -> 0 | I79: =SUM($C$74:$D$74)/12*$B79 -> 0 | J79: =SUM($C$74:$D$74)/12*$B79 -> 0 | K79: =SUM($C$74:$D$74)/12*$B79/2+SUM($E$74/12/2*B79) -> 0 | L79: =SUM($E$74)/12*$B79 -> 0 | M79: =SUM($E$74)/12*$B79 -> 0 | N79: =SUM($E$74)/12*$B79 -> 0 | O79: =SUM($E$74)/12*$B79 -> 0 | P79: =SUM($E$74)/12*$B79 -> 0 | Q79: =SUM($E$74)/12*$B79 -> 0 | R79: =SUM($E$74)/12*$B79 -> 0 | S79: =SUM(G79:R79) -> 0
A80: X | G80: =SUM($C$74:$D$74)/12*$B80 -> 0 | H80: =SUM($C$74:$D$74)/12*$B80 -> 0 | I80: =SUM($C$74:$D$74)/12*$B80 -> 0 | J80: =SUM($C$74:$D$74)/12*$B80 -> 0 | K80: =SUM($C$74:$D$74)/12*$B80/2+SUM($E$74/12/2*B80) -> 0 | L80: =SUM($E$74)/12*$B80 -> 0 | M80: =SUM($E$74)/12*$B80 -> 0 | N80: =SUM($E$74)/12*$B80 -> 0 | O80: =SUM($E$74)/12*$B80 -> 0 | P80: =SUM($E$74)/12*$B80 -> 0 | Q80: =SUM($E$74)/12*$B80 -> 0 | R80: =SUM($E$74)/12*$B80 -> 0 | S80: =SUM(G80:R80) -> 0
A81: B2B | G81: =SUM($C$74:$D$74)/12*$B81 -> 0 | H81: =SUM($C$74:$D$74)/12*$B81 -> 0 | I81: =SUM($C$74:$D$74)/12*$B81 -> 0 | J81: =SUM($C$74:$D$74)/12*$B81 -> 0 | K81: =SUM($C$74:$D$74)/12*$B81/2+SUM($E$74/12/2*B81) -> 0 | L81: =SUM($E$74)/12*$B81 -> 0 | M81: =SUM($E$74)/12*$B81 -> 0 | N81: =SUM($E$74)/12*$B81 -> 0 | O81: =SUM($E$74)/12*$B81 -> 0 | P81: =SUM($E$74)/12*$B81 -> 0 | Q81: =SUM($E$74)/12*$B81 -> 0 | R81: =SUM($E$74)/12*$B81 -> 0 | S81: =SUM(G81:R81) -> 0
A82: Website | B82: 0.5 | G82: =SUM($C$74:$D$74)/12*$B82 -> 1287 | H82: =SUM($C$74:$D$74)/12*$B82 -> 1287 | I82: =SUM($C$74:$D$74)/12*$B82 -> 1287 | J82: =SUM($C$74:$D$74)/12*$B82 -> 1287 | K82: =SUM($C$74:$D$74)/12*$B82/2+SUM($E$74/12/2*B82) -> 914.33333 | L82: =SUM($E$74)/12*$B82 -> 541.66667 | M82: =SUM($E$74)/12*$B82 -> 541.66667 | N82: =SUM($E$74)/12*$B82 -> 541.66667 | O82: =SUM($E$74)/12*$B82 -> 541.66667 | P82: =SUM($E$74)/12*$B82 -> 541.66667 | Q82: =SUM($E$74)/12*$B82 -> 541.66667 | R82: =SUM($E$74)/12*$B82 -> 541.66667 | S82: =SUM(G82:R82) -> 9854
A83: Recharge | B83: -0.5 | G83: =SUM($C$74)/12*$B83 -> -1083.3333 | H83: =SUM($C$74)/12*$B83 -> -1083.3333 | I83: =SUM($C$74)/12*$B83 -> -1083.3333 | J83: =SUM($C$74)/12*$B83 -> -1083.3333 | K83: =SUM($C$74)/12*$B83/2+SUM($E$74/12/2*B83) -> -812.5 | L83: 0 | M83: 0 | N83: 0 | O83: 0 | P83: 0 | Q83: 0 | R83: 0 | S83: =SUM(G83:R83) -> -5145.8333
A84: Total | G84: =SUM(G75:G83) -> 1490.6667 | H84: =SUM(H75:H83) -> 1490.6667 | I84: =SUM(I75:I83) -> 1490.6667 | J84: =SUM(J75:J83) -> 1490.6667 | K84: =SUM(K75:K83) -> 1016.1667 | L84: =SUM(L75:L83) -> 1083.3333 | M84: =SUM(M75:M83) -> 1083.3333 | N84: =SUM(N75:N83) -> 1083.3333 | ... R84: =SUM(R75:R83) -> 1083.3333 | S84: =SUM(S75:S81) -> 9854
G88: =G12+G23+G33+G45+G58+G70+G84 -> 17296.029 | H88: =H12+H23+H33+H45+H58+H70+H84 -> 17296.029 | I88: =I12+I23+I33+I45+I58+I70+I84 -> 17296.029 | J88: =J12+J23+J33+J45+J58+J70+J84 -> 19672.029 | K88: =K12+K23+K33+K45+K58+K70+K84 -> 16408.948 | L88: =L12+L23+L33+L45+L58+L70+L84 -> 11811.083 | M88: =M12+M23+M33+M45+M58+M70+M84 -> 10326.083 | N88: =N12+N23+N33+N45+N58+N70+N84 -> 10326.083 | ... R88: =R12+R23+R33+R45+R58+R70+R84 -> 10326.083
G89: =SUM(G5+G16+G27+G39+G52+G62+G76)*-1 -> -6535.881 | H89: =SUM(H5+H16+H27+H39+H52+H62+H76)*-1 -> -6535.881 | I89: =SUM(I5+I16+I27+I39+I52+I62+I76)*-1 -> -6535.881 | J89: =SUM(J5+J16+J27+J39+J52+J62+J76)*-1 -> -6595.281 | K89: =SUM(K5+K16+K27+K39+K52+K62+K76)*-1 -> -5817.2363 | L89: =SUM(L5+L16+L27+L39+L52+L62+L76)*-1 -> -4383.9667 | M89: =SUM(M5+M16+M27+M39+M52+M62+M76)*-1 -> -3641.4667 | N89: =SUM(N5+N16+N27+N39+N52+N62+N76)*-1 -> -3641.4667 | ... R89: =SUM(R5+R16+R27+R39+R52+R62+R76)*-1 -> -3641.4667
G90: =SUM(G88:G89) -> 10760.148 | H90: =SUM(H88:H89) -> 10760.148 | I90: =SUM(I88:I89) -> 10760.148 | J90: =SUM(J88:J89) -> 13076.748 | K90: =SUM(K88:K89) -> 10591.711 | L90: =SUM(L88:L89) -> 7427.1167 | M90: =SUM(M88:M89) -> 6684.6167 | N90: =SUM(N88:N89) -> 6684.6167 | ... R90: =SUM(R88:R89) -> 6684.6167
J93: =SUM(I90:R90) -> 81963.423
I94: FY | J94: =J93+13500 -> 95463.423

Sheet M3 Freelancers
C1: Actuals | D1: Actuals | E1: Forecast | F1: Forecast | G1: Forecast | H1: Forecast | I1: Forecast | J1: Forecast | K1: Forecast | L1: Forecast | M1: Forecast | N1: Forecast
A2: Employee Name | B2: Allocation | C2: 45931 | D2: 45962 | E2: 45992 | F2: 46023 | G2: 46054 | H2: 46082 | I2: 46113 | J2: 46143 | K2: 46174 | L2: 46204 | M2: 46235 | N2: 46266 | O2: FY26
B3: =50000/12 -> 4166.6667
A5: Facebook | B5: =0.5/3 -> 0.16666667 | I5: =$B$3*$B5 -> 694.44444 | J5: =$B$3*$B5 -> 694.44444 | K5: =$B$3*$B5 -> 694.44444 | L5: =$B$3*$B5 -> 694.44444 | M5: =$B$3*$B5 -> 694.44444 | N5: =$B$3*$B5 -> 694.44444 | O5: =SUM(C5:N5) -> 4166.6667
A6: Instagram | B6: =0.5/3 -> 0.16666667 | I6: =$B$3*$B6 -> 694.44444 | J6: =$B$3*$B6 -> 694.44444 | K6: =$B$3*$B6 -> 694.44444 | L6: =$B$3*$B6 -> 694.44444 | M6: =$B$3*$B6 -> 694.44444 | N6: =$B$3*$B6 -> 694.44444 | O6: =SUM(C6:N6) -> 4166.6667
A7: TikTok | B7: =0.5/3 -> 0.16666667 | I7: =$B$3*$B7 -> 694.44444 | J7: =$B$3*$B7 -> 694.44444 | K7: =$B$3*$B7 -> 694.44444 | L7: =$B$3*$B7 -> 694.44444 | M7: =$B$3*$B7 -> 694.44444 | N7: =$B$3*$B7 -> 694.44444 | O7: =SUM(C7:N7) -> 4166.6667
A8: Youtube | B8: 0.5 | I8: =$B$3*$B8 -> 2083.3333 | J8: =$B$3*$B8 -> 2083.3333 | K8: =$B$3*$B8 -> 2083.3333 | L8: =$B$3*$B8 -> 2083.3333 | M8: =$B$3*$B8 -> 2083.3333 | N8: =$B$3*$B8 -> 2083.3333 | O8: =SUM(C8:N8) -> 12500
A10: Total | C10: =SUM(C5:C9) -> 0 | D10: =SUM(D5:D9) -> 0 | E10: =SUM(E5:E9) -> 0 | F10: =SUM(F5:F9) -> 0 | G10: =SUM(G5:G9) -> 0 | H10: =SUM(H5:H9) -> 0 | I10: =SUM(I5:I9) -> 4166.6667 | J10: =SUM(J5:J9) -> 4166.6667 | ... O10: =SUM(O5:O9) -> 25000

Sheet OH
C1: Actuals | D1: Actuals | E1: Forecast | F1: Forecast | G1: Forecast | H1: Forecast | I1: Forecast | J1: Forecast | K1: Forecast | L1: Forecast | M1: Forecast | N1: Forecast
A2: Employee Name | B2: Allocation | C2: 45931 | D2: 45962 | E2: 45992 | F2: 46023 | G2: 46054 | H2: 46082 | I2: 46113 | J2: 46143 | K2: 46174 | L2: 46204 | M2: 46235 | N2: 46266 | O2: FY26
A3: Travel + Subsistence | B3: 1500
A4: Youtube | B4: 0.2 | C4: =$B$3*$B$5 -> 300 | D4: =$B$3*$B$5 -> 300 | E4: =$B$3*$B$5 -> 300 | F4: =$B$3*$B$5 -> 300 | G4: =$B$3*$B$5 -> 300 | H4: =$B$3*$B$5 -> 300 | I4: =$B$3*$B$5 -> 300 | J4: =$B$3*$B$5 -> 300 | ... N4: =$B$3*$B$5 -> 300 | O4: =SUM(C4:N4) -> 3600
A5: Facebook | B5: 0.2 | C5: =$B$3*$B$5 -> 300 | D5: =$B$3*$B$5 -> 300 | E5: =$B$3*$B$5 -> 300 | F5: =$B$3*$B$5 -> 300 | G5: =$B$3*$B$5 -> 300 | H5: =$B$3*$B$5 -> 300 | I5: =$B$3*$B$5 -> 300 | J5: =$B$3*$B$5 -> 300 | ... N5: =$B$3*$B$5 -> 300 | O5: =SUM(C5:N5) -> 3600
A6: Instagram | B6: 0.2 | C6: =$B$3*$B$5 -> 300 | D6: =$B$3*$B$5 -> 300 | E6: =$B$3*$B$5 -> 300 | F6: =$B$3*$B$5 -> 300 | G6: =$B$3*$B$5 -> 300 | H6: =$B$3*$B$5 -> 300 | I6: =$B$3*$B$5 -> 300 | J6: =$B$3*$B$5 -> 300 | ... N6: =$B$3*$B$5 -> 300 | O6: =SUM(C6:N6) -> 3600
A7: TikTok | B7: 0.2 | C7: =$B$3*$B$5 -> 300 | D7: =$B$3*$B$5 -> 300 | E7: =$B$3*$B$5 -> 300 | F7: =$B$3*$B$5 -> 300 | G7: =$B$3*$B$5 -> 300 | H7: =$B$3*$B$5 -> 300 | I7: =$B$3*$B$5 -> 300 | J7: =$B$3*$B$5 -> 300 | ... N7: =$B$3*$B$5 -> 300 | O7: =SUM(C7:N7) -> 3600
A8: X | B8: 0.2 | C8: =$B$3*$B$5 -> 300 | D8: =$B$3*$B$5 -> 300 | E8: =$B$3*$B$5 -> 300 | F8: =$B$3*$B$5 -> 300 | G8: =$B$3*$B$5 -> 300 | H8: =$B$3*$B$5 -> 300 | I8: =$B$3*$B$5 -> 300 | J8: =$B$3*$B$5 -> 300 | ... N8: =$B$3*$B$5 -> 300 | O8: =SUM(C8:N8) -> 3600
C9: =SUM(C5:C8) -> 1200 | D9: =SUM(D5:D8) -> 1200 | E9: =SUM(E4:E8) -> 1500 | F9: =SUM(F4:F8) -> 1500 | G9: =SUM(G4:G8) -> 1500 | H9: =SUM(H4:H8) -> 1500 | I9: =SUM(I4:I8) -> 1500 | J9: =SUM(J4:J8) -> 1500 | K9: =SUM(K4:K8) -> 1500 | L9: =SUM(L4:L8) -> 1500 | ... O9: =SUM(O4:O8) -> 18000
A11: Subscripitons - Getty | B11: 1240
A12: Magazine | B12: 0.5 | C12: =$B$11*$B12 -> 620 | D12: =$B$11*$B12 -> 620 | E12: =$B$11*$B12 -> 620 | F12: =$B$11*$B12 -> 620 | G12: =$B$11*$B12 -> 620 | H12: =$B$11*$B12 -> 620 | I12: =$B$11*$B12 -> 620 | J12: =$B$11*$B12 -> 620 | ... N12: =$B$11*$B12 -> 620 | O12: =SUM(C12:N12) -> 7440
A13: Youtube | B13: 0.1 | C13: =$B$11*$B13 -> 124 | D13: =$B$11*$B13 -> 124 | E13: =$B$11*$B13 -> 124 | F13: =$B$11*$B13 -> 124 | G13: =$B$11*$B13 -> 124 | H13: =$B$11*$B13 -> 124 | I13: =$B$11*$B13 -> 124 | J13: =$B$11*$B13 -> 124 | ... N13: =$B$11*$B13 -> 124 | O13: =SUM(C13:N13) -> 1488
A14: Facebook | B14: 0.1 | C14: =$B$11*$B14 -> 124 | D14: =$B$11*$B14 -> 124 | E14: =$B$11*$B14 -> 124 | F14: =$B$11*$B14 -> 124 | G14: =$B$11*$B14 -> 124 | H14: =$B$11*$B14 -> 124 | I14: =$B$11*$B14 -> 124 | J14: =$B$11*$B14 -> 124 | ... N14: =$B$11*$B14 -> 124 | O14: =SUM(C14:N14) -> 1488
A15: Instagram | B15: 0.1 | C15: =$B$11*$B15 -> 124 | D15: =$B$11*$B15 -> 124 | E15: =$B$11*$B15 -> 124 | F15: =$B$11*$B15 -> 124 | G15: =$B$11*$B15 -> 124 | H15: =$B$11*$B15 -> 124 | I15: =$B$11*$B15 -> 124 | J15: =$B$11*$B15 -> 124 | ... N15: =$B$11*$B15 -> 124 | O15: =SUM(C15:N15) -> 1488
A16: TikTok | B16: 0.1 | C16: =$B$11*$B16 -> 124 | D16: =$B$11*$B16 -> 124 | E16: =$B$11*$B16 -> 124 | F16: =$B$11*$B16 -> 124 | G16: =$B$11*$B16 -> 124 | H16: =$B$11*$B16 -> 124 | I16: =$B$11*$B16 -> 124 | J16: =$B$11*$B16 -> 124 | ... N16: =$B$11*$B16 -> 124 | O16: =SUM(C16:N16) -> 1488
A17: X | B17: 0.1 | C17: =$B$11*$B17 -> 124 | D17: =$B$11*$B17 -> 124 | E17: =$B$11*$B17 -> 124 | F17: =$B$11*$B17 -> 124 | G17: =$B$11*$B17 -> 124 | H17: =$B$11*$B17 -> 124 | I17: =$B$11*$B17 -> 124 | J17: =$B$11*$B17 -> 124 | ... N17: =$B$11*$B17 -> 124 | O17: =SUM(C17:N17) -> 1488
C18: =SUM(C12:C17) -> 1240 | D18: =SUM(D12:D17) -> 1240 | E18: =SUM(E12:E17) -> 1240 | F18: =SUM(F12:F17) -> 1240 | G18: =SUM(G12:G17) -> 1240 | H18: =SUM(H12:H17) -> 1240 | I18: =SUM(I12:I17) -> 1240 | J18: =SUM(J12:J17) -> 1240 | ... O18: =SUM(O12:O17) -> 14880
A20: Subscripitons - Other | B20: 1776
A21: Magazine | B21: 0.1 | C21: =$B$20*$B21 -> 177.6 | D21: =$B$20*$B21 -> 177.6 | E21: =$B$20*$B21 -> 177.6 | F21: =$B$20*$B21 -> 177.6 | G21: =$B$20*$B21 -> 177.6 | H21: =$B$20*$B21 -> 177.6 | I21: =$B$20*$B21 -> 177.6 | J21: =$B$20*$B21 -> 177.6 | ... N21: =$B$20*$B21 -> 177.6 | O21: =SUM(C21:N21) -> 2131.2 | Q21: Slack ? WeTFR?
A22: Youtube | B22: 0.2 | C22: =$B$20*$B22 -> 355.2 | D22: =$B$20*$B22 -> 355.2 | E22: =$B$20*$B22 -> 355.2 | F22: =$B$20*$B22 -> 355.2 | G22: =$B$20*$B22 -> 355.2 | H22: =$B$20*$B22 -> 355.2 | I22: =$B$20*$B22 -> 355.2 | J22: =$B$20*$B22 -> 355.2 | ... N22: =$B$20*$B22 -> 355.2 | O22: =SUM(C22:N22) -> 4262.4
A23: Facebook | B23: 0.2 | C23: =$B$20*$B23 -> 355.2 | D23: =$B$20*$B23 -> 355.2 | E23: =$B$20*$B23 -> 355.2 | F23: =$B$20*$B23 -> 355.2 | G23: =$B$20*$B23 -> 355.2 | H23: =$B$20*$B23 -> 355.2 | I23: =$B$20*$B23 -> 355.2 | J23: =$B$20*$B23 -> 355.2 | ... N23: =$B$20*$B23 -> 355.2 | O23: =SUM(C23:N23) -> 4262.4
A24: Instagram | B24: 0.2 | C24: =$B$20*$B24 -> 355.2 | D24: =$B$20*$B24 -> 355.2 | E24: =$B$20*$B24 -> 355.2 | F24: =$B$20*$B24 -> 355.2 | G24: =$B$20*$B24 -> 355.2 | H24: =$B$20*$B24 -> 355.2 | I24: =$B$20*$B24 -> 355.2 | J24: =$B$20*$B24 -> 355.2 | ... N24: =$B$20*$B24 -> 355.2 | O24: =SUM(C24:N24) -> 4262.4
A25: TikTok | B25: 0.2 | C25: =$B$20*$B25 -> 355.2 | D25: =$B$20*$B25 -> 355.2 | E25: =$B$20*$B25 -> 355.2 | F25: =$B$20*$B25 -> 355.2 | G25: =$B$20*$B25 -> 355.2 | H25: =$B$20*$B25 -> 355.2 | I25: =$B$20*$B25 -> 355.2 | J25: =$B$20*$B25 -> 355.2 | ... N25: =$B$20*$B25 -> 355.2 | O25: =SUM(C25:N25) -> 4262.4
A26: X | B26: 0.1 | C26: =$B$20*$B26 -> 177.6 | D26: =$B$20*$B26 -> 177.6 | E26: =$B$20*$B26 -> 177.6 | F26: =$B$20*$B26 -> 177.6 | G26: =$B$20*$B26 -> 177.6 | H26: =$B$20*$B26 -> 177.6 | I26: =$B$20*$B26 -> 177.6 | J26: =$B$20*$B26 -> 177.6 | ... N26: =$B$20*$B26 -> 177.6 | O26: =SUM(C26:N26) -> 2131.2
C27: =SUM(C21:C26) -> 1776 | D27: =SUM(D21:D26) -> 1776 | E27: =SUM(E21:E26) -> 1776 | F27: =SUM(F21:F26) -> 1776 | G27: =SUM(G21:G26) -> 1776 | H27: =SUM(H21:H26) -> 1776 | I27: =SUM(I21:I26) -> 1776 | J27: =SUM(J21:J26) -> 1776 | ... O27: =SUM(O21:O26) -> 21312
A29: Accountancy | B29: 1500
A30: Magazine | B30: =1/6 -> 0.16666667 | C30: =$B$29*$B30 -> 250 | D30: =$B$29*$B30 -> 250 | E30: =$B$29*$B30 -> 250 | F30: =$B$29*$B30 -> 250 | G30: =500*$B30 -> 83.333333 | H30: =500*$B30 -> 83.333333 | I30: =500*$B30 -> 83.333333 | J30: =500*$B30 -> 83.333333 | K30: =500*$B30 -> 83.333333 | L30: =500*$B30 -> 83.333333 | M30: =500*$B30 -> 83.333333 | N30: =500*$B30 -> 83.333333 | O30: =SUM(C30:N30) -> 1666.6667
A31: Youtube | B31: =1/6 -> 0.16666667 | C31: =$B$29*$B31 -> 250 | D31: =$B$29*$B31 -> 250 | E31: =$B$29*$B31 -> 250 | F31: =$B$29*$B31 -> 250 | G31: =500*$B31 -> 83.333333 | H31: =500*$B31 -> 83.333333 | I31: =500*$B31 -> 83.333333 | J31: =500*$B31 -> 83.333333 | K31: =500*$B31 -> 83.333333 | L31: =500*$B31 -> 83.333333 | M31: =500*$B31 -> 83.333333 | N31: =500*$B31 -> 83.333333 | O31: =SUM(C31:N31) -> 1666.6667
A32: Facebook | B32: =1/6 -> 0.16666667 | C32: =$B$29*$B32 -> 250 | D32: =$B$29*$B32 -> 250 | E32: =$B$29*$B32 -> 250 | F32: =$B$29*$B32 -> 250 | G32: =500*$B32 -> 83.333333 | H32: =500*$B32 -> 83.333333 | I32: =500*$B32 -> 83.333333 | J32: =500*$B32 -> 83.333333 | K32: =500*$B32 -> 83.333333 | L32: =500*$B32 -> 83.333333 | M32: =500*$B32 -> 83.333333 | N32: =500*$B32 -> 83.333333 | O32: =SUM(C32:N32) -> 1666.6667
A33: Instagram | B33: =1/6 -> 0.16666667 | C33: =$B$29*$B33 -> 250 | D33: =$B$29*$B33 -> 250 | E33: =$B$29*$B33 -> 250 | F33: =$B$29*$B33 -> 250 | G33: =500*$B33 -> 83.333333 | H33: =500*$B33 -> 83.333333 | I33: =500*$B33 -> 83.333333 | J33: =500*$B33 -> 83.333333 | K33: =500*$B33 -> 83.333333 | L33: =500*$B33 -> 83.333333 | M33: =500*$B33 -> 83.333333 | N33: =500*$B33 -> 83.333333 | O33: =SUM(C33:N33) -> 1666.6667
A34: TikTok | B34: =1/6 -> 0.16666667 | C34: =$B$29*$B34 -> 250 | D34: =$B$29*$B34 -> 250 | E34: =$B$29*$B34 -> 250 | F34: =$B$29*$B34 -> 250 | G34: =500*$B34 -> 83.333333 | H34: =500*$B34 -> 83.333333 | I34: =500*$B34 -> 83.333333 | J34: =500*$B34 -> 83.333333 | K34: =500*$B34 -> 83.333333 | L34: =500*$B34 -> 83.333333 | M34: =500*$B34 -> 83.333333 | N34: =500*$B34 -> 83.333333 | O34: =SUM(C34:N34) -> 1666.6667
A35: X | B35: =1/6 -> 0.16666667 | C35: =$B$29*$B35 -> 250 | D35: =$B$29*$B35 -> 250 | E35: =$B$29*$B35 -> 250 | F35: =$B$29*$B35 -> 250 | G35: =500*$B35 -> 83.333333 | H35: =500*$B35 -> 83.333333 | I35: =500*$B35 -> 83.333333 | J35: =500*$B35 -> 83.333333 | K35: =500*$B35 -> 83.333333 | L35: =500*$B35 -> 83.333333 | M35: =500*$B35 -> 83.333333 | N35: =500*$B35 -> 83.333333 | O35: =SUM(C35:N35) -> 1666.6667
C36: =SUM(C30:C35) -> 1500 | D36: =SUM(D30:D35) -> 1500 | E36: =SUM(E30:E35) -> 1500 | F36: =SUM(F30:F35) -> 1500 | G36: =SUM(G30:G35) -> 500 | H36: =SUM(H30:H35) -> 500 | I36: =SUM(I30:I35) -> 500 | J36: =SUM(J30:J35) -> 500 | ... O36: =SUM(O30:O35) -> 10000
E39: =E36+E27+E18+E9 -> 6016 | F39: =F36+F27+F18+F9 -> 6016 | G39: =G36+G27+G18+G9 -> 5016 | H39: =H36+H27+H18+H9 -> 5016 | I39: =I36+I27+I18+I9 -> 5016 | J39: =J36+J27+J18+J9 -> 5016 | K39: =K36+K27+K18+K9 -> 5016 | L39: =L36+L27+L18+L9 -> 5016 | ... N39: =N36+N27+N18+N9 -> 5016

Sheet OH Freelancer model
C1: Actuals | D1: Actuals | E1: Forecast | F1: Forecast | G1: Forecast | H1: Forecast | I1: Forecast | J1: Forecast | K1: Forecast | L1: Forecast | M1: Forecast | N1: Forecast
A2: Employee Name | B2: Allocation | C2: 45931 | D2: 45962 | E2: 45992 | F2: 46023 | G2: 46054 | H2: 46082 | I2: 46113 | J2: 46143 | K2: 46174 | L2: 46204 | M2: 46235 | N2: 46266 | O2: FY26
A3: Travel + Subsistence | B3: 1500
A4: Youtube | B4: 0.2 | C4: =$B$3*$B$5 -> 300 | D4: =$B$3*$B$5 -> 300 | E4: =$B$3*$B$5 -> 300 | F4: =$B$3*$B$5 -> 300 | G4: =$B$3*$B$5 -> 300 | H4: =$B$3*$B$5 -> 300 | I4: =$B$3*$B$5 -> 300 | J4: =$B$3*$B$5 -> 300 | ... N4: =$B$3*$B$5 -> 300 | O4: =SUM(C4:N4) -> 3600
A5: Facebook | B5: 0.2 | C5: =$B$3*$B$5 -> 300 | D5: =$B$3*$B$5 -> 300 | E5: =$B$3*$B$5 -> 300 | F5: =$B$3*$B$5 -> 300 | G5: =$B$3*$B$5 -> 300 | H5: =$B$3*$B$5 -> 300 | I5: =$B$3*$B$5 -> 300 | J5: =$B$3*$B$5 -> 300 | ... N5: =$B$3*$B$5 -> 300 | O5: =SUM(C5:N5) -> 3600
A6: Instagram | B6: 0.2 | C6: =$B$3*$B$5 -> 300 | D6: =$B$3*$B$5 -> 300 | E6: =$B$3*$B$5 -> 300 | F6: =$B$3*$B$5 -> 300 | G6: =$B$3*$B$5 -> 300 | H6: =$B$3*$B$5 -> 300 | I6: =$B$3*$B$5 -> 300 | J6: =$B$3*$B$5 -> 300 | ... N6: =$B$3*$B$5 -> 300 | O6: =SUM(C6:N6) -> 3600
A7: TikTok | B7: 0.2 | C7: =$B$3*$B$5 -> 300 | D7: =$B$3*$B$5 -> 300 | E7: =$B$3*$B$5 -> 300 | F7: =$B$3*$B$5 -> 300 | G7: =$B$3*$B$5 -> 300 | H7: =$B$3*$B$5 -> 300 | I7: =$B$3*$B$5 -> 300 | J7: =$B$3*$B$5 -> 300 | ... N7: =$B$3*$B$5 -> 300 | O7: =SUM(C7:N7) -> 3600
A8: X | B8: 0.2 | C8: =$B$3*$B$5 -> 300 | D8: =$B$3*$B$5 -> 300 | E8: =$B$3*$B$5 -> 300 | F8: =$B$3*$B$5 -> 300 | G8: =$B$3*$B$5 -> 300 | H8: =$B$3*$B$5 -> 300 | I8: =$B$3*$B$5 -> 300 | J8: =$B$3*$B$5 -> 300 | ... N8: =$B$3*$B$5 -> 300 | O8: =SUM(C8:N8) -> 3600
C9: =SUM(C5:C8) -> 1200 | D9: =SUM(D5:D8) -> 1200 | E9: =SUM(E5:E8) -> 1200 | F9: =SUM(F5:F8) -> 1200 | G9: =SUM(G5:G8) -> 1200 | H9: =SUM(H5:H8) -> 1200 | I9: =SUM(I5:I8) -> 1200 | J9: =SUM(J5:J8) -> 1200 | ... O9: =SUM(O5:O8) -> 14400
A11: Subscripitons - Getty | B11: 1240
A12: Magazine | B12: 0.5 | C12: =$B$11*$B12 -> 620 | D12: =$B$11*$B12 -> 620 | E12: =$B$11*$B12 -> 620 | F12: =$B$11*$B12 -> 620 | G12: =$B$11*$B12 -> 620 | H12: =$B$11*$B12 -> 620 | I12: =$B$11*$B12 -> 620 | J12: =$B$11*$B12 -> 620 | ... N12: =$B$11*$B12 -> 620 | O12: =SUM(C12:N12) -> 7440
A13: Youtube | B13: 0.1 | C13: =$B$11*$B13 -> 124 | D13: =$B$11*$B13 -> 124 | E13: =$B$11*$B13 -> 124 | F13: =$B$11*$B13 -> 124 | G13: =$B$11*$B13 -> 124 | H13: =$B$11*$B13 -> 124 | I13: =$B$11*$B13 -> 124 | J13: =$B$11*$B13 -> 124 | ... N13: =$B$11*$B13 -> 124 | O13: =SUM(C13:N13) -> 1488
A14: Facebook | B14: 0.1 | C14: =$B$11*$B14 -> 124 | D14: =$B$11*$B14 -> 124 | E14: =$B$11*$B14 -> 124 | F14: =$B$11*$B14 -> 124 | G14: =$B$11*$B14 -> 124 | H14: =$B$11*$B14 -> 124 | I14: =$B$11*$B14 -> 124 | J14: =$B$11*$B14 -> 124 | ... N14: =$B$11*$B14 -> 124 | O14: =SUM(C14:N14) -> 1488
A15: Instagram | B15: 0.1 | C15: =$B$11*$B15 -> 124 | D15: =$B$11*$B15 -> 124 | E15: =$B$11*$B15 -> 124 | F15: =$B$11*$B15 -> 124 | G15: =$B$11*$B15 -> 124 | H15: =$B$11*$B15 -> 124 | I15: =$B$11*$B15 -> 124 | J15: =$B$11*$B15 -> 124 | ... N15: =$B$11*$B15 -> 124 | O15: =SUM(C15:N15) -> 1488
A16: TikTok | B16: 0.1 | C16: =$B$11*$B16 -> 124 | D16: =$B$11*$B16 -> 124 | E16: =$B$11*$B16 -> 124 | F16: =$B$11*$B16 -> 124 | G16: =$B$11*$B16 -> 124 | H16: =$B$11*$B16 -> 124 | I16: =$B$11*$B16 -> 124 | J16: =$B$11*$B16 -> 124 | ... N16: =$B$11*$B16 -> 124 | O16: =SUM(C16:N16) -> 1488
A17: X | B17: 0.1 | C17: =$B$11*$B17 -> 124 | D17: =$B$11*$B17 -> 124 | E17: =$B$11*$B17 -> 124 | F17: =$B$11*$B17 -> 124 | G17: =$B$11*$B17 -> 124 | H17: =$B$11*$B17 -> 124 | I17: =$B$11*$B17 -> 124 | J17: =$B$11*$B17 -> 124 | ... N17: =$B$11*$B17 -> 124 | O17: =SUM(C17:N17) -> 1488
C18: =SUM(C12:C17) -> 1240 | D18: =SUM(D12:D17) -> 1240 | E18: =SUM(E12:E17) -> 1240 | F18: =SUM(F12:F17) -> 1240 | G18: =SUM(G12:G17) -> 1240 | H18: =SUM(H12:H17) -> 1240 | I18: =SUM(I12:I17) -> 1240 | J18: =SUM(J12:J17) -> 1240 | ... O18: =SUM(O12:O17) -> 14880
B19: =B20-S25-S27 -> 1312.75
A20: Subscripitons - Other | B20: 1776
A21: Magazine | B21: 0.1 | C21: =$B$20*$B21 -> 177.6 | D21: =$B$20*$B21 -> 177.6 | E21: =$B$20*$B21 -> 177.6 | F21: =$B$20*$B21 -> 177.6 | G21: =$B$20*$B21 -> 177.6 | H21: =$B$20*$B21 -> 177.6 | I21: =$B$19*$B21 -> 131.275 | J21: =$B$19*$B21 -> 131.275 | K21: =$B$19*$B21 -> 131.275 | L21: =$B$19*$B21 -> 131.275 | M21: =$B$19*$B21 -> 131.275 | N21: =$B$19*$B21 -> 131.275 | O21: =SUM(C21:N21) -> 1853.25
A22: Youtube | B22: 0.2 | C22: =$B$20*$B22 -> 355.2 | D22: =$B$20*$B22 -> 355.2 | E22: =$B$20*$B22 -> 355.2 | F22: =$B$20*$B22 -> 355.2 | G22: =$B$20*$B22 -> 355.2 | H22: =$B$20*$B22 -> 355.2 | I22: =$B$19*$B22 -> 262.55 | J22: =$B$19*$B22 -> 262.55 | K22: =$B$19*$B22 -> 262.55 | L22: =$B$19*$B22 -> 262.55 | M22: =$B$19*$B22 -> 262.55 | N22: =$B$19*$B22 -> 262.55 | O22: =SUM(C22:N22) -> 3706.5
A23: Facebook | B23: 0.2 | C23: =$B$20*$B23 -> 355.2 | D23: =$B$20*$B23 -> 355.2 | E23: =$B$20*$B23 -> 355.2 | F23: =$B$20*$B23 -> 355.2 | G23: =$B$20*$B23 -> 355.2 | H23: =$B$20*$B23 -> 355.2 | I23: =$B$19*$B23 -> 262.55 | J23: =$B$19*$B23 -> 262.55 | K23: =$B$19*$B23 -> 262.55 | L23: =$B$19*$B23 -> 262.55 | M23: =$B$19*$B23 -> 262.55 | N23: =$B$19*$B23 -> 262.55 | O23: =SUM(C23:N23) -> 3706.5
A24: Instagram | B24: 0.2 | C24: =$B$20*$B24 -> 355.2 | D24: =$B$20*$B24 -> 355.2 | E24: =$B$20*$B24 -> 355.2 | F24: =$B$20*$B24 -> 355.2 | G24: =$B$20*$B24 -> 355.2 | H24: =$B$20*$B24 -> 355.2 | I24: =$B$19*$B24 -> 262.55 | J24: =$B$19*$B24 -> 262.55 | K24: =$B$19*$B24 -> 262.55 | L24: =$B$19*$B24 -> 262.55 | M24: =$B$19*$B24 -> 262.55 | N24: =$B$19*$B24 -> 262.55 | O24: =SUM(C24:N24) -> 3706.5 | S24: Reduction in Adobe licenses
A25: TikTok | B25: 0.2 | C25: =$B$20*$B25 -> 355.2 | D25: =$B$20*$B25 -> 355.2 | E25: =$B$20*$B25 -> 355.2 | F25: =$B$20*$B25 -> 355.2 | G25: =$B$20*$B25 -> 355.2 | H25: =$B$20*$B25 -> 355.2 | I25: =$B$19*$B25 -> 262.55 | J25: =$B$19*$B25 -> 262.55 | K25: =$B$19*$B25 -> 262.55 | L25: =$B$19*$B25 -> 262.55 | M25: =$B$19*$B25 -> 262.55 | N25: =$B$19*$B25 -> 262.55 | O25: =SUM(C25:N25) -> 3706.5 | Q25: =873/12 -> 72.75 | S25: =Q25*3 -> 218.25
A26: X | B26: 0.1 | C26: =$B$20*$B26 -> 177.6 | D26: =$B$20*$B26 -> 177.6 | E26: =$B$20*$B26 -> 177.6 | F26: =$B$20*$B26 -> 177.6 | G26: =$B$20*$B26 -> 177.6 | H26: =$B$20*$B26 -> 177.6 | I26: =$B$19*$B26 -> 131.275 | J26: =$B$19*$B26 -> 131.275 | K26: =$B$19*$B26 -> 131.275 | L26: =$B$19*$B26 -> 131.275 | M26: =$B$19*$B26 -> 131.275 | N26: =$B$19*$B26 -> 131.275 | O26: =SUM(C26:N26) -> 1853.25
C27: =SUM(C21:C26) -> 1776 | D27: =SUM(D21:D26) -> 1776 | E27: =SUM(E21:E26) -> 1776 | F27: =SUM(F21:F26) -> 1776 | G27: =SUM(G21:G26) -> 1776 | H27: =SUM(H21:H26) -> 1776 | I27: =SUM(I21:I26) -> 1312.75 | J27: =SUM(J21:J26) -> 1312.75 | ... O27: =SUM(O21:O26) -> 18532.5 | S27: =490/2 -> 245 | T27: Backcharge to PSM - Artlist 50%
A29: Accountancy | B29: 1500
A30: Magazine | B30: =1/6 -> 0.16666667 | C30: =$B$29*$B30 -> 250 | D30: =$B$29*$B30 -> 250 | E30: =$B$29*$B30 -> 250 | F30: =$B$29*$B30 -> 250 | G30: =500*$B30 -> 83.333333 | H30: =500*$B30 -> 83.333333 | I30: =500*$B30 -> 83.333333 | J30: =500*$B30 -> 83.333333 | K30: =500*$B30 -> 83.333333 | L30: =500*$B30 -> 83.333333 | M30: =500*$B30 -> 83.333333 | N30: =500*$B30 -> 83.333333 | O30: =SUM(C30:N30) -> 1666.6667
A31: Youtube | B31: =1/6 -> 0.16666667 | C31: =$B$29*$B31 -> 250 | D31: =$B$29*$B31 -> 250 | E31: =$B$29*$B31 -> 250 | F31: =$B$29*$B31 -> 250 | G31: =500*$B31 -> 83.333333 | H31: =500*$B31 -> 83.333333 | I31: =500*$B31 -> 83.333333 | J31: =500*$B31 -> 83.333333 | K31: =500*$B31 -> 83.333333 | L31: =500*$B31 -> 83.333333 | M31: =500*$B31 -> 83.333333 | N31: =500*$B31 -> 83.333333 | O31: =SUM(C31:N31) -> 1666.6667
A32: Facebook | B32: =1/6 -> 0.16666667 | C32: =$B$29*$B32 -> 250 | D32: =$B$29*$B32 -> 250 | E32: =$B$29*$B32 -> 250 | F32: =$B$29*$B32 -> 250 | G32: =500*$B32 -> 83.333333 | H32: =500*$B32 -> 83.333333 | I32: =500*$B32 -> 83.333333 | J32: =500*$B32 -> 83.333333 | K32: =500*$B32 -> 83.333333 | L32: =500*$B32 -> 83.333333 | M32: =500*$B32 -> 83.333333 | N32: =500*$B32 -> 83.333333 | O32: =SUM(C32:N32) -> 1666.6667
A33: Instagram | B33: =1/6 -> 0.16666667 | C33: =$B$29*$B33 -> 250 | D33: =$B$29*$B33 -> 250 | E33: =$B$29*$B33 -> 250 | F33: =$B$29*$B33 -> 250 | G33: =500*$B33 -> 83.333333 | H33: =500*$B33 -> 83.333333 | I33: =500*$B33 -> 83.333333 | J33: =500*$B33 -> 83.333333 | K33: =500*$B33 -> 83.333333 | L33: =500*$B33 -> 83.333333 | M33: =500*$B33 -> 83.333333 | N33: =500*$B33 -> 83.333333 | O33: =SUM(C33:N33) -> 1666.6667
A34: TikTok | B34: =1/6 -> 0.16666667 | C34: =$B$29*$B34 -> 250 | D34: =$B$29*$B34 -> 250 | E34: =$B$29*$B34 -> 250 | F34: =$B$29*$B34 -> 250 | G34: =500*$B34 -> 83.333333 | H34: =500*$B34 -> 83.333333 | I34: =500*$B34 -> 83.333333 | J34: =500*$B34 -> 83.333333 | K34: =500*$B34 -> 83.333333 | L34: =500*$B34 -> 83.333333 | M34: =500*$B34 -> 83.333333 | N34: =500*$B34 -> 83.333333 | O34: =SUM(C34:N34) -> 1666.6667
A35: X | B35: =1/6 -> 0.16666667 | C35: =$B$29*$B35 -> 250 | D35: =$B$29*$B35 -> 250 | E35: =$B$29*$B35 -> 250 | F35: =$B$29*$B35 -> 250 | G35: =500*$B35 -> 83.333333 | H35: =500*$B35 -> 83.333333 | I35: =500*$B35 -> 83.333333 | J35: =500*$B35 -> 83.333333 | K35: =500*$B35 -> 83.333333 | L35: =500*$B35 -> 83.333333 | M35: =500*$B35 -> 83.333333 | N35: =500*$B35 -> 83.333333 | O35: =SUM(C35:N35) -> 1666.6667
C36: =SUM(C30:C35) -> 1500 | D36: =SUM(D30:D35) -> 1500 | E36: =SUM(E30:E35) -> 1500 | F36: =SUM(F30:F35) -> 1500 | G36: =SUM(G30:G35) -> 500 | H36: =SUM(H30:H35) -> 500 | I36: =SUM(I30:I35) -> 500 | J36: =SUM(J30:J35) -> 500 | ... O36: =SUM(O30:O35) -> 10000
